Workbook

Sheet Salespeople
A1: SalespersonID | B1: Salesperson | C1: Segment | D1: PrimarySpecialism | E1: Region | F1: Seniority
A2: SP001 | B2: Alice Brown | C2: Enterprise | D2: Cloud & IT | E2: London | F2: Senior
A3: SP002 | B3: Ben Carter | C3: Enterprise | D3: Cyber Security | E3: London | F3: Senior
A4: SP003 | B4: Chloe Singh | C4: Mid-Market | D4: Modern Workplace | E4: South | F4: Senior
A5: SP004 | B5: Daniel Wilson | C5: Mid-Market | D5: Connectivity | E5: South | F5: Senior
A6: SP005 | B6: Emma Patel | C6: SMB | D6: IT Support | E6: South | F6: Mid
A7: SP006 | B7: Farhan Khan | C7: SMB | D7: Hosted Telephony | E7: London | F7: Mid
A8: SP007 | B8: Grace Taylor | C8: Mid-Market | D8: Cyber Security | E8: Midlands | F8: Mid
A9: SP008 | B9: Harry Evans | C9: Enterprise | D9: Connectivity | E9: Midlands | F9: Mid
A10: SP009 | B10: Isla Ahmed | C10: SMB | D10: Cloud & IT | E10: North | F10: Junior
A11: SP010 | B11: Jack Thomas | C11: SMB | D11: IT Support | E11: North | F11: Junior

Sheet Customers
A1: CustomerID | B1: CustomerName | C1: Segment | D1: Region | E1: CustomerSince | F1: ExistingCustomer
A2: CUST0001 | B2: Customer 0001 | C2: SMB | D2: South | E2: 45986 | F2: 0
A3: CUST0002 | B3: Customer 0002 | C3: Enterprise | D3: Midlands | E3: 45435 | F3: 0
A4: CUST0003 | B4: Customer 0003 | C4: Mid-Market | D4: North | E4: 45664 | F4: 1
A5: CUST0004 | B5: Customer 0004 | C5: Mid-Market | D5: London | E5: 44904 | F5: 0
A6: CUST0005 | B6: Customer 0005 | C6: SMB | D6: Midlands | E6: 45100 | F6: 1
A7: CUST0006 | B7: Customer 0006 | C7: SMB | D7: South | E7: 43728 | F7: 0
A8: CUST0007 | B8: Customer 0007 | C8: SMB | D8: London | E8: 45253 | F8: 1
A9: CUST0008 | B9: Customer 0008 | C9: Enterprise | D9: London | E9: 45657 | F9: 1
A10: CUST0009 | B10: Customer 0009 | C10: Mid-Market | D10: London | E10: 45859 | F10: 1
A11: CUST0010 | B11: Customer 0010 | C11: Mid-Market | D11: Midlands | E11: 44089 | F11: 1
A12: CUST0011 | B12: Customer 0011 | C12: SMB | D12: South | E12: 44482 | F12: 0
A13: CUST0012 | B13: Customer 0012 | C13: Enterprise | D13: London | E13: 44346 | F13: 1
... A121: CUST0120 | B121: Customer 0120 | C121: Mid-Market | D121: Midlands | E121: 44150 | F121: 1

Sheet CustomerProducts
A1: CustomerID | B1: Product | C1: MonthlyRevenue | D1: Active
A2: CUST0001 | B2: Connectivity | C2: 8152.21 | D2: 1
A3: CUST0002 | B3: Modern Workplace | C3: 765.32 | D3: 1
A4: CUST0002 | B4: IT Support | C4: 8639.31 | D4: 1
A5: CUST0003 | B5: IT Support | C5: 4497.93 | D5: 1
A6: CUST0003 | B6: Hosted Telephony | C6: 4589.32 | D6: 1
A7: CUST0003 | B7: Cyber Security | C7: 1024.57 | D7: 1
A8: CUST0004 | B8: Modern Workplace | C8: 6845.66 | D8: 1
A9: CUST0005 | B9: Cyber Security | C9: 8964.6 | D9: 1
A10: CUST0005 | B10: Telco Support | C10: 786.08 | D10: 1
A11: CUST0005 | B11: Connectivity | C11: 6712.21 | D11: 1
A12: CUST0006 | B12: Connectivity | C12: 7581.59 | D12: 1
A13: CUST0007 | B13: Cyber Security | C13: 7450.18 | D13: 1
... A238: CUST0120 | B238: IT Support | C238: 1220.76 | D238: 1

Sheet Activities
A1: SalespersonID | B1: ActivityDate | C1: ActivityType | D1: ActivityPurpose | E1: DurationMinutes
A2: SP001 | B2: 45845 | C2: Email | D2: New Business | E2: 17
A3: SP001 | B3: 45664 | C3: Email | D3: New Business | E3: 14
A4: SP001 | B4: 45790 | C4: Reachout | D4: Upsell | E4: 5
A5: SP001 | B5: 45892 | C5: Call | D5: Cross-sell | E5: 15
A6: SP001 | B6: 45702 | C6: Proposal | D6: Upsell | E6: 7
A7: SP001 | B7: 45971 | C7: Proposal | D7: New Business | E7: 10
A8: SP001 | B8: 45906 | C8: Reachout | D8: New Business | E8: 12
A9: SP001 | B9: 45688 | C9: Meeting | D9: Cross-sell | E9: 63
A10: SP001 | B10: 45680 | C10: Call | D10: New Business | E10: 16
A11: SP001 | B11: 45817 | C11: Call | D11: Cross-sell | E11: 8
A12: SP001 | B12: 46020 | C12: Call | D12: Upsell | E12: 29
A13: SP001 | B13: 45815 | C13: Call | D13: New Business | E13: 18
... A4192: SP010 | B4192: 46005 | C4192: Reachout | D4192: Retention | E4192: 7

Sheet Opportunities
A1: OpportunityID | B1: CustomerID | C1: SalespersonID | D1: CreatedDate | E1: CloseDate | F1: Product | G1: OpportunityType | H1: Stage | I1: PipelineValue | J1: ExpectedGrossProfit | K1: SalesCycleDays | L1: DataOrigin | M1: ExpectedCloseDate | N1: PipelineStage | O1: WinProbability | P1: ForecastCategory | Q1: LastActivityDate | R1: NextStep | S1: NextStepDueDate | T1: DaysInStage | U1: PipelineRisk
A2: OPP0094 | B2: CUST0034 | C2: SP004 | D2: 45659 | E2: 45692 | F2: Connectivity | G2: Cross-sell | H2: Won | I2: 1788.66 | J2: 726.06 | K2: 33 | L2: Original Workbook | M2: 45692 | N2: Historical | O2: 1 | P2: Historical | R2: Historical record | T2: 0 | U2: Historical
A3: OPP0003 | B3: CUST0119 | C3: SP002 | D3: 45660 | E3: 45777 | F3: Telco Support | G3: Cross-sell | H3: Open | I3: 3696.02 | J3: 1951 | K3: 117 | L3: Original Workbook | M3: 45777 | N3: Historical | O3: 0 | P3: Historical | R3: Historical record | T3: 0 | U3: Historical
A4: OPP0126 | B4: CUST0080 | C4: SP009 | D4: 45660 | E4: 45786 | F4: Connectivity | G4: Cross-sell | H4: Lost | I4: 2830.69 | J4: 939.53 | K4: 126 | L4: Original Workbook | M4: 45786 | N4: Historical | O4: 0 | P4: Historical | R4: Historical record | T4: 0 | U4: Historical
A5: OPP0110 | B5: CUST0076 | C5: SP005 | D5: 45661 | E5: 45678 | F5: Telco Support | G5: Cross-sell | H5: Open | I5: 3584.49 | J5: 1759.62 | K5: 17 | L5: Original Workbook | M5: 45678 | N5: Historical | O5: 0 | P5: Historical | R5: Historical record | T5: 0 | U5: Historical
A6: OPP0164 | B6: CUST0007 | C6: SP008 | D6: 45661 | E6: 45777 | F6: Cloud IT | G6: Renewal | H6: Won | I6: 6468.07 | J6: 2325.43 | K6: 116 | L6: Original Workbook | M6: 45777 | N6: Historical | O6: 1 | P6: Historical | R6: Historical record | T6: 0 | U6: Historical
A7: OPP0313 | B7: CUST0056 | C7: SP009 | D7: 45661 | E7: 45749 | F7: Cloud IT | G7: Cross-sell | H7: Open | I7: 8200.11 | J7: 4264.98 | K7: 88 | L7: Original Workbook | M7: 45749 | N7: Historical | O7: 0 | P7: Historical | R7: Historical record | T7: 0 | U7: Historical
A8: OPP0052 | B8: CUST0077 | C8: SP010 | D8: 45663 | E8: 45752 | F8: Hosted Telephony | G8: Renewal | H8: Won | I8: 3726.06 | J8: 1361.09 | K8: 89 | L8: Original Workbook | M8: 45752 | N8: Historical | O8: 1 | P8: Historical | R8: Historical record | T8: 0 | U8: Historical
A9: OPP0028 | B9: CUST0057 | C9: SP004 | D9: 45664 | E9: 45791 | F9: IT Support | G9: Cross-sell | H9: Won | I9: 696.87 | J9: 240.87 | K9: 127 | L9: Original Workbook | M9: 45791 | N9: Historical | O9: 1 | P9: Historical | R9: Historical record | T9: 0 | U9: Historical
A10: OPP0270 | B10: CUST0090 | C10: SP002 | D10: 45670 | E10: 45795 | F10: Hosted Telephony | G10: Renewal | H10: Lost | I10: 2610.66 | J10: 912.95 | K10: 125 | L10: Original Workbook | M10: 45795 | N10: Historical | O10: 0 | P10: Historical | R10: Historical record | T10: 0 | U10: Historical
A11: OPP0033 | B11: CUST0065 | C11: SP006 | D11: 45672 | E11: 45689 | F11: Cloud IT | G11: Cross-sell | H11: Lost | I11: 2041.86 | J11: 866.84 | K11: 17 | L11: Original Workbook | M11: 45689 | N11: Historical | O11: 0 | P11: Historical | R11: Historical record | T11: 0 | U11: Historical
A12: OPP0113 | B12: CUST0057 | C12: SP004 | D12: 45672 | E12: 45800 | F12: Modern Workplace | G12: New Customer | H12: Open | I12: 7083.03 | J12: 3848.21 | K12: 128 | L12: Original Workbook | M12: 45800 | N12: Historical | O12: 0 | P12: Historical | R12: Historical record | T12: 0 | U12: Historical
A13: OPP0196 | B13: CUST0007 | C13: SP010 | D13: 45672 | E13: 45732 | F13: Cloud IT | G13: New Customer | H13: Lost | I13: 10581.02 | J13: 4655.49 | K13: 60 | L13: Original Workbook | M13: 45732 | N13: Historical | O13: 0 | P13: Historical | R13: Historical record | T13: 0 | U13: Historical
... A321: OPP0292 | B321: CUST0098 | C321: SP002 | D321: 45991 | E321: 46096 | F321: Hosted Telephony | G321: Renewal | H321: Won | I321: 13005.18 | J321: 5937.21 | K321: 105 | L321: Original Workbook | M321: 46096 | N321: Historical | O321: 1 | P321: Historical | R321: Historical record | T321: 0 | U321: Historical
A322: OPP0347 | B322: CUST0010 | C322: SP007 | D322: 46027 | E322: 46129 | F322: Hosted Telephony | G322: Upsell | H322: Lost | I322: 50726.41 | J322: 21183.17 | K322: 102 | L322: Synthetic Current Year | M322: 46129 | N322: Lost | O322: 0 | P322: Closed | Q322: 46157 | R322: Closed opportunity review | T322: 0 | U322: Low
A323: OPP0380 | B323: CUST0008 | C323: SP010 | D323: 46028 | F323: Telco Support | G323: New Customer | H323: Open | I323: 80209.03 | J323: 27174.92 | K323: 221 | L323: Synthetic Current Year | M323: 46340 | N323: Discovery | O323: 0.115 | P323: Pipeline | Q323: 46074 | R323: Confirm business outcomes and executive sponsor | S323: 46265 | T323: 24 | U323: High
A324: OPP0464 | B324: CUST0075 | C324: SP004 | D324: 46028 | E324: 46130 | F324: Cyber Security | G324: Upsell | H324: Won | I324: 85064.4 | J324: 22989.02 | K324: 102 | L324: Synthetic Current Year | M324: 46130 | N324: Won | O324: 1 | P324: Closed | Q324: 46067 | R324: Closed opportunity review | T324: 0 | U324: Low
A325: OPP0374 | B325: CUST0068 | C325: SP004 | D325: 46029 | F325: Hosted Telephony | G325: Cross-sell | H325: Open | I325: 54757.36 | J325: 19773.51 | K325: 220 | L325: Synthetic Current Year | M325: 46274 | N325: Negotiation | O325: 0.745 | P325: Best Case | Q325: 46082 | R325: Resolve commercial and procurement actions | S325: 46260 | T325: 69 | U325: High
A326: OPP0405 | B326: CUST0012 | C326: SP005 | D326: 46029 | E326: 46053 | F326: Telco Support | G326: New Customer | H326: Won | I326: 29349.88 | J326: 9547.68 | K326: 24 | L326: Synthetic Current Year | M326: 46053 | N326: Won | O326: 1 | P326: Closed | Q326: 46210 | R326: Closed opportunity review | T326: 0 | U326: Low
A327: OPP0454 | B327: CUST0036 | C327: SP004 | D327: 46029 | F327: Cyber Security | G327: Cross-sell | H327: Open | I327: 34131.35 | J327: 11679.43 | K327: 220 | L327: Synthetic Current Year | M327: 46318 | N327: Negotiation | O327: 0.753 | P327: Best Case | Q327: 46226 | R327: Resolve commercial and procurement actions | S327: 46252 | T327: 56 | U327: High
A328: OPP0438 | B328: CUST0079 | C328: SP008 | D328: 46034 | E328: 46149 | F328: Cyber Security | G328: New Customer | H328: Won | I328: 32682.42 | J328: 9910.78 | K328: 115 | L328: Synthetic Current Year | M328: 46149 | N328: Won | O328: 1 | P328: Closed | Q328: 46227 | R328: Closed opportunity review | T328: 0 | U328: Low
A329: OPP0325 | B329: CUST0061 | C329: SP005 | D329: 46035 | F329: IT Support | G329: New Customer | H329: Open | I329: 24312.36 | J329: 10661.43 | K329: 214 | L329: Synthetic Current Year | M329: 46356 | N329: Qualification | O329: 0.296 | P329: Pipeline | Q329: 46167 | R329: Validate budget, authority, need, and timeline | S329: 46265 | T329: 48 | U329: High
A330: OPP0337 | B330: CUST0119 | C330: SP007 | D330: 46035 | F330: Cyber Security | G330: New Customer | H330: Open | I330: 18967.95 | J330: 8029.31 | K330: 214 | L330: Synthetic Current Year | M330: 46388 | N330: Negotiation | O330: 0.776 | P330: Best Case | Q330: 46236 | R330: Resolve commercial and procurement actions | S330: 46253 | T330: 55 | U330: Medium
A331: OPP0420 | B331: CUST0039 | C331: SP010 | D331: 46035 | E331: 46130 | F331: Connectivity | G331: Cross-sell | H331: Won | I331: 50601.39 | J331: 20081.17 | K331: 95 | L331: Synthetic Current Year | M331: 46130 | N331: Won | O331: 1 | P331: Closed | Q331: 46135 | R331: Closed opportunity review | T331: 0 | U331: Low
A332: OPP0421 | B332: CUST0043 | C332: SP001 | D332: 46035 | E332: 46089 | F332: Telco Support | G332: Cross-sell | H332: Won | I332: 44405.4 | J332: 18634.27 | K332: 54 | L332: Synthetic Current Year | M332: 46089 | N332: Won | O332: 1 | P332: Closed | Q332: 46061 | R332: Closed opportunity review | T332: 0 | U332: Low
A333: OPP0476 | B333: CUST0042 | C333: SP006 | D333: 46035 | F333: Hosted Telephony | G333: Cross-sell | H333: Open | I333: 25965.51 | J333: 8749 | K333: 214 | L333: Synthetic Current Year | M333: 46310 | N333: Solution Design | O333: 0.485 | P333: Pipeline | Q333: 46065 | R333: Complete technical scope and solution workshop | S333: 46262 | T333: 51 | U333: High
A334: OPP0412 | B334: CUST0022 | C334: SP002 | D334: 46036 | E334: 46093 | F334: Connectivity | G334: Cross-sell | H334: Won | I334: 25175.44 | J334: 7841.58 | K334: 57 | L334: Synthetic Current Year | M334: 46093 | N334: Won | O334: 1 | P334: Closed | Q334: 46162 | R334: Closed opportunity review | T334: 0 | U334: Low
A335: OPP0470 | B335: CUST0054 | C335: SP010 | D335: 46037 | E335: 46127 | F335: Cloud IT | G335: Cross-sell | H335: Won | I335: 40999.2 | J335: 18292.96 | K335: 90 | L335: Synthetic Current Year | M335: 46127 | N335: Won | O335: 1 | P335: Closed | Q335: 46093 | R335: Closed opportunity review | T335: 0 | U335: Low
A336: OPP0354 | B336: CUST0037 | C336: SP004 | D336: 46038 | F336: Modern Workplace | G336: Upsell | H336: Open | I336: 38192.01 | J336: 10378.23 | K336: 211 | L336: Synthetic Current Year | M336: 46267 | N336: Proposal | O336: 0.625 | P336: Best Case | Q336: 46180 | R336: Review proposal and commercial assumptions | S336: 46261 | T336: 20 | U336: High
A337: OPP0366 | B337: CUST0115 | C337: SP006 | D337: 46041 | F337: Cyber Security | G337: Cross-sell | H337: Open | I337: 21413.75 | J337: 9362.47 | K337: 208 | L337: Synthetic Current Year | M337: 46309 | N337: Proposal | O337: 0.656 | P337: Best Case | Q337: 46089 | R337: Review proposal and commercial assumptions | S337: 46264 | T337: 33 | U337: High
A338: OPP0389 | B338: CUST0077 | C338: SP009 | D338: 46041 | E338: 46149 | F338: Cyber Security | G338: Upsell | H338: Lost | I338: 22658.52 | J338: 8192.75 | K338: 108 | L338: Synthetic Current Year | M338: 46149 | N338: Lost | O338: 0 | P338: Closed | Q338: 46151 | R338: Closed opportunity review | T338: 0 | U338: Low
A339: OPP0407 | B339: CUST0100 | C339: SP007 | D339: 46042 | F339: Cyber Security | G339: Cross-sell | H339: Open | I339: 56100.81 | J339: 19798.25 | K339: 207 | L339: Synthetic Current Year | M339: 46334 | N339: Verbal Commit | O339: 0.855 | P339: Commit | Q339: 46177 | R339: Confirm signature and implementation handover date | S339: 46252 | T339: 7 | U339: High
A340: OPP0426 | B340: CUST0120 | C340: SP006 | D340: 46043 | F340: Connectivity | G340: Cross-sell | H340: Open | I340: 83943.13 | J340: 38907.29 | K340: 206 | L340: Synthetic Current Year | M340: 46379 | N340: Qualification | O340: 0.309 | P340: Pipeline | Q340: 46193 | R340: Validate budget, authority, need, and timeline | S340: 46253 | T340: 37 | U340: High
A341: OPP0353 | B341: CUST0114 | C341: SP003 | D341: 46044 | F341: Hosted Telephony | G341: New Customer | H341: Open | I341: 17862.74 | J341: 5431.15 | K341: 205 | L341: Synthetic Current Year | M341: 46354 | N341: Verbal Commit | O341: 0.857 | P341: Commit | Q341: 46215 | R341: Confirm signature and implementation handover date | S341: 46253 | T341: 65 | U341: High
A342: OPP0378 | B342: CUST0071 | C342: SP008 | D342: 46048 | E342: 46140 | F342: Modern Workplace | G342: New Customer | H342: Won | I342: 26073.3 | J342: 11372.91 | K342: 92 | L342: Synthetic Current Year | M342: 46140 | N342: Won | O342: 1 | P342: Closed | Q342: 46075 | R342: Closed opportunity review | T342: 0 | U342: Low
A343: OPP0452 | B343: CUST0013 | C343: SP002 | D343: 46048 | F343: Cloud IT | G343: New Customer | H343: Open | I343: 21391.59 | J343: 9944.3 | K343: 201 | L343: Synthetic Current Year | M343: 46298 | N343: Negotiation | O343: 0.803 | P343: Best Case | Q343: 46053 | R343: Resolve commercial and procurement actions | S343: 46257 | T343: 80 | U343: High
A344: OPP0460 | B344: CUST0023 | C344: SP010 | D344: 46048 | E344: 46131 | F344: Hosted Telephony | G344: Upsell | H344: Lost | I344: 35234.04 | J344: 15035.53 | K344: 83 | L344: Synthetic Current Year | M344: 46131 | N344: Lost | O344: 0 | P344: Closed | Q344: 46198 | R344: Closed opportunity review | T344: 0 | U344: Low
A345: OPP0463 | B345: CUST0090 | C345: SP003 | D345: 46048 | F345: IT Support | G345: New Customer | H345: Open | I345: 12000 | J345: 3639.75 | K345: 201 | L345: Synthetic Current Year | M345: 46335 | N345: Verbal Commit | O345: 0.851 | P345: Commit | Q345: 46174 | R345: Confirm signature and implementation handover date | S345: 46255 | T345: 79 | U345: High
A346: OPP0408 | B346: CUST0002 | C346: SP008 | D346: 46049 | F346: Connectivity | G346: Upsell | H346: Open | I346: 38040.49 | J346: 15740.63 | K346: 200 | L346: Synthetic Current Year | M346: 46389 | N346: Solution Design | O346: 0.451 | P346: Pipeline | Q346: 46147 | R346: Complete technical scope and solution workshop | S346: 46257 | T346: 36 | U346: High
A347: OPP0376 | B347: CUST0061 | C347: SP006 | D347: 46050 | E347: 46107 | F347: IT Support | G347: New Customer | H347: Lost | I347: 13593.44 | J347: 4353.55 | K347: 57 | L347: Synthetic Current Year | M347: 46107 | N347: Lost | O347: 0 | P347: Closed | Q347: 46182 | R347: Closed opportunity review | T347: 0 | U347: Low
A348: OPP0410 | B348: CUST0060 | C348: SP010 | D348: 46050 | F348: Hosted Telephony | G348: Upsell | H348: Open | I348: 35849.05 | J348: 15574.26 | K348: 199 | L348: Synthetic Current Year | M348: 46397 | N348: Qualification | O348: 0.241 | P348: Pipeline | Q348: 46170 | R348: Validate budget, authority, need, and timeline | S348: 46255 | T348: 38 | U348: High
A349: OPP0327 | B349: CUST0066 | C349: SP007 | D349: 46051 | F349: Telco Support | G349: New Customer | H349: Open | I349: 18325.2 | J349: 5005.92 | K349: 198 | L349: Synthetic Current Year | M349: 46298 | N349: Solution Design | O349: 0.49 | P349: Pipeline | Q349: 46098 | R349: Complete technical scope and solution workshop | S349: 46251 | T349: 77 | U349: High
A350: OPP0477 | B350: CUST0120 | C350: SP007 | D350: 46051 | F350: Cloud IT | G350: Cross-sell | H350: Open | I350: 14690.65 | J350: 6796.07 | K350: 198 | L350: Synthetic Current Year | M350: 46387 | N350: Solution Design | O350: 0.446 | P350: Pipeline | Q350: 46116 | R350: Complete technical scope and solution workshop | S350: 46255 | T350: 82 | U350: High
A351: OPP0480 | B351: CUST0089 | C351: SP010 | D351: 46051 | F351: Connectivity | G351: Cross-sell | H351: Open | I351: 43651.47 | J351: 14887.5 | K351: 198 | L351: Synthetic Current Year | M351: 46353 | N351: Verbal Commit | O351: 0.889 | P351: Commit | Q351: 46212 | R351: Confirm signature and implementation handover date | S351: 46261 | T351: 8 | U351: High
A352: OPP0361 | B352: CUST0095 | C352: SP001 | D352: 46052 | F352: Cloud IT | G352: Upsell | H352: Open | I352: 33356.24 | J352: 11418.96 | K352: 197 | L352: Synthetic Current Year | M352: 46273 | N352: Negotiation | O352: 0.74 | P352: Best Case | Q352: 46101 | R352: Resolve commercial and procurement actions | S352: 46266 | T352: 21 | U352: High
A353: OPP0488 | B353: CUST0050 | C353: SP008 | D353: 46052 | E353: 46105 | F353: Telco Support | G353: Cross-sell | H353: Won | I353: 37928.79 | J353: 17146.31 | K353: 53 | L353: Synthetic Current Year | M353: 46105 | N353: Won | O353: 1 | P353: Closed | Q353: 46119 | R353: Closed opportunity review | T353: 0 | U353: Low
A354: OPP0373 | B354: CUST0045 | C354: SP003 | D354: 46055 | E354: 46099 | F354: Connectivity | G354: Cross-sell | H354: Won | I354: 40486.07 | J354: 14942.38 | K354: 44 | L354: Synthetic Current Year | M354: 46099 | N354: Won | O354: 1 | P354: Closed | Q354: 46197 | R354: Closed opportunity review | T354: 0 | U354: Low
A355: OPP0397 | B355: CUST0014 | C355: SP007 | D355: 46055 | F355: Telco Support | G355: New Customer | H355: Open | I355: 19474.61 | J355: 6338.81 | K355: 194 | L355: Synthetic Current Year | M355: 46288 | N355: Negotiation | O355: 0.722 | P355: Best Case | Q355: 46066 | R355: Resolve commercial and procurement actions | S355: 46254 | T355: 45 | U355: High
A356: OPP0428 | B356: CUST0107 | C356: SP008 | D356: 46055 | F356: Hosted Telephony | G356: Upsell | H356: Open | I356: 81161.04 | J356: 36169.43 | K356: 194 | L356: Synthetic Current Year | M356: 46329 | N356: Solution Design | O356: 0.426 | P356: Pipeline | Q356: 46056 | R356: Complete technical scope and solution workshop | S356: 46259 | T356: 53 | U356: High
A357: OPP0370 | B357: CUST0099 | C357: SP010 | D357: 46056 | E357: 46103 | F357: IT Support | G357: Cross-sell | H357: Won | I357: 12510.81 | J357: 4975.38 | K357: 47 | L357: Synthetic Current Year | M357: 46103 | N357: Won | O357: 1 | P357: Closed | Q357: 46162 | R357: Closed opportunity review | T357: 0 | U357: Low
A358: OPP0422 | B358: CUST0090 | C358: SP002 | D358: 46057 | F358: Cyber Security | G358: Upsell | H358: Open | I358: 15933.57 | J358: 5028.43 | K358: 192 | L358: Synthetic Current Year | M358: 46258 | N358: Verbal Commit | O358: 0.95 | P358: Commit | Q358: 46097 | R358: Confirm signature and implementation handover date | S358: 46251 | T358: 20 | U358: High
A359: OPP0449 | B359: CUST0071 | C359: SP009 | D359: 46057 | F359: Hosted Telephony | G359: Upsell | H359: Open | I359: 83539.29 | J359: 39869.94 | K359: 192 | L359: Synthetic Current Year | M359: 46346 | N359: Solution Design | O359: 0.468 | P359: Pipeline | Q359: 46195 | R359: Complete technical scope and solution workshop | S359: 46258 | T359: 47 | U359: High
A360: OPP0442 | B360: CUST0055 | C360: SP002 | D360: 46059 | E360: 46144 | F360: Hosted Telephony | G360: New Customer | H360: Lost | I360: 69366.67 | J360: 25740.89 | K360: 85 | L360: Synthetic Current Year | M360: 46144 | N360: Lost | O360: 0 | P360: Closed | Q360: 46185 | R360: Closed opportunity review | T360: 0 | U360: Low
A361: OPP0398 | B361: CUST0113 | C361: SP008 | D361: 46062 | F361: Connectivity | G361: New Customer | H361: Open | I361: 84216.63 | J361: 27671.46 | K361: 187 | L361: Synthetic Current Year | M361: 46374 | N361: Solution Design | O361: 0.464 | P361: Pipeline | Q361: 46144 | R361: Complete technical scope and solution workshop | S361: 46260 | T361: 70 | U361: High
A362: OPP0450 | B362: CUST0047 | C362: SP010 | D362: 46063 | F362: Cyber Security | G362: New Customer | H362: Open | I362: 32442.67 | J362: 15455.38 | K362: 186 | L362: Synthetic Current Year | M362: 46278 | N362: Solution Design | O362: 0.441 | P362: Pipeline | Q362: 46190 | R362: Complete technical scope and solution workshop | S362: 46253 | T362: 52 | U362: High
A363: OPP0417 | B363: CUST0007 | C363: SP007 | D363: 46069 | F363: Telco Support | G363: New Customer | H363: Open | I363: 96611.06 | J363: 40834.44 | K363: 180 | L363: Synthetic Current Year | M363: 46260 | N363: Discovery | O363: 0.169 | P363: Pipeline | Q363: 46143 | R363: Confirm business outcomes and executive sponsor | S363: 46257 | T363: 77 | U363: High
A364: OPP0467 | B364: CUST0112 | C364: SP007 | D364: 46069 | E364: 46135 | F364: Modern Workplace | G364: New Customer | H364: Won | I364: 12000 | J364: 3777.22 | K364: 66 | L364: Synthetic Current Year | M364: 46135 | N364: Won | O364: 1 | P364: Closed | Q364: 46207 | R364: Closed opportunity review | T364: 0 | U364: Low
A365: OPP0324 | B365: CUST0063 | C365: SP004 | D365: 46070 | E365: 46138 | F365: Connectivity | G365: New Customer | H365: Won | I365: 34419.16 | J365: 12325.22 | K365: 68 | L365: Synthetic Current Year | M365: 46138 | N365: Won | O365: 1 | P365: Closed | Q365: 46160 | R365: Closed opportunity review | T365: 0 | U365: Low
A366: OPP0351 | B366: CUST0027 | C366: SP001 | D366: 46071 | E366: 46142 | F366: Hosted Telephony | G366: Cross-sell | H366: Won | I366: 145000 | J366: 57603.12 | K366: 71 | L366: Synthetic Current Year | M366: 46142 | N366: Won | O366: 1 | P366: Closed | Q366: 46166 | R366: Closed opportunity review | T366: 0 | U366: Low
A367: OPP0364 | B367: CUST0073 | C367: SP004 | D367: 46071 | E367: 46096 | F367: Connectivity | G367: Upsell | H367: Won | I367: 19976.92 | J367: 5625.65 | K367: 25 | L367: Synthetic Current Year | M367: 46096 | N367: Won | O367: 1 | P367: Closed | Q367: 46103 | R367: Closed opportunity review | T367: 0 | U367: Low
A368: OPP0447 | B368: CUST0002 | C368: SP007 | D368: 46071 | F368: IT Support | G368: New Customer | H368: Open | I368: 31653.38 | J368: 12958.31 | K368: 178 | L368: Synthetic Current Year | M368: 46288 | N368: Proposal | O368: 0.573 | P368: Best Case | Q368: 46207 | R368: Review proposal and commercial assumptions | S368: 46262 | T368: 18 | U368: High
A369: OPP0350 | B369: CUST0114 | C369: SP010 | D369: 46072 | F369: Cloud IT | G369: Upsell | H369: Open | I369: 18881.65 | J369: 9126.97 | K369: 177 | L369: Synthetic Current Year | M369: 46373 | N369: Solution Design | O369: 0.48 | P369: Pipeline | Q369: 46216 | R369: Complete technical scope and solution workshop | S369: 46265 | T369: 12 | U369: High
A370: OPP0346 | B370: CUST0086 | C370: SP006 | D370: 46073 | E370: 46180 | F370: Cloud IT | G370: Upsell | H370: Won | I370: 22754.58 | J370: 11066.76 | K370: 107 | L370: Synthetic Current Year | M370: 46180 | N370: Won | O370: 1 | P370: Closed | Q370: 46162 | R370: Closed opportunity review | T370: 0 | U370: Low
A371: OPP0395 | B371: CUST0062 | C371: SP005 | D371: 46073 | F371: Cyber Security | G371: New Customer | H371: Open | I371: 18159.61 | J371: 6122.04 | K371: 176 | L371: Synthetic Current Year | M371: 46269 | N371: Negotiation | O371: 0.762 | P371: Best Case | Q371: 46156 | R371: Resolve commercial and procurement actions | S371: 46263 | T371: 12 | U371: High
A372: OPP0406 | B372: CUST0051 | C372: SP006 | D372: 46076 | F372: Cloud IT | G372: New Customer | H372: Open | I372: 46151.34 | J372: 21670.13 | K372: 173 | L372: Synthetic Current Year | M372: 46342 | N372: Proposal | O372: 0.62 | P372: Best Case | Q372: 46214 | R372: Review proposal and commercial assumptions | S372: 46263 | T372: 58 | U372: High
A373: OPP0339 | B373: CUST0110 | C373: SP009 | D373: 46077 | E373: 46154 | F373: Cloud IT | G373: New Customer | H373: Won | I373: 27983.27 | J373: 10933.65 | K373: 77 | L373: Synthetic Current Year | M373: 46154 | N373: Won | O373: 1 | P373: Closed | Q373: 46082 | R373: Closed opportunity review | T373: 0 | U373: Low
A374: OPP0500 | B374: CUST0108 | C374: SP010 | D374: 46079 | F374: Modern Workplace | G374: Cross-sell | H374: Open | I374: 31499.42 | J374: 14762.66 | K374: 170 | L374: Synthetic Current Year | M374: 46290 | N374: Qualification | O374: 0.232 | P374: Pipeline | Q374: 46178 | R374: Validate budget, authority, need, and timeline | S374: 46256 | T374: 84 | U374: High
A375: OPP0330 | B375: CUST0113 | C375: SP010 | D375: 46080 | F375: Telco Support | G375: Cross-sell | H375: Open | I375: 33367.52 | J375: 14141.85 | K375: 169 | L375: Synthetic Current Year | M375: 46272 | N375: Qualification | O375: 0.273 | P375: Pipeline | Q375: 46109 | R375: Validate budget, authority, need, and timeline | S375: 46253 | T375: 13 | U375: High
A376: OPP0341 | B376: CUST0001 | C376: SP001 | D376: 46080 | F376: IT Support | G376: Cross-sell | H376: Open | I376: 20652.09 | J376: 5840.88 | K376: 169 | L376: Synthetic Current Year | M376: 46372 | N376: Negotiation | O376: 0.694 | P376: Best Case | Q376: 46206 | R376: Resolve commercial and procurement actions | S376: 46252 | T376: 35 | U376: High
A377: OPP0386 | B377: CUST0061 | C377: SP006 | D377: 46080 | F377: IT Support | G377: Upsell | H377: Open | I377: 12000 | J377: 5570.73 | K377: 169 | L377: Synthetic Current Year | M377: 46301 | N377: Solution Design | O377: 0.441 | P377: Pipeline | Q377: 46114 | R377: Complete technical scope and solution workshop | S377: 46251 | T377: 3 | U377: High
A378: OPP0344 | B378: CUST0018 | C378: SP004 | D378: 46083 | F378: Connectivity | G378: Cross-sell | H378: Open | I378: 39044.01 | J378: 18879.66 | K378: 166 | L378: Synthetic Current Year | M378: 46363 | N378: Qualification | O378: 0.292 | P378: Pipeline | Q378: 46191 | R378: Validate budget, authority, need, and timeline | S378: 46262 | T378: 67 | U378: High
A379: OPP0418 | B379: CUST0111 | C379: SP008 | D379: 46083 | E379: 46178 | F379: IT Support | G379: New Customer | H379: Lost | I379: 41084.07 | J379: 12188.28 | K379: 95 | L379: Synthetic Current Year | M379: 46178 | N379: Lost | O379: 0 | P379: Closed | Q379: 46174 | R379: Closed opportunity review | T379: 0 | U379: Low
A380: OPP0379 | B380: CUST0118 | C380: SP009 | D380: 46084 | F380: Cyber Security | G380: New Customer | H380: Open | I380: 88127.24 | J380: 29633.65 | K380: 165 | L380: Synthetic Current Year | M380: 46372 | N380: Discovery | O380: 0.134 | P380: Pipeline | Q380: 46133 | R380: Confirm business outcomes and executive sponsor | S380: 46264 | T380: 47 | U380: High
A381: OPP0394 | B381: CUST0011 | C381: SP004 | D381: 46084 | F381: Connectivity | G381: New Customer | H381: Open | I381: 23370.24 | J381: 7590.63 | K381: 165 | L381: Synthetic Current Year | M381: 46278 | N381: Proposal | O381: 0.634 | P381: Best Case | Q381: 46117 | R381: Review proposal and commercial assumptions | S381: 46256 | T381: 26 | U381: High
A382: OPP0321 | B382: CUST0070 | C382: SP001 | D382: 46086 | F382: Connectivity | G382: New Customer | H382: Open | I382: 48414.54 | J382: 21376.27 | K382: 163 | L382: Synthetic Current Year | M382: 46402 | N382: Discovery | O382: 0.09 | P382: Pipeline | Q382: 46213 | R382: Confirm business outcomes and executive sponsor | S382: 46263 | T382: 4 | U382: High
A383: OPP0338 | B383: CUST0107 | C383: SP008 | D383: 46087 | E383: 46156 | F383: Hosted Telephony | G383: Cross-sell | H383: Won | I383: 23101.71 | J383: 9201.18 | K383: 69 | L383: Synthetic Current Year | M383: 46156 | N383: Won | O383: 1 | P383: Closed | Q383: 46152 | R383: Closed opportunity review | T383: 0 | U383: Low
A384: OPP0448 | B384: CUST0030 | C384: SP008 | D384: 46087 | F384: Connectivity | G384: Cross-sell | H384: Open | I384: 25310.8 | J384: 10752.66 | K384: 162 | L384: Synthetic Current Year | M384: 46324 | N384: Qualification | O384: 0.284 | P384: Pipeline | Q384: 46164 | R384: Validate budget, authority, need, and timeline | S384: 46253 | T384: 78 | U384: High
A385: OPP0392 | B385: CUST0061 | C385: SP002 | D385: 46092 | E385: 46124 | F385: Cyber Security | G385: Cross-sell | H385: Won | I385: 48283.93 | J385: 15377.24 | K385: 32 | L385: Synthetic Current Year | M385: 46124 | N385: Won | O385: 1 | P385: Closed | Q385: 46097 | R385: Closed opportunity review | T385: 0 | U385: Low
A386: OPP0489 | B386: CUST0007 | C386: SP009 | D386: 46092 | F386: Cyber Security | G386: New Customer | H386: Open | I386: 73957.9 | J386: 31171.32 | K386: 157 | L386: Synthetic Current Year | M386: 46302 | N386: Proposal | O386: 0.665 | P386: Best Case | Q386: 46193 | R386: Review proposal and commercial assumptions | S386: 46265 | T386: 71 | U386: High
A387: OPP0471 | B387: CUST0059 | C387: SP001 | D387: 46093 | E387: 46150 | F387: Cyber Security | G387: Upsell | H387: Won | I387: 32627.25 | J387: 13505.15 | K387: 57 | L387: Synthetic Current Year | M387: 46150 | N387: Won | O387: 1 | P387: Closed | Q387: 46200 | R387: Closed opportunity review | T387: 0 | U387: Low
A388: OPP0495 | B388: CUST0019 | C388: SP005 | D388: 46093 | F388: Connectivity | G388: Upsell | H388: Open | I388: 50274.71 | J388: 18926.1 | K388: 156 | L388: Synthetic Current Year | M388: 46357 | N388: Qualification | O388: 0.266 | P388: Pipeline | Q388: 46170 | R388: Validate budget, authority, need, and timeline | S388: 46259 | T388: 5 | U388: High
A389: OPP0466 | B389: CUST0107 | C389: SP006 | D389: 46097 | E389: 46160 | F389: Modern Workplace | G389: New Customer | H389: Won | I389: 25852.89 | J389: 12536.61 | K389: 63 | L389: Synthetic Current Year | M389: 46160 | N389: Won | O389: 1 | P389: Closed | Q389: 46124 | R389: Closed opportunity review | T389: 0 | U389: Low
A390: OPP0409 | B390: CUST0112 | C390: SP009 | D390: 46100 | E390: 46213 | F390: Connectivity | G390: Cross-sell | H390: Won | I390: 22706.34 | J390: 10486.78 | K390: 113 | L390: Synthetic Current Year | M390: 46213 | N390: Won | O390: 1 | P390: Closed | Q390: 46179 | R390: Closed opportunity review | T390: 0 | U390: Low
A391: OPP0434 | B391: CUST0104 | C391: SP004 | D391: 46100 | F391: Hosted Telephony | G391: New Customer | H391: Open | I391: 48793.71 | J391: 17909.65 | K391: 149 | L391: Synthetic Current Year | M391: 46302 | N391: Negotiation | O391: 0.773 | P391: Best Case | Q391: 46199 | R391: Resolve commercial and procurement actions | S391: 46264 | T391: 50 | U391: High
A392: OPP0453 | B392: CUST0120 | C392: SP003 | D392: 46100 | F392: Cyber Security | G392: Cross-sell | H392: Open | I392: 51780.39 | J392: 21195.43 | K392: 149 | L392: Synthetic Current Year | M392: 46258 | N392: Proposal | O392: 0.644 | P392: Best Case | Q392: 46155 | R392: Review proposal and commercial assumptions | S392: 46256 | T392: 29 | U392: High
A393: OPP0481 | B393: CUST0068 | C393: SP001 | D393: 46100 | F393: IT Support | G393: New Customer | H393: Open | I393: 137101.89 | J393: 62865.52 | K393: 149 | L393: Synthetic Current Year | M393: 46268 | N393: Discovery | O393: 0.153 | P393: Pipeline | Q393: 46142 | R393: Confirm business outcomes and executive sponsor | S393: 46252 | T393: 61 | U393: High
A394: OPP0336 | B394: CUST0014 | C394: SP006 | D394: 46101 | F394: Hosted Telephony | G394: New Customer | H394: Open | I394: 26560.25 | J394: 10718.7 | K394: 148 | L394: Synthetic Current Year | M394: 46318 | N394: Discovery | O394: 0.05 | P394: Pipeline | Q394: 46194 | R394: Confirm business outcomes and executive sponsor | S394: 46258 | T394: 3 | U394: High
A395: OPP0388 | B395: CUST0052 | C395: SP008 | D395: 46101 | F395: Cyber Security | G395: Cross-sell | H395: Open | I395: 24263.34 | J395: 6779.05 | K395: 148 | L395: Synthetic Current Year | M395: 46340 | N395: Negotiation | O395: 0.824 | P395: Best Case | Q395: 46169 | R395: Resolve commercial and procurement actions | S395: 46258 | T395: 34 | U395: High
A396: OPP0358 | B396: CUST0005 | C396: SP008 | D396: 46104 | F396: Cyber Security | G396: Cross-sell | H396: Open | I396: 73789.31 | J396: 32147.78 | K396: 145 | L396: Synthetic Current Year | M396: 46396 | N396: Solution Design | O396: 0.446 | P396: Pipeline | Q396: 46126 | R396: Complete technical scope and solution workshop | S396: 46252 | T396: 49 | U396: High
A397: OPP0413 | B397: CUST0100 | C397: SP003 | D397: 46104 | F397: IT Support | G397: Cross-sell | H397: Open | I397: 36933.66 | J397: 17942.18 | K397: 145 | L397: Synthetic Current Year | M397: 46368 | N397: Solution Design | O397: 0.52 | P397: Pipeline | Q397: 46220 | R397: Complete technical scope and solution workshop | S397: 46255 | T397: 29 | U397: High
A398: OPP0416 | B398: CUST0032 | C398: SP006 | D398: 46106 | F398: Cyber Security | G398: Cross-sell | H398: Open | I398: 18284.5 | J398: 6951.95 | K398: 143 | L398: Synthetic Current Year | M398: 46373 | N398: Solution Design | O398: 0.444 | P398: Pipeline | Q398: 46131 | R398: Complete technical scope and solution workshop | S398: 46266 | T398: 57 | U398: High
A399: OPP0446 | B399: CUST0041 | C399: SP006 | D399: 46106 | F399: Hosted Telephony | G399: New Customer | H399: Open | I399: 25499.59 | J399: 9655.71 | K399: 143 | L399: Synthetic Current Year | M399: 46280 | N399: Negotiation | O399: 0.771 | P399: Best Case | Q399: 46119 | R399: Resolve commercial and procurement actions | S399: 46265 | T399: 69 | U399: High
A400: OPP0411 | B400: CUST0100 | C400: SP001 | D400: 46111 | F400: IT Support | G400: Upsell | H400: Open | I400: 13228.66 | J400: 3784.03 | K400: 138 | L400: Synthetic Current Year | M400: 46381 | N400: Discovery | O400: 0.082 | P400: Pipeline | Q400: 46224 | R400: Confirm business outcomes and executive sponsor | S400: 46251 | T400: 66 | U400: High
A401: OPP0431 | B401: CUST0020 | C401: SP001 | D401: 46111 | F401: Connectivity | G401: Upsell | H401: Open | I401: 73764.42 | J401: 28821.52 | K401: 138 | L401: Synthetic Current Year | M401: 46318 | N401: Proposal | O401: 0.595 | P401: Best Case | Q401: 46176 | R401: Review proposal and commercial assumptions | S401: 46266 | T401: 78 | U401: High
A402: OPP0352 | B402: CUST0041 | C402: SP002 | D402: 46112 | F402: Cloud IT | G402: New Customer | H402: Open | I402: 84684.21 | J402: 33416.49 | K402: 137 | L402: Synthetic Current Year | M402: 46293 | N402: Verbal Commit | O402: 0.887 | P402: Commit | Q402: 46214 | R402: Confirm signature and implementation handover date | S402: 46263 | T402: 19 | U402: High
... A404: OPP0362 | B404: CUST0019 | C404: SP002 | D404: 46114 | F404: IT Support | G404: Upsell | H404: Open | I404: 13666.24 | J404: 4881.19 | K404: 135 | L404: Synthetic Current Year | M404: 46259 | N404: Negotiation | O404: 0.737 | P404: Best Case | Q404: 46225 | R404: Resolve commercial and procurement actions | S404: 46258 | T404: 28 | U404: High
A405: OPP0371 | B405: CUST0047 | C405: SP001 | D405: 46115 | E405: 46224 | F405: Cloud IT | G405: New Customer | H405: Won | I405: 52780.29 | J405: 18029.24 | K405: 109 | L405: Synthetic Current Year | M405: 46224 | N405: Won | O405: 1 | P405: Closed | Q405: 46201 | R405: Closed opportunity review | T405: 0 | U405: Low
A406: OPP0423 | B406: CUST0014 | C406: SP003 | D406: 46118 | E406: 46162 | F406: Modern Workplace | G406: Upsell | H406: Lost | I406: 36612.88 | J406: 15953.07 | K406: 44 | L406: Synthetic Current Year | M406: 46162 | N406: Lost | O406: 0 | P406: Closed | Q406: 46199 | R406: Closed opportunity review | T406: 0 | U406: Low
A407: OPP0363 | B407: CUST0088 | C407: SP003 | D407: 46119 | F407: Cloud IT | G407: Upsell | H407: Open | I407: 47508.5 | J407: 21605.42 | K407: 130 | L407: Synthetic Current Year | M407: 46274 | N407: Verbal Commit | O407: 0.891 | P407: Commit | Q407: 46136 | R407: Confirm signature and implementation handover date | S407: 46265 | T407: 82 | U407: High
A408: OPP0484 | B408: CUST0018 | C408: SP004 | D408: 46120 | E408: 46187 | F408: Telco Support | G408: New Customer | H408: Lost | I408: 37710.34 | J408: 12833.39 | K408: 67 | L408: Synthetic Current Year | M408: 46187 | N408: Lost | O408: 0 | P408: Closed | Q408: 46133 | R408: Closed opportunity review | T408: 0 | U408: Low
...

Sheet SynergyReferrals
A1: ReferralID | B1: ReferralDate | C1: FromSalespersonID | D1: ToSalespersonID | E1: ProductArea | F1: ReferralType | G1: ReferralStatus
A2: REF0001 | B2: 45699 | C2: SP008 | D2: SP004 | E2: Cyber Security | F2: Expansion Opportunity | G2: Accepted
A3: REF0002 | B3: 45798 | C3: SP001 | D3: SP002 | E3: Modern Workplace | F3: Existing Customer | G3: Converted
A4: REF0003 | B4: 45731 | C4: SP001 | D4: SP003 | E4: Cloud IT | F4: Existing Customer | G4: Accepted
A5: REF0004 | B5: 45949 | C5: SP007 | D5: SP001 | E5: Cloud IT | F5: Expansion Opportunity | G5: Accepted
A6: REF0005 | B6: 45916 | C6: SP008 | D6: SP004 | E6: IT Support | F6: Warm Lead | G6: Converted
A7: REF0006 | B7: 45982 | C7: SP006 | D7: SP008 | E7: IT Support | F7: Expansion Opportunity | G7: Accepted
A8: REF0007 | B8: 45889 | C8: SP003 | D8: SP005 | E8: IT Support | F8: Expansion Opportunity | G8: Converted
A9: REF0008 | B9: 45795 | C9: SP009 | D9: SP001 | E9: Cyber Security | F9: Warm Lead | G9: Converted
A10: REF0009 | B10: 45732 | C10: SP004 | D10: SP006 | E10: Cloud IT | F10: Warm Lead | G10: Accepted
A11: REF0010 | B11: 45912 | C11: SP009 | D11: SP001 | E11: Cloud IT | F11: Expansion Opportunity | G11: Converted
A12: REF0011 | B12: 45989 | C12: SP001 | D12: SP003 | E12: IT Support | F12: Warm Lead | G12: Accepted
A13: REF0012 | B13: 45953 | C13: SP001 | D13: SP003 | E13: Modern Workplace | F13: Existing Customer | G13: Converted
... A121: REF0120 | B121: 45711 | C121: SP006 | D121: SP008 | E121: Telco Support | F121: Warm Lead | G121: Converted

Sheet SynergyMap
A1: FromSalespersonID | B1: ToSalespersonID | C1: SynergyType | D1: SynergyStrength
A2: SP001 | B2: SP002 | C2: Cloud & IT + Cyber Security | D2: 0.85
A3: SP001 | B3: SP003 | C3: Cloud & IT + Modern Workplace | D3: 0.75
A4: SP001 | B4: SP004 | C4: Cloud & IT + Connectivity | D4: 0.65
A5: SP002 | B5: SP003 | C5: Cyber Security + Modern Workplace | D5: 0.8
A6: SP002 | B6: SP007 | C6: Cyber Security + Cyber Security | D6: 0.7
A7: SP003 | B7: SP005 | C7: Modern Workplace + IT Support | D7: 0.75
A8: SP004 | B8: SP006 | C8: Connectivity + Hosted Telephony | D8: 0.9
A9: SP004 | B9: SP008 | C9: Connectivity + Connectivity | D9: 0.7
A10: SP005 | B10: SP006 | C10: IT Support + Hosted Telephony | D10: 0.65
A11: SP005 | B11: SP010 | C11: IT Support + IT Support | D11: 0.55
A12: SP006 | B12: SP008 | C12: Hosted Telephony + Connectivity | D12: 0.8
A13: SP007 | B13: SP001 | C13: Cyber Security + Cloud & IT | D13: 0.75
... A16: SP010 | B16: SP005 | C16: IT Support + IT Support | D16: 0.6

Sheet MonthlyPerformance
A1: Month | B1: SalespersonID | C1: CustomerReachouts | D1: Meetings | E1: OpportunitiesCreated | F1: OpportunitiesWon | G1: NewCustomers | H1: CrossSellOpportunities | I1: Revenue | J1: GrossProfit | K1: CrossSellRevenue | L1: TargetAttainment | M1: RetentionRate | N1: WinRate | O1: GrossMarginPct | P1: ReachoutsPerMeeting | Q1: MeetingsPerOpportunity | R1: ReachoutsPerOpportunity | S1: MeetingsPerWin | T1: RevenuePerMeeting | U1: GrossProfitPerMeeting | V1: RevenuePerOpportunity | W1: GrossProfitPerOpportunity | X1: WinsPer100Reachouts | Y1: CrossSellRevenuePct | Z1: CrossSellOpportunityRate | AA1: NewCustomersPerWin | AB1: GrossProfitPerReachout | AC1: DataOrigin
A2: 45658 | B2: SP001 | C2: 64 | D2: 18 | E2: 7 | F2: 2 | G2: 1 | H2: 3 | I2: 33703.35 | J2: 10586.22 | K2: 2620.29 | L2: 0.98 | M2: 0.82 | N2: 0.28571429 | AC2: Original Workbook
A3: 45658 | B3: SP002 | C3: 45 | D3: 25 | E3: 5 | F3: 2 | G3: 3 | H3: 1 | I3: 59156.62 | J3: 20482.38 | K3: 6041.66 | L3: 0.97 | M3: 0.74 | N3: 0.4 | AC3: Original Workbook
A4: 45658 | B4: SP003 | C4: 56 | D4: 12 | E4: 7 | F4: 3 | G4: 0 | H4: 0 | I4: 45363.19 | J4: 16396.76 | K4: 5143.43 | L4: 0.88 | M4: 0.93 | N4: 0.42857143 | AC4: Original Workbook
A5: 45658 | B5: SP004 | C5: 37 | D5: 22 | E5: 4 | F5: 2 | G5: 0 | H5: 4 | I5: 39873.12 | J5: 12545.78 | K5: 2227.07 | L5: 0.76 | M5: 0.74 | N5: 0.5 | AC5: Original Workbook
A6: 45658 | B6: SP005 | C6: 46 | D6: 11 | E6: 5 | F6: 2 | G6: 1 | H6: 3 | I6: 45876.88 | J6: 16744.16 | K6: 3982.78 | L6: 0.78 | M6: 0.62 | N6: 0.4 | AC6: Original Workbook
A7: 45658 | B7: SP006 | C7: 37 | D7: 11 | E7: 5 | F7: 2 | G7: 1 | H7: 1 | I7: 19918.1 | J7: 8335.88 | K7: 1043.22 | L7: 0.89 | M7: 0.97 | N7: 0.4 | AC7: Original Workbook
A8: 45658 | B8: SP007 | C8: 41 | D8: 11 | E8: 3 | F8: 0 | G8: 0 | H8: 2 | I8: 5876.93 | J8: 1663.44 | K8: 200.62 | L8: 1.12 | M8: 0.61 | N8: 0 | AC8: Original Workbook
A9: 45658 | B9: SP008 | C9: 36 | D9: 13 | E9: 3 | F9: 2 | G9: 1 | H9: 1 | I9: 28291.07 | J9: 7943.87 | K9: 2935.95 | L9: 0.9 | M9: 0.84 | N9: 0.66666667 | AC9: Original Workbook
A10: 45658 | B10: SP009 | C10: 47 | D10: 9 | E10: 5 | F10: 4 | G10: 0 | H10: 0 | I10: 35008.7 | J10: 10302.32 | K10: 3630.64 | L10: 0.89 | M10: 0.69 | N10: 0.8 | AC10: Original Workbook
A11: 45658 | B11: SP010 | C11: 25 | D11: 19 | E11: 5 | F11: 3 | G11: 0 | H11: 1 | I11: 27876.07 | J11: 9242.94 | K11: 987.89 | L11: 0.93 | M11: 1.05 | N11: 0.6 | AC11: Original Workbook
A12: 45689 | B12: SP001 | C12: 54 | D12: 14 | E12: 6 | F12: 3 | G12: 0 | H12: 3 | I12: 48034.46 | J12: 17072.97 | K12: 2146.66 | L12: 1.1 | M12: 0.75 | N12: 0.5 | AC12: Original Workbook
A13: 45689 | B13: SP002 | C13: 48 | D13: 18 | E13: 6 | F13: 3 | G13: 2 | H13: 1 | I13: 62337.2 | J13: 19516.81 | K13: 7424.06 | L13: 1.03 | M13: 1.01 | N13: 0.5 | AC13: Original Workbook
... A201: 46235 | B201: SP010 | C201: 15 | D201: 4 | E201: 2 | F201: 0 | G201: 0 | H201: 0 | I201: 0 | J201: 0 | K201: 0 | L201: 0 | M201: 0.47 | N201: 0 | AC201: Synthetic Current Year

Sheet Targets
A1: SalespersonID | B1: AnnualRevenueTarget | C1: AnnualNewCustomerTarget | D1: AnnualCrossSellTarget
A2: SP001 | B2: 550000 | C2: 20 | D2: 25
A3: SP002 | B3: 650000 | C3: 15 | D3: 20
A4: SP003 | B4: 450000 | C4: 15 | D4: 25
A5: SP004 | B5: 650000 | C5: 15 | D5: 25
A6: SP005 | B6: 650000 | C6: 10 | D6: 20
A7: SP006 | B7: 750000 | C7: 15 | D7: 15
A8: SP007 | B8: 650000 | C8: 20 | D8: 25
A9: SP008 | B9: 550000 | C9: 15 | D9: 30
A10: SP009 | B10: 550000 | C10: 15 | D10: 20
A11: SP010 | B11: 450000 | C11: 10 | D11: 25

Sheet FeatureDictionary
A1: Feature | B1: Category | C1: Definition | D1: WhyItMatters
A2: CustomerReachouts | B2: Activity | C2: Number of customer/prospect reachouts | D2: Activity level
A3: Meetings | B3: Activity | C3: Customer/prospect meetings | D3: Engagement quality/volume
A4: OpportunitiesCreated | B4: Pipeline | C4: New opportunities created | D4: Pipeline generation
A5: OpportunitiesWon | B5: Outcome | C5: Closed-won opportunities | D5: Conversion
A6: WinRate | B6: Outcome | C6: Won opportunities / opportunities | D6: Sales effectiveness
A7: Revenue | B7: Outcome | C7: Revenue generated | D7: Primary commercial outcome
A8: GrossProfit | B8: Outcome | C8: Gross profit generated | D8: Profitability
A9: NewCustomers | B9: Growth | C9: New customers acquired | D9: New logo acquisition
A10: CrossSellOpportunities | B10: Growth | C10: Cross-sell opportunities created | D10: Account expansion
A11: CrossSellRevenue | B11: Growth | C11: Revenue from cross-sell | D11: Account expansion
A12: RetentionRate | B12: Customer | C12: Customer retention measure | D12: Account health
... A56: AchievabilityScore | B56: Pipeline | C56: Coverage, weighted coverage, and YTD pace combined into a transparent 0-100 score | D56: Supports manager judgement about annual target risk

Sheet ExampleModelOutput
A1: SalespersonID | B1: Salesperson | C1: PerformanceScore | D1: PredictedRevenue | E1: BenchmarkRevenue | F1: PerformanceGap | G1: PrimaryGap | H1: RecommendedAction
A2: SP001 | B2: Alice Brown | C2: 91 | D2: 675000 | E2: 640000 | F2: 35000 | G2: Cross-sell + Cyber Security | H2: Increase cross-sell discovery across existing Cloud customers
A3: SP005 | B3: Emma Patel | C3: 73 | D3: 465000 | E3: 540000 | F3: -75000 | G3: Meetings + Opportunity Creation | H3: Increase qualified meetings and multi-service discovery
A4: SP009 | B4: Isla Ahmed | C4: 61 | D4: 320000 | E4: 455000 | F4: -135000 | G4: New Customers + Meetings | H4: Increase prospecting and partner/referral activity

Sheet ExistingCustomerBilling
A1: BillingID | B1: CustomerID | C1: BillingMonth | D1: ServiceCategory | E1: Service | F1: ContractID | G1: AccountOwnerID | H1: BillingType | I1: MRR | J1: OneOffCharges | K1: UsageCharges | L1: DiscountAmount | M1: TotalBilled | N1: GrossMarginPct | O1: GrossProfit | P1: BillingStatus | Q1: PaymentStatus | R1: IsRecurring | S1: ContractTermMonths | T1: RenewalDate | U1: BillingContractServiceKey | V1: ContractLinkStatus | W1: ContractLinkNote
A2: BILL00001 | B2: CUST0001 | C2: 45658 | D2: Support | E2: Telco Support | F2: CTR-0001-01 | G2: SP001 | H2: Recurring + Usage | I2: 406 | J2: 0 | K2: 24.63 | L2: 0 | M2: 430.63 | N2: 0.26 | O2: 111.96 | P2: Billed | Q2: Paid | R2: 1 | S2: 24 | T2: 46143 | U2: CUST0001|Telco Support | V2: Linked | W2: Billing row links to matching customer/service contract
A3: BILL00002 | B3: CUST0001 | C3: 45689 | D3: Support | E3: Telco Support | F3: CTR-0001-01 | G3: SP001 | H3: Recurring + Usage | I3: 406 | J3: 0 | K3: 21.68 | L3: 20.3 | M3: 407.38 | N3: 0.33 | O3: 134.44 | P3: Billed | Q3: Pending | R3: 1 | S3: 24 | T3: 46143 | U3: CUST0001|Telco Support | V3: Linked | W3: Billing row links to matching customer/service contract
A4: BILL00003 | B4: CUST0001 | C4: 45717 | D4: Support | E4: Telco Support | F4: CTR-0001-01 | G4: SP001 | H4: Recurring + Usage | I4: 406 | J4: 0 | K4: 24.53 | L4: 0 | M4: 430.53 | N4: 0.35 | O4: 150.69 | P4: Billed | Q4: Paid | R4: 1 | S4: 24 | T4: 46143 | U4: CUST0001|Telco Support | V4: Linked | W4: Billing row links to matching customer/service contract
A5: BILL00004 | B5: CUST0001 | C5: 45748 | D5: Support | E5: Telco Support | F5: CTR-0001-01 | G5: SP001 | H5: Recurring + Usage | I5: 406 | J5: 0 | K5: 9.24 | L5: 12.18 | M5: 403.06 | N5: 0.35 | O5: 141.07 | P5: Billed | Q5: Paid | R5: 1 | S5: 24 | T5: 46143 | U5: CUST0001|Telco Support | V5: Linked | W5: Billing row links to matching customer/service contract
A6: BILL00005 | B6: CUST0001 | C6: 45778 | D6: Support | E6: Telco Support | F6: CTR-0001-01 | G6: SP001 | H6: Recurring + Usage | I6: 406 | J6: 0 | K6: 17.24 | L6: 12.18 | M6: 411.06 | N6: 0.3 | O6: 123.32 | P6: Billed | Q6: Paid | R6: 1 | S6: 24 | T6: 46143 | U6: CUST0001|Telco Support | V6: Linked | W6: Billing row links to matching customer/service contract
A7: BILL00006 | B7: CUST0001 | C7: 45809 | D7: Support | E7: Telco Support | F7: CTR-0001-01 | G7: SP001 | H7: Recurring + Usage | I7: 406 | J7: 190.57 | K7: 53.35 | L7: 12.18 | M7: 637.74 | N7: 0.24 | O7: 153.06 | P7: Billed | Q7: Pending | R7: 1 | S7: 24 | T7: 46143 | U7: CUST0001|Telco Support | V7: Linked | W7: Billing row links to matching customer/service contract
A8: BILL00007 | B8: CUST0001 | C8: 45839 | D8: Support | E8: Telco Support | F8: CTR-0001-01 | G8: SP001 | H8: Recurring + Usage | I8: 406 | J8: 149.08 | K8: 41.97 | L8: 32.48 | M8: 564.57 | N8: 0.35 | O8: 197.6 | P8: Billed | Q8: Paid | R8: 1 | S8: 24 | T8: 46143 | U8: CUST0001|Telco Support | V8: Linked | W8: Billing row links to matching customer/service contract
A9: BILL00008 | B9: CUST0001 | C9: 45870 | D9: Support | E9: Telco Support | F9: CTR-0001-01 | G9: SP001 | H9: Recurring + Usage | I9: 406 | J9: 0 | K9: 43.42 | L9: 0 | M9: 449.42 | N9: 0.33 | O9: 148.31 | P9: Billed | Q9: Paid | R9: 1 | S9: 24 | T9: 46143 | U9: CUST0001|Telco Support | V9: Linked | W9: Billing row links to matching customer/service contract
A10: BILL00009 | B10: CUST0001 | C10: 45901 | D10: Support | E10: Telco Support | F10: CTR-0001-01 | G10: SP001 | H10: Recurring + Usage | I10: 406 | J10: 0 | K10: 31.63 | L10: 12.18 | M10: 425.45 | N10: 0.31 | O10: 131.89 | P10: Billed | Q10: Pending | R10: 1 | S10: 24 | T10: 46143 | U10: CUST0001|Telco Support | V10: Linked | W10: Billing row links to matching customer/service contract
A11: BILL00010 | B11: CUST0001 | C11: 45931 | D11: Support | E11: Telco Support | F11: CTR-0001-01 | G11: SP001 | H11: Recurring + Usage | I11: 406 | J11: 0 | K11: 46.97 | L11: 0 | M11: 452.97 | N11: 0.26 | O11: 117.77 | P11: Billed | Q11: Paid | R11: 1 | S11: 24 | T11: 46143 | U11: CUST0001|Telco Support | V11: Linked | W11: Billing row links to matching customer/service contract
A12: BILL00011 | B12: CUST0001 | C12: 45962 | D12: Support | E12: Telco Support | F12: CTR-0001-01 | G12: SP001 | H12: Recurring + Usage | I12: 406 | J12: 0 | K12: 40.82 | L12: 0 | M12: 446.82 | N12: 0.29 | O12: 129.58 | P12: Billed | Q12: Paid | R12: 1 | S12: 24 | T12: 46143 | U12: CUST0001|Telco Support | V12: Linked | W12: Billing row links to matching customer/service contract
A13: BILL00012 | B13: CUST0001 | C13: 45992 | D13: Support | E13: Telco Support | F13: CTR-0001-01 | G13: SP001 | H13: Recurring + Usage | I13: 406 | J13: 0 | K13: 53.53 | L13: 20.3 | M13: 439.23 | N13: 0.36 | O13: 158.12 | P13: Billed | Q13: Paid | R13: 1 | S13: 24 | T13: 46143 | U13: CUST0001|Telco Support | V13: Linked | W13: Billing row links to matching customer/service contract
... A2521: BILL02520 | B2521: CUST0100 | C2521: 45992 | D2521: Managed Services | E2521: Cloud IT | F2521: CTR-0100-01 | G2521: SP006 | H2521: Recurring + Usage | I2521: 11307 | J2521: 0 | K2521: 246.83 | L2521: 0 | M2521: 11553.83 | N2521: 0.37 | O2521: 4274.92 | P2521: Billed | Q2521: Paid | R2521: 1 | S2521: 36 | T2521: 46384 | U2521: CUST0100|Cloud IT | V2521: Linked | W2521: Billing row links to matching customer/service contract
A2522: BILL02521 | B2522: CUST0035 | C2522: 45962 | D2522: Managed Services | E2522: Cyber Security | F2522: CTR-0035-01 | G2522: SP008 | H2522: One-Off | I2522: 0 | J2522: 20400 | K2522: 0 | L2522: 0 | M2522: 20400 | N2522: 0.53 | O2522: 10812 | P2522: Billed | Q2522: Pending | R2522: 0 | S2522: 0 | U2522: CUST0035|Cyber Security | V2522: Linked | W2522: Billing row links to matching customer/service contract
A2523: BILL02522 | B2523: CUST0034 | C2523: 45689 | D2523: Managed Services | E2523: Cyber Security | F2523: CTR-0034-01 | G2523: SP006 | H2523: One-Off | I2523: 0 | J2523: 27021 | K2523: 0 | L2523: 0 | M2523: 27021 | N2523: 0.55 | O2523: 14861.55 | P2523: Billed | Q2523: Pending | R2523: 0 | S2523: 0 | U2523: CUST0034|Cyber Security | V2523: Linked | W2523: Billing row links to matching customer/service contract
A2524: BILL02523 | B2524: CUST0035 | C2524: 45689 | D2524: Support | E2524: IT Support | F2524: CTR-0035-01 | G2524: SP008 | H2524: One-Off | I2524: 0 | J2524: 18984 | K2524: 0 | L2524: 0 | M2524: 18984 | N2524: 0.39 | O2524: 7403.76 | P2524: Billed | Q2524: Pending | R2524: 0 | S2524: 0 | U2524: CUST0035|IT Support | V2524: Linked | W2524: Billing row links to matching customer/service contract
A2525: BILL02524 | B2525: CUST0005 | C2525: 45809 | D2525: Support | E2525: IT Support | F2525: CTR-0005-01 | G2525: SP008 | H2525: One-Off | I2525: 0 | J2525: 30958 | K2525: 0 | L2525: 0 | M2525: 30958 | N2525: 0.37 | O2525: 11454.46 | P2525: Billed | Q2525: Paid | R2525: 0 | S2525: 0 | U2525: CUST0005|IT Support | V2525: Linked | W2525: Billing row links to matching customer/service contract
A2526: BILL02525 | B2526: CUST0094 | C2526: 45962 | D2526: Support | E2526: IT Support | F2526: CTR-0094-01 | G2526: SP001 | H2526: One-Off | I2526: 0 | J2526: 11092 | K2526: 0 | L2526: 0 | M2526: 11092 | N2526: 0.37 | O2526: 4104.04 | P2526: Billed | Q2526: Paid | R2526: 0 | S2526: 0 | U2526: CUST0094|IT Support | V2526: Linked | W2526: Billing row links to matching customer/service contract
A2527: BILL02526 | B2527: CUST0094 | C2527: 45717 | D2527: Support | E2527: IT Support | F2527: CTR-0094-01 | G2527: SP001 | H2527: One-Off | I2527: 0 | J2527: 2760 | K2527: 0 | L2527: 0 | M2527: 2760 | N2527: 0.48 | O2527: 1324.8 | P2527: Billed | Q2527: Paid | R2527: 0 | S2527: 0 | U2527: CUST0094|IT Support | V2527: Linked | W2527: Billing row links to matching customer/service contract
A2528: BILL02527 | B2528: CUST0010 | C2528: 45962 | D2528: Managed Services | E2528: Cyber Security | F2528: CTR-0010-01 | G2528: SP008 | H2528: One-Off | I2528: 0 | J2528: 10127 | K2528: 0 | L2528: 0 | M2528: 10127 | N2528: 0.45 | O2528: 4557.15 | P2528: Billed | Q2528: Paid | R2528: 0 | S2528: 0 | U2528: CUST0010|Cyber Security | V2528: Linked | W2528: Billing row links to matching customer/service contract
A2529: BILL02528 | B2529: CUST0021 | C2529: 45901 | D2529: Support | E2529: Telco Support | F2529: CTR-0021-01 | G2529: SP002 | H2529: One-Off | I2529: 0 | J2529: 7312 | K2529: 0 | L2529: 0 | M2529: 7312 | N2529: 0.36 | O2529: 2632.32 | P2529: Billed | Q2529: Paid | R2529: 0 | S2529: 0 | U2529: CUST0021|Telco Support | V2529: Linked | W2529: Billing row links to matching customer/service contract
A2530: BILL02529 | B2530: CUST0067 | C2530: 45839 | D2530: Managed Services | E2530: Cloud IT | F2530: CTR-0067-02 | G2530: SP008 | H2530: One-Off | I2530: 0 | J2530: 20897 | K2530: 0 | L2530: 0 | M2530: 20897 | N2530: 0.36 | O2530: 7522.92 | P2530: Billed | Q2530: Paid | R2530: 0 | S2530: 0 | U2530: CUST0067|Cloud IT | V2530: Linked | W2530: Billing row links to matching customer/service contract
A2531: BILL02530 | B2531: CUST0052 | C2531: 45839 | D2531: Telco | E2531: Hosted Telephony | F2531: CTR-0052-01 | G2531: SP002 | H2531: One-Off | I2531: 0 | J2531: 14343 | K2531: 0 | L2531: 0 | M2531: 14343 | N2531: 0.29 | O2531: 4159.47 | P2531: Billed | Q2531: Paid | R2531: 0 | S2531: 0 | U2531: CUST0052|Hosted Telephony | V2531: Linked | W2531: Billing row links to matching customer/service contract
A2532: BILL02531 | B2532: CUST0036 | C2532: 45689 | D2532: Telco | E2532: Hosted Telephony | F2532: CTR-0036-01 | G2532: SP004 | H2532: One-Off | I2532: 0 | J2532: 20357 | K2532: 0 | L2532: 0 | M2532: 20357 | N2532: 0.41 | O2532: 8346.37 | P2532: Billed | Q2532: Pending | R2532: 0 | S2532: 0 | U2532: CUST0036|Hosted Telephony | V2532: Linked | W2532: Billing row links to matching customer/service contract
A2533: BILL02532 | B2533: CUST0064 | C2533: 45931 | D2533: Support | E2533: Telco Support | F2533: CTR-0064-02 | G2533: SP007 | H2533: One-Off | I2533: 0 | J2533: 27034 | K2533: 0 | L2533: 0 | M2533: 27034 | N2533: 0.35 | O2533: 9461.9 | P2533: Billed | Q2533: Paid | R2533: 0 | S2533: 0 | U2533: CUST0064|Telco Support | V2533: Linked | W2533: Billing row links to matching customer/service contract
... A2601: BILL02600 | B2601: CUST0047 | C2601: 45839 | D2601: Managed Services | E2601: Cyber Security | F2601: CTR-0047-01 | G2601: SP010 | H2601: One-Off | I2601: 0 | J2601: 28926 | K2601: 0 | L2601: 0 | M2601: 28926 | N2601: 0.47 | O2601: 13595.22 | P2601: Billed | Q2601: Paid | R2601: 0 | S2601: 0 | U2601: CUST0047|Cyber Security | V2601: Linked | W2601: Billing row links to matching customer/service contract

Sheet BillingSummaryByService
A1: ServiceCategory | B1: Service | C1: ActiveCustomers | D1: RecurringMRR | E1: AnnualisedRecurringRevenue | F1: OneOffCharges | G1: UsageCharges | H1: Discounts | I1: TotalBilled | J1: GrossProfit | K1: AvgGrossMargin | L1: OverdueBills | M1: CrossSellSignal
A2: Managed Services | B2: Cloud IT | C2: =COUNTA(_xlfn.UNIQUE(_xlfn._xlws.FILTER(ExistingCustomerBilling!$B$2:$B$2601,ExistingCustomerBilling!$E$2:$E$2601=$B2))) | D2: =SUMIFS(ExistingCustomerBilling!$I:$I,ExistingCustomerBilling!$E:$E,$B2,ExistingCustomerBilling!$R:$R,1) | E2: =D2*12 | F2: =SUMIFS(ExistingCustomerBilling!$J:$J,ExistingCustomerBilling!$E:$E,$B2) | G2: =SUMIFS(ExistingCustomerBilling!$K:$K,ExistingCustomerBilling!$E:$E,$B2) | H2: =SUMIFS(ExistingCustomerBilling!$L:$L,ExistingCustomerBilling!$E:$E,$B2) | I2: =SUMIFS(ExistingCustomerBilling!$M:$M,ExistingCustomerBilling!$E:$E,$B2) | J2: =SUMIFS(ExistingCustomerBilling!$O:$O,ExistingCustomerBilling!$E:$E,$B2) | K2: =IFERROR(J2/I2,0) | L2: =COUNTIFS(ExistingCustomerBilling!$E:$E,$B2,ExistingCustomerBilling!$Q:$Q,"Overdue") | M2: =IF(C2<35,"High whitespace / cross-sell potential",IF(K2<0.35,"Margin review","Maintain / expand"))
A3: Managed Services | B3: Modern Workplace | C3: =COUNTA(_xlfn.UNIQUE(_xlfn._xlws.FILTER(ExistingCustomerBilling!$B$2:$B$2601,ExistingCustomerBilling!$E$2:$E$2601=$B3))) | D3: =SUMIFS(ExistingCustomerBilling!$I:$I,ExistingCustomerBilling!$E:$E,$B3,ExistingCustomerBilling!$R:$R,1) | E3: =D3*12 | F3: =SUMIFS(ExistingCustomerBilling!$J:$J,ExistingCustomerBilling!$E:$E,$B3) | G3: =SUMIFS(ExistingCustomerBilling!$K:$K,ExistingCustomerBilling!$E:$E,$B3) | H3: =SUMIFS(ExistingCustomerBilling!$L:$L,ExistingCustomerBilling!$E:$E,$B3) | I3: =SUMIFS(ExistingCustomerBilling!$M:$M,ExistingCustomerBilling!$E:$E,$B3) | J3: =SUMIFS(ExistingCustomerBilling!$O:$O,ExistingCustomerBilling!$E:$E,$B3) | K3: =IFERROR(J3/I3,0) | L3: =COUNTIFS(ExistingCustomerBilling!$E:$E,$B3,ExistingCustomerBilling!$Q:$Q,"Overdue") | M3: =IF(C3<35,"High whitespace / cross-sell potential",IF(K3<0.35,"Margin review","Maintain / expand"))
A4: Managed Services | B4: Cyber Security | C4: =COUNTA(_xlfn.UNIQUE(_xlfn._xlws.FILTER(ExistingCustomerBilling!$B$2:$B$2601,ExistingCustomerBilling!$E$2:$E$2601=$B4))) | D4: =SUMIFS(ExistingCustomerBilling!$I:$I,ExistingCustomerBilling!$E:$E,$B4,ExistingCustomerBilling!$R:$R,1) | E4: =D4*12 | F4: =SUMIFS(ExistingCustomerBilling!$J:$J,ExistingCustomerBilling!$E:$E,$B4) | G4: =SUMIFS(ExistingCustomerBilling!$K:$K,ExistingCustomerBilling!$E:$E,$B4) | H4: =SUMIFS(ExistingCustomerBilling!$L:$L,ExistingCustomerBilling!$E:$E,$B4) | I4: =SUMIFS(ExistingCustomerBilling!$M:$M,ExistingCustomerBilling!$E:$E,$B4) | J4: =SUMIFS(ExistingCustomerBilling!$O:$O,ExistingCustomerBilling!$E:$E,$B4) | K4: =IFERROR(J4/I4,0) | L4: =COUNTIFS(ExistingCustomerBilling!$E:$E,$B4,ExistingCustomerBilling!$Q:$Q,"Overdue") | M4: =IF(C4<35,"High whitespace / cross-sell potential",IF(K4<0.35,"Margin review","Maintain / expand"))
A5: Telco | B5: Connectivity | C5: =COUNTA(_xlfn.UNIQUE(_xlfn._xlws.FILTER(ExistingCustomerBilling!$B$2:$B$2601,ExistingCustomerBilling!$E$2:$E$2601=$B5))) | D5: =SUMIFS(ExistingCustomerBilling!$I:$I,ExistingCustomerBilling!$E:$E,$B5,ExistingCustomerBilling!$R:$R,1) | E5: =D5*12 | F5: =SUMIFS(ExistingCustomerBilling!$J:$J,ExistingCustomerBilling!$E:$E,$B5) | G5: =SUMIFS(ExistingCustomerBilling!$K:$K,ExistingCustomerBilling!$E:$E,$B5) | H5: =SUMIFS(ExistingCustomerBilling!$L:$L,ExistingCustomerBilling!$E:$E,$B5) | I5: =SUMIFS(ExistingCustomerBilling!$M:$M,ExistingCustomerBilling!$E:$E,$B5) | J5: =SUMIFS(ExistingCustomerBilling!$O:$O,ExistingCustomerBilling!$E:$E,$B5) | K5: =IFERROR(J5/I5,0) | L5: =COUNTIFS(ExistingCustomerBilling!$E:$E,$B5,ExistingCustomerBilling!$Q:$Q,"Overdue") | M5: =IF(C5<35,"High whitespace / cross-sell potential",IF(K5<0.35,"Margin review","Maintain / expand"))
A6: Telco | B6: Hosted Telephony | C6: =COUNTA(_xlfn.UNIQUE(_xlfn._xlws.FILTER(ExistingCustomerBilling!$B$2:$B$2601,ExistingCustomerBilling!$E$2:$E$2601=$B6))) | D6: =SUMIFS(ExistingCustomerBilling!$I:$I,ExistingCustomerBilling!$E:$E,$B6,ExistingCustomerBilling!$R:$R,1) | E6: =D6*12 | F6: =SUMIFS(ExistingCustomerBilling!$J:$J,ExistingCustomerBilling!$E:$E,$B6) | G6: =SUMIFS(ExistingCustomerBilling!$K:$K,ExistingCustomerBilling!$E:$E,$B6) | H6: =SUMIFS(ExistingCustomerBilling!$L:$L,ExistingCustomerBilling!$E:$E,$B6) | I6: =SUMIFS(ExistingCustomerBilling!$M:$M,ExistingCustomerBilling!$E:$E,$B6) | J6: =SUMIFS(ExistingCustomerBilling!$O:$O,ExistingCustomerBilling!$E:$E,$B6) | K6: =IFERROR(J6/I6,0) | L6: =COUNTIFS(ExistingCustomerBilling!$E:$E,$B6,ExistingCustomerBilling!$Q:$Q,"Overdue") | M6: =IF(C6<35,"High whitespace / cross-sell potential",IF(K6<0.35,"Margin review","Maintain / expand"))
A7: Support | B7: IT Support | C7: =COUNTA(_xlfn.UNIQUE(_xlfn._xlws.FILTER(ExistingCustomerBilling!$B$2:$B$2601,ExistingCustomerBilling!$E$2:$E$2601=$B7))) | D7: =SUMIFS(ExistingCustomerBilling!$I:$I,ExistingCustomerBilling!$E:$E,$B7,ExistingCustomerBilling!$R:$R,1) | E7: =D7*12 | F7: =SUMIFS(ExistingCustomerBilling!$J:$J,ExistingCustomerBilling!$E:$E,$B7) | G7: =SUMIFS(ExistingCustomerBilling!$K:$K,ExistingCustomerBilling!$E:$E,$B7) | H7: =SUMIFS(ExistingCustomerBilling!$L:$L,ExistingCustomerBilling!$E:$E,$B7) | I7: =SUMIFS(ExistingCustomerBilling!$M:$M,ExistingCustomerBilling!$E:$E,$B7) | J7: =SUMIFS(ExistingCustomerBilling!$O:$O,ExistingCustomerBilling!$E:$E,$B7) | K7: =IFERROR(J7/I7,0) | L7: =COUNTIFS(ExistingCustomerBilling!$E:$E,$B7,ExistingCustomerBilling!$Q:$Q,"Overdue") | M7: =IF(C7<35,"High whitespace / cross-sell potential",IF(K7<0.35,"Margin review","Maintain / expand"))
A8: Support | B8: Telco Support | C8: =COUNTA(_xlfn.UNIQUE(_xlfn._xlws.FILTER(ExistingCustomerBilling!$B$2:$B$2601,ExistingCustomerBilling!$E$2:$E$2601=$B8))) | D8: =SUMIFS(ExistingCustomerBilling!$I:$I,ExistingCustomerBilling!$E:$E,$B8,ExistingCustomerBilling!$R:$R,1) | E8: =D8*12 | F8: =SUMIFS(ExistingCustomerBilling!$J:$J,ExistingCustomerBilling!$E:$E,$B8) | G8: =SUMIFS(ExistingCustomerBilling!$K:$K,ExistingCustomerBilling!$E:$E,$B8) | H8: =SUMIFS(ExistingCustomerBilling!$L:$L,ExistingCustomerBilling!$E:$E,$B8) | I8: =SUMIFS(ExistingCustomerBilling!$M:$M,ExistingCustomerBilling!$E:$E,$B8) | J8: =SUMIFS(ExistingCustomerBilling!$O:$O,ExistingCustomerBilling!$E:$E,$B8) | K8: =IFERROR(J8/I8,0) | L8: =COUNTIFS(ExistingCustomerBilling!$E:$E,$B8,ExistingCustomerBilling!$Q:$Q,"Overdue") | M8: =IF(C8<35,"High whitespace / cross-sell potential",IF(K8<0.35,"Margin review","Maintain / expand"))
A9: TOTAL | B9: All Services | C9: =COUNTA(_xlfn.UNIQUE(ExistingCustomerBilling!$B$2:$B$2601)) | D9: =SUM(D2:D8) | E9: =SUM(E2:E8) | F9: =SUM(F2:F8) | G9: =SUM(G2:G8) | H9: =SUM(H2:H8) | I9: =SUM(I2:I8) | J9: =SUM(J2:J8) | K9: =IFERROR(J9/I9,0) | L9: =SUM(L2:L8) | M9: Portfolio view

Sheet BillingFeatureNotes
A1: Section | B1: Detail
A2: Purpose | B2: This workbook now includes existing customer billing history across Managed Services, Telco and Support services.
A3: Why added | B3: Customer billing data helps the model understand current account value, recurring revenue, gross profit, product penetration, renewal timing and cross-sell whitespace.
A4: Main billing sheet | B4: ExistingCustomerBilling
A5: Summary sheet | B5: BillingSummaryByService
A6: Key model features | B6: MRR, annualised recurring revenue, gross profit, margin, active service count, product penetration, overdue bills, renewal date proximity, usage growth, service mix.
A7: Manager value | B7: Sales managers can identify high-value customers, underpenetrated accounts, cross-sell opportunities, service gaps and renewal risk.
A8: Data scientist value | B8: The model can test whether billing patterns improve prediction accuracy and whether product/service mix changes salesperson performance predictions.
A9: Future extension | B9: When call transcripts or salesperson notes are added, model behaviour can be compared before and after the new features are introduced.
A10: Important caveat | B10: The billing data is simulated for demo purposes and should be replaced with approved real billing data before production use.

Sheet Contracts
A1: ContractID | B1: CustomerID | C1: AccountOwnerID | D1: ContractName | E1: ContractType | F1: ContractStatus | G1: OriginalStartDate | H1: CurrentStartDate | I1: OriginalEndDate | J1: CurrentEndDate | K1: ContractTermMonths | L1: RenewalWindowDays | M1: DaysToRenewal | N1: AutoRenewal | O1: EndDateChangeCount | P1: RollbackCount | Q1: RollbackAllowed | R1: HealthCheckRequired | S1: HealthCheckReason | T1: SuggestedAction | U1: ContractMRR | V1: ContractARR | W1: EstimatedAnnualGrossProfit | X1: RenewalRisk | Y1: SnapshotDate
A2: CTR-0001-01 | B2: CUST0001 | C2: SP001 | D2: CUST0001 Support Agreement 1 | E2: Support Agreement | F2: Expired - Rolling | G2: 45962 | H2: 45962 | I2: 46682 | J2: 46112 | K2: 24 | L2: 120 | M2: -137 | N2: 1 | O2: 0 | P2: 0 | Q2: 1 | R2: 1 | S2: Contract has passed end date and appears to be rolling or needs review | T2: Immediate contract health check and renewal confirmation | U2: 374.77 | V2: 4497.24 | W2: 1394.16 | X2: Medium | Y2: 46249
A3: CTR-0002-01 | B3: CUST0002 | C3: SP004 | D3: CUST0002 Multi-Service Agreement 1 | E3: Multi-Service Agreement | F3: Upcoming Renewal | G3: 45597 | H3: 45597 | I3: 46317 | J3: 46282 | K3: 24 | L3: 120 | M3: 33 | N3: 0 | O3: 1 | P3: 1 | Q3: 1 | R3: 1 | S3: Renewal due within 60 days | T3: Schedule renewal and service-value review | U3: 7001 | V3: 84012 | W3: 29133.12 | X3: Medium | Y3: 46249
A4: CTR-0003-01 | B4: CUST0003 | C4: SP006 | D4: CUST0003 Telco Agreement 1 | E4: Telco Agreement | F4: Upcoming Renewal | G4: 45017 | H4: 45017 | I4: 45377 | J4: 46331 | K4: 12 | L4: 120 | M4: 82 | N4: 1 | O4: 0 | P4: 0 | Q4: 0 | R4: 1 | S4: Renewal due within 120 days | T4: Plan proactive health check and whitespace review | U4: 2790 | V4: 33480 | W4: 10044 | X4: High | Y4: 46249
A5: CTR-0004-01 | B5: CUST0004 | C5: SP007 | D5: CUST0004 Multi-Service Agreement 1 | E5: Multi-Service Agreement | F5: Active | G5: 45337 | H5: 45337 | I5: 45697 | J5: 46934 | K5: 12 | L5: 120 | M5: 685 | N5: 1 | O5: 3 | P5: 1 | Q5: 1 | R5: 0 | T5: Monitor | U5: 617 | V5: 7404 | W5: 2369.28 | X5: Low | Y5: 46249
A6: CTR-0004-02 | B6: CUST0004 | C6: SP007 | D6: CUST0004 Multi-Service Agreement 2 | E6: Multi-Service Agreement | F6: Upcoming Renewal | G6: 45337 | H6: 45337 | I6: 46417 | J6: 46259 | K6: 36 | L6: 120 | M6: 10 | N6: 1 | O6: 2 | P6: 0 | Q6: 1 | R6: 1 | S6: Renewal due within 30 days | T6: Urgent customer renewal health check | U6: 8767 | V6: 105204 | W6: 49559.04 | X6: Low | Y6: 46249
A7: CTR-0004-03 | B7: CUST0004 | C7: SP007 | D7: CUST0004 Managed Service Agreement 3 | E7: Managed Service Agreement | F7: Active | G7: 45792 | H7: 45792 | I7: 46512 | J7: 46736 | K7: 24 | L7: 120 | M7: 487 | N7: 0 | O7: 0 | P7: 0 | Q7: 1 | R7: 0 | T7: Monitor | U7: 8937 | V7: 107244 | W7: 45042.48 | X7: Low | Y7: 46249
A8: CTR-0005-01 | B8: CUST0005 | C8: SP008 | D8: CUST0005 Multi-Service Agreement 1 | E8: Multi-Service Agreement | F8: Upcoming Renewal | G8: 45689 | H8: 45689 | I8: 46409 | J8: 46355 | K8: 24 | L8: 120 | M8: 106 | N8: 0 | O8: 0 | P8: 0 | Q8: 0 | R8: 1 | S8: Renewal due within 120 days | T8: Plan proactive health check and whitespace review | U8: 5814 | V8: 69768 | W8: 27209.52 | X8: Low | Y8: 46249
A9: CTR-0005-02 | B9: CUST0005 | C9: SP008 | D9: CUST0005 Multi-Service Agreement 2 | E9: Multi-Service Agreement | F9: Upcoming Renewal | G9: 45703 | H9: 45703 | I9: 46063 | J9: 46259 | K9: 12 | L9: 120 | M9: 10 | N9: 1 | O9: 2 | P9: 0 | Q9: 1 | R9: 1 | S9: Renewal due within 30 days | T9: Urgent customer renewal health check | U9: 1295 | V9: 15540 | W9: 5088.48 | X9: Medium | Y9: 46249
A10: CTR-0005-03 | B10: CUST0005 | C10: SP008 | D10: CUST0005 Support Agreement 3 | E10: Support Agreement | F10: Upcoming Renewal | G10: 45519 | H10: 45519 | I10: 46239 | J10: 46272 | K10: 24 | L10: 120 | M10: 23 | N10: 1 | O10: 3 | P10: 0 | Q10: 1 | R10: 1 | S10: Renewal due within 30 days | T10: Urgent customer renewal health check | U10: 1954 | V10: 23448 | W10: 7034.4 | X10: Medium | Y10: 46249
A11: CTR-0006-01 | B11: CUST0006 | C11: SP006 | D11: CUST0006 Multi-Service Agreement 1 | E11: Multi-Service Agreement | F11: Expired - Rolling | G11: 45184 | H11: 45184 | I11: 45544 | J11: 46222 | K11: 12 | L11: 120 | M11: -27 | N11: 1 | O11: 3 | P11: 0 | Q11: 1 | R11: 1 | S11: Contract has passed end date and appears to be rolling or needs review | T11: Immediate contract health check and renewal confirmation | U11: 3213 | V11: 38556 | W11: 11525.4 | X11: Medium | Y11: 46249
A12: CTR-0007-01 | B12: CUST0007 | C12: SP006 | D12: CUST0007 Multi-Service Agreement 1 | E12: Multi-Service Agreement | F12: Expired - Rolling | G12: 45383 | H12: 45383 | I12: 45743 | J12: 46160 | K12: 12 | L12: 120 | M12: -89 | N12: 1 | O12: 1 | P12: 1 | Q12: 1 | R12: 1 | S12: Contract has passed end date and appears to be rolling or needs review | T12: Immediate contract health check and renewal confirmation | U12: 1830.46 | V12: 21965.52 | W12: 8868.48 | X12: Low | Y12: 46249
A13: CTR-0008-01 | B13: CUST0008 | C13: SP003 | D13: CUST0008 Support Agreement 1 | E13: Support Agreement | F13: Active | G13: 45184 | H13: 45184 | I13: 45544 | J13: 46449 | K13: 12 | L13: 120 | M13: 200 | N13: 0 | O13: 0 | P13: 0 | Q13: 1 | R13: 0 | T13: Monitor | U13: 2313 | V13: 27756 | W13: 8049.24 | X13: Low | Y13: 46249
A14: CTR-0008-02 | B14: CUST0008 | C14: SP003 | D14: CUST0008 Telco Agreement 2 | E14: Telco Agreement | F14: Active | G14: 45519 | H14: 45519 | I14: 45879 | J14: 46595 | K14: 12 | L14: 120 | M14: 346 | N14: 0 | O14: 1 | P14: 1 | Q14: 1 | R14: 0 | T14: Monitor | U14: 2649 | V14: 31788 | W14: 10807.92 | X14: Low | Y14: 46249
A15: CTR-0008-03 | B15: CUST0008 | C15: SP003 | D15: CUST0008 Multi-Service Agreement 3 | E15: Multi-Service Agreement | F15: Active | G15: 45000 | H15: 45000 | I15: 45720 | J15: 46825 | K15: 24 | L15: 120 | M15: 576 | N15: 0 | O15: 1 | P15: 0 | Q15: 0 | R15: 0 | T15: Monitor | U15: 2476 | V15: 29712 | W15: 12776.16 | X15: Low | Y15: 46249
A16: CTR-0009-01 | B16: CUST0009 | C16: SP009 | D16: CUST0009 Support Agreement 1 | E16: Support Agreement | F16: Upcoming Renewal | G16: 45566 | H16: 45566 | I16: 46286 | J16: 46315 | K16: 24 | L16: 120 | M16: 66 | N16: 0 | O16: 0 | P16: 0 | Q16: 1 | R16: 1 | S16: Renewal due within 120 days | T16: Plan proactive health check and whitespace review | U16: 4829.54 | V16: 57954.48 | W16: 25500 | X16: Low | Y16: 46249
A17: CTR-0010-01 | B17: CUST0010 | C17: SP008 | D17: CUST0010 Multi-Service Agreement 1 | E17: Multi-Service Agreement | F17: Upcoming Renewal | G17: 45505 | H17: 45505 | I17: 46585 | J17: 46317 | K17: 36 | L17: 120 | M17: 68 | N17: 0 | O17: 0 | P17: 0 | Q17: 1 | R17: 1 | S17: Renewal due within 120 days | T17: Plan proactive health check and whitespace review | U17: 5966 | V17: 71592 | W17: 31500.48 | X17: Medium | Y17: 46249
A18: CTR-0010-02 | B18: CUST0010 | C18: SP008 | D18: CUST0010 Multi-Service Agreement 2 | E18: Multi-Service Agreement | F18: Active | G18: 45200 | H18: 45200 | I18: 46280 | J18: 46681 | K18: 36 | L18: 120 | M18: 432 | N18: 1 | O18: 0 | P18: 0 | Q18: 0 | R18: 0 | T18: Monitor | U18: 1080 | V18: 12960 | W18: 4017.6 | X18: Low | Y18: 46249
A19: CTR-0010-03 | B19: CUST0010 | C19: SP008 | D19: CUST0010 Managed Service Agreement 3 | E19: Managed Service Agreement | F19: Active | G19: 45200 | H19: 45200 | I19: 46280 | J19: 46464 | K19: 36 | L19: 120 | M19: 215 | N19: 0 | O19: 0 | P19: 0 | Q19: 0 | R19: 0 | T19: Monitor | U19: 0 | V19: 0 | W19: 0 | X19: Low | Y19: 46249
A20: CTR-0011-01 | B20: CUST0011 | C20: SP005 | D20: CUST0011 Support Agreement 1 | E20: Support Agreement | F20: Active | G20: 45976 | H20: 45976 | I20: 46696 | J20: 46828 | K20: 24 | L20: 120 | M20: 579 | N20: 1 | O20: 3 | P20: 2 | Q20: 1 | R20: 0 | T20: Monitor | U20: 449 | V20: 5388 | W20: 1616.4 | X20: Low | Y20: 46249
A21: CTR-0012-01 | B21: CUST0012 | C21: SP010 | D21: CUST0012 Managed Service Agreement 1 | E21: Managed Service Agreement | F21: Upcoming Renewal | G21: 45170 | H21: 45170 | I21: 46250 | J21: 46353 | K21: 36 | L21: 120 | M21: 104 | N21: 1 | O21: 0 | P21: 0 | Q21: 0 | R21: 1 | S21: Renewal due within 120 days | T21: Plan proactive health check and whitespace review | U21: 1291.71 | V21: 15500.52 | W21: 5890.2 | X21: Medium | Y21: 46249
A22: CTR-0013-01 | B22: CUST0013 | C22: SP005 | D22: CUST0013 Multi-Service Agreement 1 | E22: Multi-Service Agreement | F22: Active | G22: 45778 | H22: 45778 | I22: 46858 | J22: 46880 | K22: 36 | L22: 120 | M22: 631 | N22: 0 | O22: 0 | P22: 0 | Q22: 1 | R22: 0 | T22: Monitor | U22: 4144 | V22: 49728 | W22: 19104.48 | X22: Low | Y22: 46249
A23: CTR-0014-01 | B23: CUST0014 | C23: SP003 | D23: CUST0014 Multi-Service Agreement 1 | E23: Multi-Service Agreement | F23: Expired - Needs Review | G23: 45306 | H23: 45306 | I23: 46026 | J23: 46190 | K23: 24 | L23: 120 | M23: -59 | N23: 0 | O23: 0 | P23: 0 | Q23: 0 | R23: 1 | S23: Contract has passed end date and appears to be rolling or needs review | T23: Immediate contract health check and renewal confirmation | U23: 5978 | V23: 71736 | W23: 29558.28 | X23: High | Y23: 46249
A24: CTR-0015-01 | B24: CUST0015 | C24: SP009 | D24: CUST0015 Multi-Service Agreement 1 | E24: Multi-Service Agreement | F24: Upcoming Renewal | G24: 45519 | H24: 45519 | I24: 46239 | J24: 46290 | K24: 24 | L24: 120 | M24: 41 | N24: 1 | O24: 0 | P24: 0 | Q24: 1 | R24: 1 | S24: Renewal due within 60 days | T24: Schedule renewal and service-value review | U24: 6220 | V24: 74640 | W24: 30361.44 | X24: Low | Y24: 46249
A25: CTR-0015-02 | B25: CUST0015 | C25: SP009 | D25: CUST0015 Multi-Service Agreement 2 | E25: Multi-Service Agreement | F25: Expired - Needs Review | G25: 45413 | H25: 45413 | I25: 46493 | J25: 46182 | K25: 36 | L25: 120 | M25: -67 | N25: 1 | O25: 0 | P25: 0 | Q25: 0 | R25: 1 | S25: Contract has passed end date and appears to be rolling or needs review | T25: Immediate contract health check and renewal confirmation | U25: 8832 | V25: 105984 | W25: 44513.28 | X25: Low | Y25: 46249
A26: CTR-0016-01 | B26: CUST0016 | C26: SP007 | D26: CUST0016 Managed Service Agreement 1 | E26: Managed Service Agreement | F26: Active | G26: 45884 | H26: 45884 | I26: 46244 | J26: 46850 | K26: 12 | L26: 120 | M26: 601 | N26: 1 | O26: 1 | P26: 0 | Q26: 1 | R26: 0 | T26: Monitor | U26: 8414 | V26: 100968 | W26: 42406.56 | X26: Low | Y26: 46249
A27: CTR-0017-01 | B27: CUST0017 | C27: SP005 | D27: CUST0017 Managed Service Agreement 1 | E27: Managed Service Agreement | F27: Active | G27: 45275 | H27: 45275 | I27: 45635 | J27: 46388 | K27: 12 | L27: 120 | M27: 139 | N27: 1 | O27: 1 | P27: 0 | Q27: 1 | R27: 0 | T27: Monitor | U27: 11431 | V27: 137172 | W27: 56240.52 | X27: Low | Y27: 46249
A28: CTR-0017-02 | B28: CUST0017 | C28: SP005 | D28: CUST0017 Managed Service Agreement 2 | E28: Managed Service Agreement | F28: Active | G28: 45931 | H28: 45931 | I28: 46291 | J28: 46715 | K28: 12 | L28: 120 | M28: 466 | N28: 0 | O28: 2 | P28: 1 | Q28: 1 | R28: 0 | T28: Monitor | U28: 1624 | V28: 19488 | W28: 9549.12 | X28: Low | Y28: 46249
A29: CTR-0018-01 | B29: CUST0018 | C29: SP004 | D29: CUST0018 Support Agreement 1 | E29: Support Agreement | F29: Upcoming Renewal | G29: 44972 | H29: 44972 | I29: 46052 | J29: 46279 | K29: 36 | L29: 120 | M29: 30 | N29: 0 | O29: 0 | P29: 0 | Q29: 0 | R29: 1 | S29: Renewal due within 30 days | T29: Urgent customer renewal health check | U29: 2240 | V29: 26880 | W29: 8064 | X29: Low | Y29: 46249
A30: CTR-0018-02 | B30: CUST0018 | C30: SP004 | D30: CUST0018 Managed Service Agreement 2 | E30: Managed Service Agreement | F30: Upcoming Renewal | G30: 45823 | H30: 45823 | I30: 46903 | J30: 46289 | K30: 36 | L30: 120 | M30: 40 | N30: 1 | O30: 4 | P30: 0 | Q30: 1 | R30: 1 | S30: Renewal due within 60 days | T30: Schedule renewal and service-value review | U30: 7694 | V30: 92328 | W30: 44317.44 | X30: Medium | Y30: 46249
A31: CTR-0019-01 | B31: CUST0019 | C31: SP002 | D31: CUST0019 Support Agreement 1 | E31: Support Agreement | F31: Upcoming Renewal | G31: 45611 | H31: 45611 | I31: 46331 | J31: 46254 | K31: 24 | L31: 120 | M31: 5 | N31: 0 | O31: 1 | P31: 1 | Q31: 1 | R31: 1 | S31: Renewal due within 30 days | T31: Urgent customer renewal health check | U31: 1020.92 | V31: 12251.04 | W31: 3675.36 | X31: High | Y31: 46249
A32: CTR-0020-01 | B32: CUST0020 | C32: SP006 | D32: CUST0020 Multi-Service Agreement 1 | E32: Multi-Service Agreement | F32: Expired - Rolling | G32: 45031 | H32: 45031 | I32: 45391 | J32: 46128 | K32: 12 | L32: 120 | M32: -121 | N32: 1 | O32: 1 | P32: 0 | Q32: 0 | R32: 1 | S32: Contract has passed end date and appears to be rolling or needs review | T32: Immediate contract health check and renewal confirmation | U32: 12266 | V32: 147192 | W32: 60666.48 | X32: Medium | Y32: 46249
A33: CTR-0020-02 | B33: CUST0020 | C33: SP006 | D33: CUST0020 Support Agreement 2 | E33: Support Agreement | F33: Expired - Rolling | G33: 45108 | H33: 45108 | I33: 45468 | J33: 46107 | K33: 12 | L33: 120 | M33: -142 | N33: 0 | O33: 0 | P33: 0 | Q33: 1 | R33: 1 | S33: Contract has passed end date and appears to be rolling or needs review | T33: Immediate contract health check and renewal confirmation | U33: 3604 | V33: 43248 | W33: 18596.64 | X33: Medium | Y33: 46249
A34: CTR-0021-01 | B34: CUST0021 | C34: SP002 | D34: CUST0021 Multi-Service Agreement 1 | E34: Multi-Service Agreement | F34: Upcoming Renewal | G34: 45566 | H34: 45566 | I34: 46286 | J34: 46363 | K34: 24 | L34: 120 | M34: 114 | N34: 1 | O34: 0 | P34: 0 | Q34: 1 | R34: 1 | S34: Renewal due within 120 days | T34: Plan proactive health check and whitespace review | U34: 2845 | V34: 34140 | W34: 11949 | X34: Medium | Y34: 46249
A35: CTR-0021-02 | B35: CUST0021 | C35: SP002 | D35: CUST0021 Managed Service Agreement 2 | E35: Managed Service Agreement | F35: Upcoming Renewal | G35: 45778 | H35: 45778 | I35: 46858 | J35: 46354 | K35: 36 | L35: 120 | M35: 105 | N35: 0 | O35: 3 | P35: 0 | Q35: 1 | R35: 1 | S35: Renewal due within 120 days | T35: Plan proactive health check and whitespace review | U35: 7961 | V35: 95532 | W35: 45855.36 | X35: Low | Y35: 46249
A36: CTR-0022-01 | B36: CUST0022 | C36: SP009 | D36: CUST0022 Multi-Service Agreement 1 | E36: Multi-Service Agreement | F36: Upcoming Renewal | G36: 45792 | H36: 45792 | I36: 46512 | J36: 46346 | K36: 24 | L36: 120 | M36: 97 | N36: 1 | O36: 1 | P36: 1 | Q36: 1 | R36: 1 | S36: Renewal due within 120 days | T36: Plan proactive health check and whitespace review | U36: 6153 | V36: 73836 | W36: 27032.04 | X36: High | Y36: 46249
A37: CTR-0023-01 | B37: CUST0023 | C37: SP006 | D37: CUST0023 Multi-Service Agreement 1 | E37: Multi-Service Agreement | F37: Active | G37: 45366 | H37: 45366 | I37: 46086 | J37: 46407 | K37: 24 | L37: 120 | M37: 158 | N37: 1 | O37: 1 | P37: 0 | Q37: 0 | R37: 0 | T37: Monitor | U37: 5818 | V37: 69816 | W37: 28841.4 | X37: Low | Y37: 46249
A38: CTR-0023-02 | B38: CUST0023 | C38: SP006 | D38: CUST0023 Telco Agreement 2 | E38: Telco Agreement | F38: Expired - Needs Review | G38: 45292 | H38: 45292 | I38: 45652 | J38: 46205 | K38: 12 | L38: 120 | M38: -44 | N38: 0 | O38: 0 | P38: 0 | Q38: 1 | R38: 1 | S38: Contract has passed end date and appears to be rolling or needs review | T38: Immediate contract health check and renewal confirmation | U38: 1871 | V38: 22452 | W38: 7184.64 | X38: Low | Y38: 46249
A39: CTR-0024-01 | B39: CUST0024 | C39: SP001 | D39: CUST0024 Multi-Service Agreement 1 | E39: Multi-Service Agreement | F39: Upcoming Renewal | G39: 44958 | H39: 44958 | I39: 46038 | J39: 46293 | K39: 36 | L39: 120 | M39: 44 | N39: 1 | O39: 3 | P39: 0 | Q39: 1 | R39: 1 | S39: Renewal due within 60 days | T39: Schedule renewal and service-value review | U39: 8558 | V39: 102696 | W39: 41794.2 | X39: Low | Y39: 46249
A40: CTR-0025-01 | B40: CUST0025 | C40: SP006 | D40: CUST0025 Multi-Service Agreement 1 | E40: Multi-Service Agreement | F40: Expired - Needs Review | G40: 45945 | H40: 45945 | I40: 46665 | J40: 46076 | K40: 24 | L40: 120 | M40: -173 | N40: 0 | O40: 3 | P40: 0 | Q40: 1 | R40: 1 | S40: Contract has passed end date and appears to be rolling or needs review | T40: Immediate contract health check and renewal confirmation | U40: 3788 | V40: 45456 | W40: 14810.16 | X40: Medium | Y40: 46249
A41: CTR-0026-01 | B41: CUST0026 | C41: SP006 | D41: CUST0026 Telco Agreement 1 | E41: Telco Agreement | F41: Active | G41: 45108 | H41: 45108 | I41: 45828 | J41: 46549 | K41: 24 | L41: 120 | M41: 300 | N41: 0 | O41: 0 | P41: 0 | Q41: 1 | R41: 0 | T41: Monitor | U41: 2302 | V41: 27624 | W41: 8839.68 | X41: Low | Y41: 46249
A42: CTR-0027-01 | B42: CUST0027 | C42: SP008 | D42: CUST0027 Support Agreement 1 | E42: Support Agreement | F42: Upcoming Renewal | G42: 45245 | H42: 45245 | I42: 46325 | J42: 46259 | K42: 36 | L42: 120 | M42: 10 | N42: 1 | O42: 3 | P42: 1 | Q42: 1 | R42: 1 | S42: Renewal due within 30 days | T42: Urgent customer renewal health check | U42: 775 | V42: 9300 | W42: 2976 | X42: High | Y42: 46249
A43: CTR-0028-01 | B43: CUST0028 | C43: SP003 | D43: CUST0028 Support Agreement 1 | E43: Support Agreement | F43: Upcoming Renewal | G43: 45641 | H43: 45641 | I43: 46361 | J43: 46330 | K43: 24 | L43: 120 | M43: 81 | N43: 1 | O43: 3 | P43: 1 | Q43: 1 | R43: 1 | S43: Renewal due within 120 days | T43: Plan proactive health check and whitespace review | U43: 1358.77 | V43: 16305.24 | W43: 4891.56 | X43: High | Y43: 46249
A44: CTR-0029-01 | B44: CUST0029 | C44: SP008 | D44: CUST0029 Multi-Service Agreement 1 | E44: Multi-Service Agreement | F44: Active | G44: 45536 | H44: 45536 | I44: 46256 | J44: 46523 | K44: 24 | L44: 120 | M44: 274 | N44: 1 | O44: 0 | P44: 0 | Q44: 0 | R44: 0 | T44: Monitor | U44: 10305 | V44: 123660 | W44: 52878.6 | X44: Low | Y44: 46249
A45: CTR-0030-01 | B45: CUST0030 | C45: SP002 | D45: CUST0030 Multi-Service Agreement 1 | E45: Multi-Service Agreement | F45: Active | G45: 45689 | H45: 45689 | I45: 46409 | J45: 46502 | K45: 24 | L45: 120 | M45: 253 | N45: 1 | O45: 0 | P45: 0 | Q45: 1 | R45: 0 | T45: Monitor | U45: 800 | V45: 9600 | W45: 3456 | X45: Low | Y45: 46249
A46: CTR-0030-02 | B46: CUST0030 | C46: SP002 | D46: CUST0030 Managed Service Agreement 2 | E46: Managed Service Agreement | F46: Upcoming Renewal | G46: 44958 | H46: 44958 | I46: 46038 | J46: 46302 | K46: 36 | L46: 120 | M46: 53 | N46: 1 | O46: 1 | P46: 1 | Q46: 1 | R46: 1 | S46: Renewal due within 60 days | T46: Schedule renewal and service-value review | U46: 9723 | V46: 116676 | W46: 47837.16 | X46: Medium | Y46: 46249
A47: CTR-0031-01 | B47: CUST0031 | C47: SP001 | D47: CUST0031 Multi-Service Agreement 1 | E47: Multi-Service Agreement | F47: Active | G47: 45915 | H47: 45915 | I47: 46275 | J47: 46725 | K47: 12 | L47: 120 | M47: 476 | N47: 0 | O47: 1 | P47: 0 | Q47: 1 | R47: 0 | T47: Monitor | U47: 9809 | V47: 117708 | W47: 53409 | X47: Low | Y47: 46249
A48: CTR-0032-01 | B48: CUST0032 | C48: SP003 | D48: CUST0032 Multi-Service Agreement 1 | E48: Multi-Service Agreement | F48: Upcoming Renewal | G48: 45292 | H48: 45292 | I48: 46012 | J48: 46279 | K48: 24 | L48: 120 | M48: 30 | N48: 1 | O48: 1 | P48: 0 | Q48: 0 | R48: 1 | S48: Renewal due within 30 days | T48: Urgent customer renewal health check | U48: 2785 | V48: 33420 | W48: 13748.64 | X48: Medium | Y48: 46249
A49: CTR-0033-01 | B49: CUST0033 | C49: SP002 | D49: CUST0033 Multi-Service Agreement 1 | E49: Multi-Service Agreement | F49: Active | G49: 45641 | H49: 45641 | I49: 46001 | J49: 46881 | K49: 12 | L49: 120 | M49: 632 | N49: 1 | O49: 1 | P49: 1 | Q49: 1 | R49: 0 | T49: Monitor | U49: 6198 | V49: 74376 | W49: 34956.72 | X49: Low | Y49: 46249
A50: CTR-0033-02 | B50: CUST0033 | C50: SP002 | D50: CUST0033 Multi-Service Agreement 2 | E50: Multi-Service Agreement | F50: Active | G50: 45047 | H50: 45047 | I50: 46127 | J50: 46630 | K50: 36 | L50: 120 | M50: 381 | N50: 1 | O50: 1 | P50: 0 | Q50: 0 | R50: 0 | T50: Monitor | U50: 9519 | V50: 114228 | W50: 45691.2 | X50: Low | Y50: 46249
A51: CTR-0034-01 | B51: CUST0034 | C51: SP006 | D51: CUST0034 Managed Service Agreement 1 | E51: Managed Service Agreement | F51: Active | G51: 45962 | H51: 45962 | I51: 46322 | J51: 46888 | K51: 12 | L51: 120 | M51: 639 | N51: 1 | O51: 0 | P51: 0 | Q51: 1 | R51: 0 | T51: Monitor | U51: 0 | V51: 0 | W51: 0 | X51: Low | Y51: 46249
A52: CTR-0034-02 | B52: CUST0034 | C52: SP006 | D52: CUST0034 Managed Service Agreement 2 | E52: Managed Service Agreement | F52: Upcoming Renewal | G52: 45658 | H52: 45658 | I52: 46018 | J52: 46289 | K52: 12 | L52: 120 | M52: 40 | N52: 0 | O52: 2 | P52: 0 | Q52: 1 | R52: 1 | S52: Renewal due within 60 days | T52: Schedule renewal and service-value review | U52: 8604 | V52: 103248 | W52: 44396.64 | X52: Low | Y52: 46249
A53: CTR-0034-03 | B53: CUST0034 | C53: SP006 | D53: CUST0034 Telco Agreement 3 | E53: Telco Agreement | F53: Upcoming Renewal | G53: 45139 | H53: 45139 | I53: 46219 | J53: 46360 | K53: 36 | L53: 120 | M53: 111 | N53: 1 | O53: 4 | P53: 0 | Q53: 1 | R53: 1 | S53: Renewal due within 120 days | T53: Plan proactive health check and whitespace review | U53: 2458 | V53: 29496 | W53: 9438.72 | X53: High | Y53: 46249
A54: CTR-0035-01 | B54: CUST0035 | C54: SP008 | D54: CUST0035 Multi-Service Agreement 1 | E54: Multi-Service Agreement | F54: Expired - Rolling | G54: 44972 | H54: 44972 | I54: 45332 | J54: 46127 | K54: 12 | L54: 120 | M54: -122 | N54: 0 | O54: 2 | P54: 0 | Q54: 1 | R54: 1 | S54: Contract has passed end date and appears to be rolling or needs review | T54: Immediate contract health check and renewal confirmation | U54: 4393.85 | V54: 52726.2 | W54: 25308.6 | X54: High | Y54: 46249
A55: CTR-0036-01 | B55: CUST0036 | C55: SP004 | D55: CUST0036 Multi-Service Agreement 1 | E55: Multi-Service Agreement | F55: Active | G55: 45292 | H55: 45292 | I55: 46012 | J55: 46924 | K55: 24 | L55: 120 | M55: 675 | N55: 0 | O55: 0 | P55: 0 | Q55: 1 | R55: 0 | T55: Monitor | U55: 1471.38 | V55: 17656.56 | W55: 6166.32 | X55: Low | Y55: 46249
A56: CTR-0036-02 | B56: CUST0036 | C56: SP004 | D56: CUST0036 Managed Service Agreement 2 | E56: Managed Service Agreement | F56: Expired - Needs Review | G56: 45078 | H56: 45078 | I56: 45438 | J56: 46093 | K56: 12 | L56: 120 | M56: -156 | N56: 1 | O56: 0 | P56: 0 | Q56: 1 | R56: 1 | S56: Contract has passed end date and appears to be rolling or needs review | T56: Immediate contract health check and renewal confirmation | U56: 3148.62 | V56: 37783.44 | W56: 18136.08 | X56: High | Y56: 46249
A57: CTR-0037-01 | B57: CUST0037 | C57: SP009 | D57: CUST0037 Multi-Service Agreement 1 | E57: Multi-Service Agreement | F57: Active | G57: 45292 | H57: 45292 | I57: 45652 | J57: 46757 | K57: 12 | L57: 120 | M57: 508 | N57: 1 | O57: 4 | P57: 0 | Q57: 1 | R57: 0 | T57: Monitor | U57: 7933 | V57: 95196 | W57: 40934.28 | X57: Low | Y57: 46249
A58: CTR-0038-01 | B58: CUST0038 | C58: SP009 | D58: CUST0038 Telco Agreement 1 | E58: Telco Agreement | F58: Upcoming Renewal | G58: 45413 | H58: 45413 | I58: 46133 | J58: 46342 | K58: 24 | L58: 120 | M58: 93 | N58: 1 | O58: 0 | P58: 0 | Q58: 0 | R58: 1 | S58: Renewal due within 120 days | T58: Plan proactive health check and whitespace review | U58: 522 | V58: 6264 | W58: 2380.32 | X58: Medium | Y58: 46249
A59: CTR-0038-02 | B59: CUST0038 | C59: SP009 | D59: CUST0038 Multi-Service Agreement 2 | E59: Multi-Service Agreement | F59: Expired - Rolling | G59: 45108 | H59: 45108 | I59: 46188 | J59: 46114 | K59: 36 | L59: 120 | M59: -135 | N59: 1 | O59: 0 | P59: 0 | Q59: 0 | R59: 1 | S59: Contract has passed end date and appears to be rolling or needs review | T59: Immediate contract health check and renewal confirmation | U59: 3900 | V59: 46800 | W59: 19410.6 | X59: High | Y59: 46249
A60: CTR-0039-01 | B60: CUST0039 | C60: SP005 | D60: CUST0039 Managed Service Agreement 1 | E60: Managed Service Agreement | F60: Active | G60: 45458 | H60: 45458 | I60: 45818 | J60: 46724 | K60: 12 | L60: 120 | M60: 475 | N60: 0 | O60: 2 | P60: 1 | Q60: 1 | R60: 0 | T60: Monitor | U60: 1059 | V60: 12708 | W60: 4956.12 | X60: Low | Y60: 46249
A61: CTR-0039-02 | B61: CUST0039 | C61: SP005 | D61: CUST0039 Support Agreement 2 | E61: Support Agreement | F61: Active | G61: 45792 | H61: 45792 | I61: 46872 | J61: 46497 | K61: 36 | L61: 120 | M61: 248 | N61: 1 | O61: 3 | P61: 1 | Q61: 1 | R61: 0 | T61: Monitor | U61: 6184 | V61: 74208 | W61: 34135.68 | X61: Low | Y61: 46249
A62: CTR-0040-01 | B62: CUST0040 | C62: SP008 | D62: CUST0040 Support Agreement 1 | E62: Support Agreement | F62: Expired - Rolling | G62: 45153 | H62: 45153 | I62: 45513 | J62: 46137 | K62: 12 | L62: 120 | M62: -112 | N62: 0 | O62: 0 | P62: 0 | Q62: 0 | R62: 1 | S62: Contract has passed end date and appears to be rolling or needs review | T62: Immediate contract health check and renewal confirmation | U62: 0 | V62: 0 | W62: 0 | X62: High | Y62: 46249
A63: CTR-0040-02 | B63: CUST0040 | C63: SP008 | D63: CUST0040 Managed Service Agreement 2 | E63: Managed Service Agreement | F63: Upcoming Renewal | G63: 45337 | H63: 45337 | I63: 45697 | J63: 46288 | K63: 12 | L63: 120 | M63: 39 | N63: 1 | O63: 1 | P63: 0 | Q63: 0 | R63: 1 | S63: Renewal due within 60 days | T63: Schedule renewal and service-value review | U63: 6364 | V63: 76368 | W63: 31310.88 | X63: Low | Y63: 46249
A64: CTR-0040-03 | B64: CUST0040 | C64: SP008 | D64: CUST0040 Multi-Service Agreement 3 | E64: Multi-Service Agreement | F64: Expired - Needs Review | G64: 45337 | H64: 45337 | I64: 46057 | J64: 46245 | K64: 24 | L64: 120 | M64: -4 | N64: 1 | O64: 1 | P64: 0 | Q64: 1 | R64: 1 | S64: Contract has passed end date and appears to be rolling or needs review | T64: Immediate contract health check and renewal confirmation | U64: 5675 | V64: 68100 | W64: 25302.96 | X64: High | Y64: 46249
A65: CTR-0041-01 | B65: CUST0041 | C65: SP008 | D65: CUST0041 Support Agreement 1 | E65: Support Agreement | F65: Upcoming Renewal | G65: 45000 | H65: 45000 | I65: 45720 | J65: 46356 | K65: 24 | L65: 120 | M65: 107 | N65: 1 | O65: 1 | P65: 0 | Q65: 1 | R65: 1 | S65: Renewal due within 120 days | T65: Plan proactive health check and whitespace review | U65: 1579 | V65: 18948 | W65: 8337.12 | X65: High | Y65: 46249
A66: CTR-0042-01 | B66: CUST0042 | C66: SP007 | D66: CUST0042 Telco Agreement 1 | E66: Telco Agreement | F66: Active | G66: 45748 | H66: 45748 | I66: 46828 | J66: 46558 | K66: 36 | L66: 120 | M66: 309 | N66: 1 | O66: 0 | P66: 0 | Q66: 1 | R66: 0 | T66: Monitor | U66: 3053 | V66: 36636 | W66: 12456.24 | X66: Low | Y66: 46249
A67: CTR-0042-02 | B67: CUST0042 | C67: SP007 | D67: CUST0042 Managed Service Agreement 2 | E67: Managed Service Agreement | F67: Active | G67: 45200 | H67: 45200 | I67: 45920 | J67: 46450 | K67: 24 | L67: 120 | M67: 201 | N67: 0 | O67: 1 | P67: 0 | Q67: 1 | R67: 0 | T67: Monitor | U67: 2188 | V67: 26256 | W67: 9977.28 | X67: Low | Y67: 46249
A68: CTR-0043-01 | B68: CUST0043 | C68: SP005 | D68: CUST0043 Managed Service Agreement 1 | E68: Managed Service Agreement | F68: Expired - Needs Review | G68: 45931 | H68: 45931 | I68: 46291 | J68: 46247 | K68: 12 | L68: 120 | M68: -2 | N68: 0 | O68: 1 | P68: 0 | Q68: 1 | R68: 1 | S68: Contract has passed end date and appears to be rolling or needs review | T68: Immediate contract health check and renewal confirmation | U68: 0 | V68: 0 | W68: 0 | X68: High | Y68: 46249
A69: CTR-0043-02 | B69: CUST0043 | C69: SP005 | D69: CUST0043 Multi-Service Agreement 2 | E69: Multi-Service Agreement | F69: Upcoming Renewal | G69: 45017 | H69: 45017 | I69: 45737 | J69: 46303 | K69: 24 | L69: 120 | M69: 54 | N69: 1 | O69: 0 | P69: 0 | Q69: 1 | R69: 1 | S69: Renewal due within 60 days | T69: Schedule renewal and service-value review | U69: 8622 | V69: 103464 | W69: 46510.56 | X69: Medium | Y69: 46249
A70: CTR-0043-03 | B70: CUST0043 | C70: SP005 | D70: CUST0043 Support Agreement 3 | E70: Support Agreement | F70: Active | G70: 45214 | H70: 45214 | I70: 46294 | J70: 46661 | K70: 36 | L70: 120 | M70: 412 | N70: 1 | O70: 1 | P70: 0 | Q70: 0 | R70: 0 | T70: Monitor | U70: 5716 | V70: 68592 | W70: 30866.4 | X70: Low | Y70: 46249
A71: CTR-0044-01 | B71: CUST0044 | C71: SP010 | D71: CUST0044 Multi-Service Agreement 1 | E71: Multi-Service Agreement | F71: Expired - Needs Review | G71: 44927 | H71: 44927 | I71: 45647 | J71: 46149 | K71: 24 | L71: 120 | M71: -100 | N71: 0 | O71: 2 | P71: 0 | Q71: 1 | R71: 1 | S71: Contract has passed end date and appears to be rolling or needs review | T71: Immediate contract health check and renewal confirmation | U71: 4812 | V71: 57744 | W71: 25984.8 | X71: Medium | Y71: 46249
A72: CTR-0044-02 | B72: CUST0044 | C72: SP010 | D72: CUST0044 Managed Service Agreement 2 | E72: Managed Service Agreement | F72: Active | G72: 45306 | H72: 45306 | I72: 46026 | J72: 46628 | K72: 24 | L72: 120 | M72: 379 | N72: 1 | O72: 2 | P72: 0 | Q72: 1 | R72: 0 | T72: Monitor | U72: 5456 | V72: 65472 | W72: 32081.28 | X72: Low | Y72: 46249
A73: CTR-0045-01 | B73: CUST0045 | C73: SP004 | D73: CUST0045 Multi-Service Agreement 1 | E73: Multi-Service Agreement | F73: Active | G73: 45597 | H73: 45597 | I73: 46317 | J73: 46546 | K73: 24 | L73: 120 | M73: 297 | N73: 0 | O73: 4 | P73: 1 | Q73: 1 | R73: 0 | T73: Monitor | U73: 5206 | V73: 62472 | W73: 22753.44 | X73: Low | Y73: 46249
A74: CTR-0045-02 | B74: CUST0045 | C74: SP004 | D74: CUST0045 Telco Agreement 2 | E74: Telco Agreement | F74: Active | G74: 45122 | H74: 45122 | I74: 45482 | J74: 46531 | K74: 12 | L74: 120 | M74: 282 | N74: 0 | O74: 0 | P74: 0 | Q74: 1 | R74: 0 | T74: Monitor | U74: 3544 | V74: 42528 | W74: 14034.24 | X74: Low | Y74: 46249
A75: CTR-0046-01 | B75: CUST0046 | C75: SP003 | D75: CUST0046 Multi-Service Agreement 1 | E75: Multi-Service Agreement | F75: Upcoming Renewal | G75: 45792 | H75: 45792 | I75: 46512 | J75: 46340 | K75: 24 | L75: 120 | M75: 91 | N75: 1 | O75: 2 | P75: 1 | Q75: 1 | R75: 1 | S75: Renewal due within 120 days | T75: Plan proactive health check and whitespace review | U75: 5128 | V75: 61536 | W75: 27075.84 | X75: High | Y75: 46249
A76: CTR-0047-01 | B76: CUST0047 | C76: SP010 | D76: CUST0047 Multi-Service Agreement 1 | E76: Multi-Service Agreement | F76: Upcoming Renewal | G76: 45275 | H76: 45275 | I76: 46355 | J76: 46315 | K76: 36 | L76: 120 | M76: 66 | N76: 0 | O76: 1 | P76: 1 | Q76: 1 | R76: 1 | S76: Renewal due within 120 days | T76: Plan proactive health check and whitespace review | U76: 7084 | V76: 85008 | W76: 31344.72 | X76: Low | Y76: 46249
A77: CTR-0048-01 | B77: CUST0048 | C77: SP004 | D77: CUST0048 Telco Agreement 1 | E77: Telco Agreement | F77: Active | G77: 45092 | H77: 45092 | I77: 45812 | J77: 46902 | K77: 24 | L77: 120 | M77: 653 | N77: 1 | O77: 0 | P77: 0 | Q77: 1 | R77: 0 | T77: Monitor | U77: 706 | V77: 8472 | W77: 2795.76 | X77: Low | Y77: 46249
A78: CTR-0048-02 | B78: CUST0048 | C78: SP004 | D78: CUST0048 Multi-Service Agreement 2 | E78: Multi-Service Agreement | F78: Upcoming Renewal | G78: 46006 | H78: 46006 | I78: 46366 | J78: 46279 | K78: 12 | L78: 120 | M78: 30 | N78: 1 | O78: 2 | P78: 0 | Q78: 1 | R78: 1 | S78: Renewal due within 30 days | T78: Urgent customer renewal health check | U78: 0 | V78: 0 | W78: 0 | X78: Low | Y78: 46249
A79: CTR-0048-03 | B79: CUST0048 | C79: SP004 | D79: CUST0048 Managed Service Agreement 3 | E79: Managed Service Agreement | F79: Active | G79: 45092 | H79: 45092 | I79: 45452 | J79: 46883 | K79: 12 | L79: 120 | M79: 634 | N79: 1 | O79: 1 | P79: 0 | Q79: 1 | R79: 0 | T79: Monitor | U79: 9282 | V79: 111384 | W79: 45667.44 | X79: Low | Y79: 46249
A80: CTR-0049-01 | B80: CUST0049 | C80: SP001 | D80: CUST0049 Multi-Service Agreement 1 | E80: Multi-Service Agreement | F80: Expired - Rolling | G80: 45323 | H80: 45323 | I80: 45683 | J80: 46132 | K80: 12 | L80: 120 | M80: -117 | N80: 1 | O80: 2 | P80: 1 | Q80: 1 | R80: 1 | S80: Contract has passed end date and appears to be rolling or needs review | T80: Immediate contract health check and renewal confirmation | U80: 2929 | V80: 35148 | W80: 11815.44 | X80: Medium | Y80: 46249
A81: CTR-0049-02 | B81: CUST0049 | C81: SP001 | D81: CUST0049 Managed Service Agreement 2 | E81: Managed Service Agreement | F81: Expired - Rolling | G81: 45884 | H81: 45884 | I81: 46244 | J81: 46105 | K81: 12 | L81: 120 | M81: -144 | N81: 0 | O81: 2 | P81: 0 | Q81: 1 | R81: 1 | S81: Contract has passed end date and appears to be rolling or needs review | T81: Immediate contract health check and renewal confirmation | U81: 1471 | V81: 17652 | W81: 7060.8 | X81: Low | Y81: 46249
A82: CTR-0050-01 | B82: CUST0050 | C82: SP002 | D82: CUST0050 Multi-Service Agreement 1 | E82: Multi-Service Agreement | F82: Upcoming Renewal | G82: 45870 | H82: 45870 | I82: 46230 | J82: 46283 | K82: 12 | L82: 120 | M82: 34 | N82: 1 | O82: 2 | P82: 2 | Q82: 1 | R82: 1 | S82: Renewal due within 60 days | T82: Schedule renewal and service-value review | U82: 8573 | V82: 102876 | W82: 46089.96 | X82: High | Y82: 46249
A83: CTR-0050-02 | B83: CUST0050 | C83: SP002 | D83: CUST0050 Multi-Service Agreement 2 | E83: Multi-Service Agreement | F83: Upcoming Renewal | G83: 45474 | H83: 45474 | I83: 46194 | J83: 46260 | K83: 24 | L83: 120 | M83: 11 | N83: 1 | O83: 2 | P83: 0 | Q83: 1 | R83: 1 | S83: Renewal due within 30 days | T83: Urgent customer renewal health check | U83: 4081.54 | V83: 48978.48 | W83: 16757.16 | X83: High | Y83: 46249
A84: CTR-0051-01 | B84: CUST0051 | C84: SP007 | D84: CUST0051 Multi-Service Agreement 1 | E84: Multi-Service Agreement | F84: Active | G84: 45214 | H84: 45214 | I84: 45934 | J84: 46446 | K84: 24 | L84: 120 | M84: 197 | N84: 1 | O84: 0 | P84: 0 | Q84: 1 | R84: 0 | T84: Monitor | U84: 12781 | V84: 153372 | W84: 67667.88 | X84: Low | Y84: 46249
A85: CTR-0052-01 | B85: CUST0052 | C85: SP002 | D85: CUST0052 Multi-Service Agreement 1 | E85: Multi-Service Agreement | F85: Active | G85: 45474 | H85: 45474 | I85: 45834 | J85: 46717 | K85: 12 | L85: 120 | M85: 468 | N85: 1 | O85: 1 | P85: 0 | Q85: 1 | R85: 0 | T85: Monitor | U85: 5013 | V85: 60156 | W85: 22859.28 | X85: Low | Y85: 46249
A86: CTR-0053-01 | B86: CUST0053 | C86: SP008 | D86: CUST0053 Telco Agreement 1 | E86: Telco Agreement | F86: Expired - Needs Review | G86: 45823 | H86: 45823 | I86: 46543 | J86: 46192 | K86: 24 | L86: 120 | M86: -57 | N86: 0 | O86: 4 | P86: 0 | Q86: 1 | R86: 1 | S86: Contract has passed end date and appears to be rolling or needs review | T86: Immediate contract health check and renewal confirmation | U86: 754 | V86: 9048 | W86: 2895.36 | X86: High | Y86: 46249
A87: CTR-0053-02 | B87: CUST0053 | C87: SP008 | D87: CUST0053 Support Agreement 2 | E87: Support Agreement | F87: Upcoming Renewal | G87: 45597 | H87: 45597 | I87: 46677 | J87: 46296 | K87: 36 | L87: 120 | M87: 47 | N87: 0 | O87: 0 | P87: 0 | Q87: 1 | R87: 1 | S87: Renewal due within 60 days | T87: Schedule renewal and service-value review | U87: 6681 | V87: 80172 | W87: 35275.68 | X87: Low | Y87: 46249
A88: CTR-0053-03 | B88: CUST0053 | C88: SP008 | D88: CUST0053 Telco Agreement 3 | E88: Telco Agreement | F88: Upcoming Renewal | G88: 45427 | H88: 45427 | I88: 45787 | J88: 46257 | K88: 12 | L88: 120 | M88: 8 | N88: 1 | O88: 1 | P88: 0 | Q88: 1 | R88: 1 | S88: Renewal due within 30 days | T88: Urgent customer renewal health check | U88: 665 | V88: 7980 | W88: 2793 | X88: Low | Y88: 46249
A89: CTR-0054-01 | B89: CUST0054 | C89: SP006 | D89: CUST0054 Managed Service Agreement 1 | E89: Managed Service Agreement | F89: Expired - Rolling | G89: 45397 | H89: 45397 | I89: 45757 | J89: 46139 | K89: 12 | L89: 120 | M89: -110 | N89: 1 | O89: 1 | P89: 0 | Q89: 1 | R89: 1 | S89: Contract has passed end date and appears to be rolling or needs review | T89: Immediate contract health check and renewal confirmation | U89: 8158 | V89: 97896 | W89: 46990.08 | X89: High | Y89: 46249
A90: CTR-0055-01 | B90: CUST0055 | C90: SP004 | D90: CUST0055 Managed Service Agreement 1 | E90: Managed Service Agreement | F90: Upcoming Renewal | G90: 45292 | H90: 45292 | I90: 45652 | J90: 46346 | K90: 12 | L90: 120 | M90: 97 | N90: 1 | O90: 2 | P90: 1 | Q90: 1 | R90: 1 | S90: Renewal due within 120 days | T90: Plan proactive health check and whitespace review | U90: 2712 | V90: 32544 | W90: 12366.72 | X90: Low | Y90: 46249
A91: CTR-0055-02 | B91: CUST0055 | C91: SP004 | D91: CUST0055 Telco Agreement 2 | E91: Telco Agreement | F91: Active | G91: 44941 | H91: 44941 | I91: 45661 | J91: 46378 | K91: 24 | L91: 120 | M91: 129 | N91: 0 | O91: 2 | P91: 1 | Q91: 1 | R91: 0 | T91: Monitor | U91: 879 | V91: 10548 | W91: 3797.28 | X91: Low | Y91: 46249
A92: CTR-0056-01 | B92: CUST0056 | C92: SP009 | D92: CUST0056 Support Agreement 1 | E92: Support Agreement | F92: Active | G92: 45597 | H92: 45597 | I92: 45957 | J92: 46584 | K92: 12 | L92: 120 | M92: 335 | N92: 0 | O92: 1 | P92: 0 | Q92: 0 | R92: 0 | T92: Monitor | U92: 2621 | V92: 31452 | W92: 14467.92 | X92: Low | Y92: 46249
A93: CTR-0056-02 | B93: CUST0056 | C93: SP009 | D93: CUST0056 Support Agreement 2 | E93: Support Agreement | F93: Upcoming Renewal | G93: 45444 | H93: 45444 | I93: 46524 | J93: 46324 | K93: 36 | L93: 120 | M93: 75 | N93: 0 | O93: 1 | P93: 1 | Q93: 1 | R93: 1 | S93: Renewal due within 120 days | T93: Plan proactive health check and whitespace review | U93: 425 | V93: 5100 | W93: 1530 | X93: Medium | Y93: 46249
A94: CTR-0056-03 | B94: CUST0056 | C94: SP009 | D94: CUST0056 Multi-Service Agreement 3 | E94: Multi-Service Agreement | F94: Upcoming Renewal | G94: 45870 | H94: 45870 | I94: 46590 | J94: 46346 | K94: 24 | L94: 120 | M94: 97 | N94: 1 | O94: 2 | P94: 0 | Q94: 1 | R94: 1 | S94: Renewal due within 120 days | T94: Plan proactive health check and whitespace review | U94: 7189 | V94: 86268 | W94: 32994 | X94: High | Y94: 46249
A95: CTR-0057-01 | B95: CUST0057 | C95: SP003 | D95: CUST0057 Multi-Service Agreement 1 | E95: Multi-Service Agreement | F95: Active | G95: 45870 | H95: 45870 | I95: 46950 | J95: 46539 | K95: 36 | L95: 120 | M95: 290 | N95: 0 | O95: 0 | P95: 0 | Q95: 1 | R95: 0 | T95: Monitor | U95: 2272 | V95: 27264 | W95: 8451.84 | X95: Low | Y95: 46249
A96: CTR-0058-01 | B96: CUST0058 | C96: SP005 | D96: CUST0058 Multi-Service Agreement 1 | E96: Multi-Service Agreement | F96: Active | G96: 45931 | H96: 45931 | I96: 46291 | J96: 46936 | K96: 12 | L96: 120 | M96: 687 | N96: 0 | O96: 2 | P96: 0 | Q96: 1 | R96: 0 | T96: Monitor | U96: 8642 | V96: 103704 | W96: 40234.08 | X96: Low | Y96: 46249
A97: CTR-0058-02 | B97: CUST0058 | C97: SP005 | D97: CUST0058 Managed Service Agreement 2 | E97: Managed Service Agreement | F97: Active | G97: 45292 | H97: 45292 | I97: 46372 | J97: 46622 | K97: 36 | L97: 120 | M97: 373 | N97: 1 | O97: 1 | P97: 0 | Q97: 1 | R97: 0 | T97: Monitor | U97: 4838 | V97: 58056 | W97: 22061.28 | X97: Low | Y97: 46249
A98: CTR-0059-01 | B98: CUST0059 | C98: SP010 | D98: CUST0059 Multi-Service Agreement 1 | E98: Multi-Service Agreement | F98: Active | G98: 45017 | H98: 45017 | I98: 45377 | J98: 46521 | K98: 12 | L98: 120 | M98: 272 | N98: 1 | O98: 3 | P98: 1 | Q98: 1 | R98: 0 | T98: Monitor | U98: 3336 | V98: 40032 | W98: 17614.08 | X98: Low | Y98: 46249
A99: CTR-0060-01 | B99: CUST0060 | C99: SP003 | D99: CUST0060 Telco Agreement 1 | E99: Telco Agreement | F99: Active | G99: 45323 | H99: 45323 | I99: 46403 | J99: 46835 | K99: 36 | L99: 120 | M99: 586 | N99: 0 | O99: 0 | P99: 0 | Q99: 0 | R99: 0 | T99: Monitor | U99: 3299 | V99: 39588 | W99: 13064.04 | X99: Low | Y99: 46249
A100: CTR-0060-02 | B100: CUST0060 | C100: SP003 | D100: CUST0060 Telco Agreement 2 | E100: Telco Agreement | F100: Upcoming Renewal | G100: 45153 | H100: 45153 | I100: 45873 | J100: 46362 | K100: 24 | L100: 120 | M100: 113 | N100: 1 | O100: 3 | P100: 0 | Q100: 1 | R100: 1 | S100: Renewal due within 120 days | T100: Plan proactive health check and whitespace review | U100: 1059 | V100: 12708 | W100: 4701.96 | X100: Medium | Y100: 46249
...

Sheet ContractServices
A1: ContractServiceID | B1: ContractID | C1: CustomerID | D1: ServiceCategory | E1: Service | F1: AccountOwnerID | G1: BillingFrequency | H1: ServiceMRR | I1: ServiceARR | J1: GrossMarginPct | K1: MonthlyGrossProfit | L1: ServiceStatus | M1: ServiceStartDate | N1: ServiceEndDate | O1: ServiceRole | P1: BillingContractServiceKey
A2: CSVC00001 | B2: CTR-0001-01 | C2: CUST0001 | D2: Support | E2: Telco Support | F2: SP001 | G2: Monthly | H2: 374.77 | I2: 4497.24 | J2: 0.31 | K2: 116.18 | L2: Pending Renewal | M2: 45962 | N2: 46112 | O2: Renewal service | P2: CUST0001|Telco Support
A3: CSVC00002 | B3: CTR-0002-01 | C3: CUST0002 | D3: Managed Services | E3: Modern Workplace | F3: SP004 | G3: Monthly | H3: 4678 | I3: 56136 | J3: 0.37 | K3: 1730.86 | L3: Pending Renewal | M3: 45597 | N3: 46282 | O3: Renewal service | P3: CUST0002|Modern Workplace
A4: CSVC00003 | B4: CTR-0002-01 | C4: CUST0002 | D4: Support | E4: Telco Support | F4: SP004 | G4: Annual | H4: 2323 | I4: 27876 | J4: 0.3 | K4: 696.9 | L4: Pending Renewal | M4: 45597 | N4: 46282 | O4: Core service | P4: CUST0002|Telco Support
A5: CSVC00004 | B5: CTR-0003-01 | C5: CUST0003 | D5: Telco | E5: Connectivity | F5: SP006 | G5: Monthly | H5: 2790 | I5: 33480 | J5: 0.3 | K5: 837 | L5: Pending Renewal | M5: 45017 | N5: 46331 | O5: Expansion service | P5: CUST0003|Connectivity
A6: CSVC00005 | B6: CTR-0004-01 | C6: CUST0004 | D6: Support | E6: Telco Support | F6: SP007 | G6: Quarterly | H6: 617 | I6: 7404 | J6: 0.32 | K6: 197.44 | L6: Active | M6: 45337 | N6: 46934 | O6: Core service | P6: CUST0004|Telco Support
A7: CSVC00006 | B7: CTR-0004-01 | C7: CUST0004 | D7: Support | E7: IT Support | F7: SP007 | G7: Annual | H7: 0 | I7: 0 | J7: 0.43 | K7: 0 | L7: Active | M7: 45337 | N7: 46934 | O7: Renewal service | P7: CUST0004|IT Support
A8: CSVC00007 | B8: CTR-0004-02 | C8: CUST0004 | D8: Telco | E8: Connectivity | F8: SP007 | G8: Quarterly | H8: 489 | I8: 5868 | J8: 0.32 | K8: 156.48 | L8: Pending Renewal | M8: 45337 | N8: 46259 | O8: Core service | P8: CUST0004|Connectivity
A9: CSVC00008 | B9: CTR-0004-02 | C9: CUST0004 | D9: Managed Services | E9: Cyber Security | F9: SP007 | G9: Annual | H9: 8278 | I9: 99336 | J9: 0.48 | K9: 3973.44 | L9: Pending Renewal | M9: 45337 | N9: 46259 | O9: Renewal service | P9: CUST0004|Cyber Security
A10: CSVC00009 | B10: CTR-0004-03 | C10: CUST0004 | D10: Managed Services | E10: Cloud IT | F10: SP007 | G10: Annual | H10: 8937 | I10: 107244 | J10: 0.42 | K10: 3753.54 | L10: Active | M10: 45792 | N10: 46736 | O10: Core service | P10: CUST0004|Cloud IT
A11: CSVC00010 | B11: CTR-0005-01 | C11: CUST0005 | D11: Support | E11: IT Support | F11: SP008 | G11: Annual | H11: 0 | I11: 0 | J11: 0.37 | K11: 0 | L11: Pending Renewal | M11: 45689 | N11: 46355 | O11: Core service | P11: CUST0005|IT Support
A12: CSVC00011 | B12: CTR-0005-01 | C12: CUST0005 | D12: Managed Services | E12: Modern Workplace | F12: SP008 | G12: Annual | H12: 5814 | I12: 69768 | J12: 0.39 | K12: 2267.46 | L12: Pending Renewal | M12: 45689 | N12: 46355 | O12: Core service | P12: CUST0005|Modern Workplace
A13: CSVC00012 | B13: CTR-0005-02 | C13: CUST0005 | D13: Telco | E13: Connectivity | F13: SP008 | G13: Annual | H13: 542 | I13: 6504 | J13: 0.31 | K13: 168.02 | L13: Pending Renewal | M13: 45703 | N13: 46259 | O13: Renewal service | P13: CUST0005|Connectivity
... A264: CSVC00263 | B264: CTR-0100-01 | C264: CUST0100 | D264: Support | E264: Telco Support | F264: SP006 | G264: Annual | H264: 436 | I264: 5232 | J264: 0.3 | K264: 130.8 | L264: Pending Renewal | M264: 45017 | N264: 46206 | O264: Renewal service | P264: CUST0100|Telco Support

Sheet ContractAuditLog
A1: AuditID | B1: ContractID | C1: CustomerID | D1: ChangeDate | E1: ChangedByRole | F1: ChangeType | G1: PreviousEndDate | H1: NewEndDate | I1: RollbackFlag | J1: RollbackReason | K1: DaysChanged | L1: ApprovalStatus | M1: SalespersonLinked | N1: ChangeReason
A2: AUD00001 | B2: CTR-0002-01 | C2: CUST0002 | D2: 45851 | E2: Account Manager | F2: Rollback | G2: 46317 | H2: 46317 | I2: 1 | J2: Rollback to previous agreed end date | K2: 0 | L2: Approved | M2: SP004 | N2: Renewal alignment
A3: AUD00002 | B3: CTR-0004-01 | C3: CUST0004 | D3: 45431 | E3: Commercial Director | F3: Commercial Amendment | G3: 45697 | H3: 45757 | I3: 0 | K3: 60 | L3: Approved | M3: SP007 | N3: Commercial negotiation
A4: AUD00003 | B4: CTR-0004-01 | C4: CUST0004 | D4: 45645 | E4: Commercial Director | F4: Commercial Amendment | G4: 45757 | H4: 45727 | I4: 0 | K4: -30 | L4: Pending Review | M4: SP007 | N4: Customer request
A5: AUD00004 | B5: CTR-0004-01 | C5: CUST0004 | D5: 45597 | E5: Sales Ops | F5: Rollback | G5: 45727 | H5: 45697 | I5: 1 | J5: Rollback to previous agreed end date | K5: -30 | L5: Pending Review | M5: SP007 | N5: Commercial negotiation
A6: AUD00005 | B6: CTR-0004-02 | C6: CUST0004 | D6: 46305 | E6: Finance | F6: Shortening | G6: 46417 | H6: 46387 | I6: 0 | K6: -30 | L6: Approved | M6: SP007 | N6: Customer request
A7: AUD00006 | B7: CTR-0004-02 | C7: CUST0004 | D7: 45617 | E7: Sales Ops | F7: Extension | G7: 46387 | H7: 46567 | I7: 0 | K7: 180 | L7: Pending Review | M7: SP007 | N7: Billing correction
A8: AUD00007 | B8: CTR-0005-02 | C8: CUST0005 | D8: 45949 | E8: Sales Ops | F8: Renewal Pushback | G8: 46063 | H8: 46093 | I8: 0 | K8: 30 | L8: Approved | M8: SP008 | N8: Commercial negotiation
A9: AUD00008 | B9: CTR-0005-02 | C9: CUST0005 | D9: 45979 | E9: Finance | F9: Commercial Amendment | G9: 46093 | H9: 46153 | I9: 0 | K9: 60 | L9: Pending Review | M9: SP008 | N9: Customer request
A10: AUD00009 | B10: CTR-0005-03 | C10: CUST0005 | D10: 45843 | E10: Commercial Director | F10: Commercial Amendment | G10: 46239 | H10: 46269 | I10: 0 | K10: 30 | L10: Approved | M10: SP008 | N10: Customer request
A11: AUD00010 | B11: CTR-0005-03 | C11: CUST0005 | D11: 46064 | E11: Sales Ops | F11: Commercial Amendment | G11: 46269 | H11: 46329 | I11: 0 | K11: 60 | L11: Approved | M11: SP008 | N11: Commercial negotiation
A12: AUD00011 | B12: CTR-0005-03 | C12: CUST0005 | D12: 46216 | E12: Account Manager | F12: Renewal Pushback | G12: 46329 | H12: 46419 | I12: 0 | K12: 90 | L12: Pending Review | M12: SP008 | N12: Internal correction
A13: AUD00012 | B13: CTR-0006-01 | C13: CUST0006 | D13: 45276 | E13: Sales Ops | F13: Shortening | G13: 45544 | H13: 45484 | I13: 0 | K13: -60 | L13: Approved | M13: SP006 | N13: Commercial negotiation
A14: AUD00013 | B14: CTR-0006-01 | C14: CUST0006 | D14: 45455 | E14: Account Manager | F14: Commercial Amendment | G14: 45484 | H14: 45544 | I14: 0 | K14: 60 | L14: Approved | M14: SP006 | N14: Internal correction
A15: AUD00014 | B15: CTR-0006-01 | C15: CUST0006 | D15: 45327 | E15: Commercial Director | F15: Extension | G15: 45544 | H15: 45574 | I15: 0 | K15: 30 | L15: Pending Review | M15: SP006 | N15: Billing correction
A16: AUD00015 | B16: CTR-0007-01 | C16: CUST0007 | D16: 45613 | E16: Sales Ops | F16: Rollback | G16: 45743 | H16: 45743 | I16: 1 | J16: Rollback to previous agreed end date | K16: 0 | L16: Pending Review | M16: SP006 | N16: Billing correction
A17: AUD00016 | B17: CTR-0008-02 | C17: CUST0008 | D17: 45585 | E17: Finance | F17: Rollback | G17: 45879 | H17: 45879 | I17: 1 | J17: Rollback to previous agreed end date | K17: 0 | L17: Approved | M17: SP003 | N17: Internal correction
A18: AUD00017 | B18: CTR-0008-03 | C18: CUST0008 | D18: 45040 | E18: Commercial Director | F18: Renewal Pushback | G18: 45720 | H18: 45750 | I18: 0 | K18: 30 | L18: Approved | M18: SP003 | N18: Customer request
A19: AUD00018 | B19: CTR-0011-01 | C19: CUST0011 | D19: 46118 | E19: Sales Ops | F19: Rollback | G19: 46696 | H19: 46696 | I19: 1 | J19: Rollback to previous agreed end date | K19: 0 | L19: Approved | M19: SP005 | N19: Internal correction
A20: AUD00019 | B20: CTR-0011-01 | C20: CUST0011 | D20: 46519 | E20: Account Manager | F20: Rollback | G20: 46696 | H20: 46696 | I20: 1 | J20: Rollback to previous agreed end date | K20: 0 | L20: Approved | M20: SP005 | N20: Billing correction
A21: AUD00020 | B21: CTR-0011-01 | C21: CUST0011 | D21: 46503 | E21: Account Manager | F21: Extension | G21: 46696 | H21: 46726 | I21: 0 | K21: 30 | L21: Approved | M21: SP005 | N21: Billing correction
A22: AUD00021 | B22: CTR-0016-01 | C22: CUST0016 | D22: 46203 | E22: Account Manager | F22: Extension | G22: 46244 | H22: 46304 | I22: 0 | K22: 60 | L22: Pending Review | M22: SP007 | N22: Renewal alignment
A23: AUD00022 | B23: CTR-0017-01 | C23: CUST0017 | D23: 45596 | E23: Commercial Director | F23: Renewal Pushback | G23: 45635 | H23: 45695 | I23: 0 | K23: 60 | L23: Pending Review | M23: SP005 | N23: Commercial negotiation
A24: AUD00023 | B24: CTR-0017-02 | C24: CUST0017 | D24: 46113 | E24: Commercial Director | F24: Rollback | G24: 46291 | H24: 46291 | I24: 1 | J24: Rollback to previous agreed end date | K24: 0 | L24: Approved | M24: SP005 | N24: Renewal alignment
A25: AUD00024 | B25: CTR-0017-02 | C25: CUST0017 | D25: 46037 | E25: Finance | F25: Extension | G25: 46291 | H25: 46471 | I25: 0 | K25: 180 | L25: Approved | M25: SP005 | N25: Customer request
A26: AUD00025 | B26: CTR-0018-02 | C26: CUST0018 | D26: 46116 | E26: Account Manager | F26: Renewal Pushback | G26: 46903 | H26: 46933 | I26: 0 | K26: 30 | L26: Approved | M26: SP004 | N26: Internal correction
A27: AUD00026 | B27: CTR-0018-02 | C27: CUST0018 | D27: 46613 | E27: Sales Ops | F27: Renewal Pushback | G27: 46933 | H27: 46963 | I27: 0 | K27: 30 | L27: Approved | M27: SP004 | N27: Customer request
A28: AUD00027 | B28: CTR-0018-02 | C28: CUST0018 | D28: 46127 | E28: Commercial Director | F28: Shortening | G28: 46963 | H28: 46933 | I28: 0 | K28: -30 | L28: Approved | M28: SP004 | N28: Commercial negotiation
A29: AUD00028 | B29: CTR-0018-02 | C29: CUST0018 | D29: 46535 | E29: Commercial Director | F29: Shortening | G29: 46933 | H29: 46873 | I29: 0 | K29: -60 | L29: Pending Review | M29: SP004 | N29: Billing correction
A30: AUD00029 | B30: CTR-0019-01 | C30: CUST0019 | D30: 46273 | E30: Sales Ops | F30: Rollback | G30: 46331 | H30: 46331 | I30: 1 | J30: Rollback to previous agreed end date | K30: 0 | L30: Pending Review | M30: SP002 | N30: Customer request
A31: AUD00030 | B31: CTR-0020-01 | C31: CUST0020 | D31: 45112 | E31: Sales Ops | F31: Extension | G31: 45391 | H31: 45481 | I31: 0 | K31: 90 | L31: Approved | M31: SP006 | N31: Internal correction
A32: AUD00031 | B32: CTR-0021-02 | C32: CUST0021 | D32: 46272 | E32: Finance | F32: Commercial Amendment | G32: 46858 | H32: 46918 | I32: 0 | K32: 60 | L32: Pending Review | M32: SP002 | N32: Billing correction
A33: AUD00032 | B33: CTR-0021-02 | C33: CUST0021 | D33: 46625 | E33: Account Manager | F33: Renewal Pushback | G33: 46918 | H33: 47008 | I33: 0 | K33: 90 | L33: Approved | M33: SP002 | N33: Customer request
A34: AUD00033 | B34: CTR-0021-02 | C34: CUST0021 | D34: 46696 | E34: Account Manager | F34: Extension | G34: 47008 | H34: 47038 | I34: 0 | K34: 30 | L34: Pending Review | M34: SP002 | N34: Commercial negotiation
A35: AUD00034 | B35: CTR-0022-01 | C35: CUST0022 | D35: 46087 | E35: Account Manager | F35: Rollback | G35: 46512 | H35: 46512 | I35: 1 | J35: Rollback to previous agreed end date | K35: 0 | L35: Approved | M35: SP009 | N35: Internal correction
A36: AUD00035 | B36: CTR-0023-01 | C36: CUST0023 | D36: 46069 | E36: Sales Ops | F36: Extension | G36: 46086 | H36: 46116 | I36: 0 | K36: 30 | L36: Approved | M36: SP006 | N36: Internal correction
A37: AUD00036 | B37: CTR-0024-01 | C37: CUST0024 | D37: 45252 | E37: Account Manager | F37: Extension | G37: 46038 | H37: 46068 | I37: 0 | K37: 30 | L37: Approved | M37: SP001 | N37: Billing correction
A38: AUD00037 | B38: CTR-0024-01 | C38: CUST0024 | D38: 45287 | E38: Sales Ops | F38: Renewal Pushback | G38: 46068 | H38: 46128 | I38: 0 | K38: 60 | L38: Pending Review | M38: SP001 | N38: Commercial negotiation
A39: AUD00038 | B39: CTR-0024-01 | C39: CUST0024 | D39: 45576 | E39: Sales Ops | F39: Shortening | G39: 46128 | H39: 46098 | I39: 0 | K39: -30 | L39: Approved | M39: SP001 | N39: Renewal alignment
A40: AUD00039 | B40: CTR-0025-01 | C40: CUST0025 | D40: 46126 | E40: Account Manager | F40: Shortening | G40: 46665 | H40: 46635 | I40: 0 | K40: -30 | L40: Approved | M40: SP006 | N40: Commercial negotiation
A41: AUD00040 | B41: CTR-0025-01 | C41: CUST0025 | D41: 45993 | E41: Finance | F41: Commercial Amendment | G41: 46635 | H41: 46695 | I41: 0 | K41: 60 | L41: Approved | M41: SP006 | N41: Commercial negotiation
A42: AUD00041 | B42: CTR-0025-01 | C42: CUST0025 | D42: 46487 | E42: Sales Ops | F42: Renewal Pushback | G42: 46695 | H42: 46755 | I42: 0 | K42: 60 | L42: Approved | M42: SP006 | N42: Internal correction
A43: AUD00042 | B43: CTR-0027-01 | C43: CUST0027 | D43: 46234 | E43: Commercial Director | F43: Extension | G43: 46325 | H43: 46415 | I43: 0 | K43: 90 | L43: Approved | M43: SP008 | N43: Commercial negotiation
A44: AUD00043 | B44: CTR-0027-01 | C44: CUST0027 | D44: 45699 | E44: Sales Ops | F44: Rollback | G44: 46415 | H44: 46325 | I44: 1 | J44: Rollback to previous agreed end date | K44: -90 | L44: Pending Review | M44: SP008 | N44: Renewal alignment
A45: AUD00044 | B45: CTR-0027-01 | C45: CUST0027 | D45: 45708 | E45: Account Manager | F45: Extension | G45: 46325 | H45: 46385 | I45: 0 | K45: 60 | L45: Approved | M45: SP008 | N45: Customer request
A46: AUD00045 | B46: CTR-0028-01 | C46: CUST0028 | D46: 45875 | E46: Sales Ops | F46: Commercial Amendment | G46: 46361 | H46: 46391 | I46: 0 | K46: 30 | L46: Approved | M46: SP003 | N46: Commercial negotiation
A47: AUD00046 | B47: CTR-0028-01 | C47: CUST0028 | D47: 46117 | E47: Commercial Director | F47: Renewal Pushback | G47: 46391 | H47: 46481 | I47: 0 | K47: 90 | L47: Approved | M47: SP003 | N47: Customer request
A48: AUD00047 | B48: CTR-0028-01 | C48: CUST0028 | D48: 45933 | E48: Sales Ops | F48: Rollback | G48: 46481 | H48: 46361 | I48: 1 | J48: Rollback to previous agreed end date | K48: -120 | L48: Approved | M48: SP003 | N48: Customer request
A49: AUD00048 | B49: CTR-0030-02 | C49: CUST0030 | D49: 45940 | E49: Account Manager | F49: Rollback | G49: 46038 | H49: 46038 | I49: 1 | J49: Rollback to previous agreed end date | K49: 0 | L49: Pending Review | M49: SP002 | N49: Internal correction
A50: AUD00049 | B50: CTR-0031-01 | C50: CUST0031 | D50: 46192 | E50: Sales Ops | F50: Commercial Amendment | G50: 46275 | H50: 46305 | I50: 0 | K50: 30 | L50: Approved | M50: SP001 | N50: Commercial negotiation
A51: AUD00050 | B51: CTR-0032-01 | C51: CUST0032 | D51: 45370 | E51: Sales Ops | F51: Extension | G51: 46012 | H51: 46102 | I51: 0 | K51: 90 | L51: Approved | M51: SP003 | N51: Internal correction
A52: AUD00051 | B52: CTR-0033-01 | C52: CUST0033 | D52: 45737 | E52: Sales Ops | F52: Rollback | G52: 46001 | H52: 46001 | I52: 1 | J52: Rollback to previous agreed end date | K52: 0 | L52: Approved | M52: SP002 | N52: Customer request
A53: AUD00052 | B53: CTR-0033-02 | C53: CUST0033 | D53: 45151 | E53: Finance | F53: Shortening | G53: 46127 | H53: 46037 | I53: 0 | K53: -90 | L53: Approved | M53: SP002 | N53: Renewal alignment
A54: AUD00053 | B54: CTR-0034-02 | C54: CUST0034 | D54: 45815 | E54: Account Manager | F54: Renewal Pushback | G54: 46018 | H54: 46108 | I54: 0 | K54: 90 | L54: Approved | M54: SP006 | N54: Billing correction
A55: AUD00054 | B55: CTR-0034-02 | C55: CUST0034 | D55: 45852 | E55: Account Manager | F55: Commercial Amendment | G55: 46108 | H55: 46138 | I55: 0 | K55: 30 | L55: Approved | M55: SP006 | N55: Commercial negotiation
A56: AUD00055 | B56: CTR-0034-03 | C56: CUST0034 | D56: 46093 | E56: Finance | F56: Commercial Amendment | G56: 46219 | H56: 46189 | I56: 0 | K56: -30 | L56: Pending Review | M56: SP006 | N56: Internal correction
A57: AUD00056 | B57: CTR-0034-03 | C57: CUST0034 | D57: 45775 | E57: Finance | F57: Renewal Pushback | G57: 46189 | H57: 46249 | I57: 0 | K57: 60 | L57: Pending Review | M57: SP006 | N57: Customer request
A58: AUD00057 | B58: CTR-0034-03 | C58: CUST0034 | D58: 45803 | E58: Sales Ops | F58: Renewal Pushback | G58: 46249 | H58: 46279 | I58: 0 | K58: 30 | L58: Approved | M58: SP006 | N58: Commercial negotiation
A59: AUD00058 | B59: CTR-0034-03 | C59: CUST0034 | D59: 45235 | E59: Sales Ops | F59: Renewal Pushback | G59: 46279 | H59: 46309 | I59: 0 | K59: 30 | L59: Approved | M59: SP006 | N59: Billing correction
A60: AUD00059 | B60: CTR-0035-01 | C60: CUST0035 | D60: 45317 | E60: Sales Ops | F60: Commercial Amendment | G60: 45332 | H60: 45302 | I60: 0 | K60: -30 | L60: Pending Review | M60: SP008 | N60: Commercial negotiation
A61: AUD00060 | B61: CTR-0035-01 | C61: CUST0035 | D61: 45308 | E61: Finance | F61: Commercial Amendment | G61: 45302 | H61: 45362 | I61: 0 | K61: 60 | L61: Approved | M61: SP008 | N61: Renewal alignment
A62: AUD00061 | B62: CTR-0037-01 | C62: CUST0037 | D62: 45582 | E62: Sales Ops | F62: Commercial Amendment | G62: 45652 | H62: 45682 | I62: 0 | K62: 30 | L62: Approved | M62: SP009 | N62: Commercial negotiation
A63: AUD00062 | B63: CTR-0037-01 | C63: CUST0037 | D63: 45567 | E63: Finance | F63: Commercial Amendment | G63: 45682 | H63: 45652 | I63: 0 | K63: -30 | L63: Approved | M63: SP009 | N63: Billing correction
A64: AUD00063 | B64: CTR-0037-01 | C64: CUST0037 | D64: 45467 | E64: Sales Ops | F64: Commercial Amendment | G64: 45652 | H64: 45622 | I64: 0 | K64: -30 | L64: Approved | M64: SP009 | N64: Internal correction
A65: AUD00064 | B65: CTR-0037-01 | C65: CUST0037 | D65: 45578 | E65: Commercial Director | F65: Commercial Amendment | G65: 45622 | H65: 45652 | I65: 0 | K65: 30 | L65: Approved | M65: SP009 | N65: Billing correction
A66: AUD00065 | B66: CTR-0039-01 | C66: CUST0039 | D66: 45512 | E66: Account Manager | F66: Rollback | G66: 45818 | H66: 45818 | I66: 1 | J66: Rollback to previous agreed end date | K66: 0 | L66: Pending Review | M66: SP005 | N66: Renewal alignment
A67: AUD00066 | B67: CTR-0039-01 | C67: CUST0039 | D67: 45666 | E67: Account Manager | F67: Shortening | G67: 45818 | H67: 45788 | I67: 0 | K67: -30 | L67: Pending Review | M67: SP005 | N67: Billing correction
A68: AUD00067 | B68: CTR-0039-02 | C68: CUST0039 | D68: 46158 | E68: Account Manager | F68: Extension | G68: 46872 | H68: 46932 | I68: 0 | K68: 60 | L68: Approved | M68: SP005 | N68: Renewal alignment
A69: AUD00068 | B69: CTR-0039-02 | C69: CUST0039 | D69: 46295 | E69: Account Manager | F69: Rollback | G69: 46932 | H69: 46872 | I69: 1 | J69: Rollback to previous agreed end date | K69: -60 | L69: Approved | M69: SP005 | N69: Renewal alignment
A70: AUD00069 | B70: CTR-0039-02 | C70: CUST0039 | D70: 46524 | E70: Commercial Director | F70: Commercial Amendment | G70: 46872 | H70: 46902 | I70: 0 | K70: 30 | L70: Approved | M70: SP005 | N70: Billing correction
A71: AUD00070 | B71: CTR-0040-02 | C71: CUST0040 | D71: 45382 | E71: Sales Ops | F71: Shortening | G71: 45697 | H71: 45667 | I71: 0 | K71: -30 | L71: Approved | M71: SP008 | N71: Internal correction
A72: AUD00071 | B72: CTR-0040-03 | C72: CUST0040 | D72: 45449 | E72: Finance | F72: Shortening | G72: 46057 | H72: 46027 | I72: 0 | K72: -30 | L72: Approved | M72: SP008 | N72: Commercial negotiation
A73: AUD00072 | B73: CTR-0041-01 | C73: CUST0041 | D73: 45354 | E73: Account Manager | F73: Shortening | G73: 45720 | H73: 45690 | I73: 0 | K73: -30 | L73: Approved | M73: SP008 | N73: Commercial negotiation
A74: AUD00073 | B74: CTR-0042-02 | C74: CUST0042 | D74: 45374 | E74: Finance | F74: Extension | G74: 45920 | H74: 46100 | I74: 0 | K74: 180 | L74: Approved | M74: SP007 | N74: Customer request
A75: AUD00074 | B75: CTR-0043-01 | C75: CUST0043 | D75: 46281 | E75: Finance | F75: Commercial Amendment | G75: 46291 | H75: 46351 | I75: 0 | K75: 60 | L75: Pending Review | M75: SP005 | N75: Commercial negotiation
A76: AUD00075 | B76: CTR-0043-03 | C76: CUST0043 | D76: 46260 | E76: Account Manager | F76: Commercial Amendment | G76: 46294 | H76: 46354 | I76: 0 | K76: 60 | L76: Approved | M76: SP005 | N76: Internal correction
A77: AUD00076 | B77: CTR-0044-01 | C77: CUST0044 | D77: 45372 | E77: Finance | F77: Commercial Amendment | G77: 45647 | H77: 45707 | I77: 0 | K77: 60 | L77: Pending Review | M77: SP010 | N77: Customer request
A78: AUD00077 | B78: CTR-0044-01 | C78: CUST0044 | D78: 45171 | E78: Account Manager | F78: Shortening | G78: 45707 | H78: 45677 | I78: 0 | K78: -30 | L78: Approved | M78: SP010 | N78: Billing correction
A79: AUD00078 | B79: CTR-0044-02 | C79: CUST0044 | D79: 45571 | E79: Finance | F79: Extension | G79: 46026 | H79: 46056 | I79: 0 | K79: 30 | L79: Approved | M79: SP010 | N79: Internal correction
A80: AUD00079 | B80: CTR-0044-02 | C80: CUST0044 | D80: 45452 | E80: Sales Ops | F80: Renewal Pushback | G80: 46056 | H80: 46116 | I80: 0 | K80: 60 | L80: Approved | M80: SP010 | N80: Internal correction
A81: AUD00080 | B81: CTR-0045-01 | C81: CUST0045 | D81: 45940 | E81: Finance | F81: Shortening | G81: 46317 | H81: 46257 | I81: 0 | K81: -60 | L81: Approved | M81: SP004 | N81: Internal correction
A82: AUD00081 | B82: CTR-0045-01 | C82: CUST0045 | D82: 45899 | E82: Commercial Director | F82: Extension | G82: 46257 | H82: 46287 | I82: 0 | K82: 30 | L82: Pending Review | M82: SP004 | N82: Billing correction
A83: AUD00082 | B83: CTR-0045-01 | C83: CUST0045 | D83: 45852 | E83: Commercial Director | F83: Rollback | G83: 46287 | H83: 46317 | I83: 1 | J83: Rollback to previous agreed end date | K83: 30 | L83: Approved | M83: SP004 | N83: Customer request
A84: AUD00083 | B84: CTR-0045-01 | C84: CUST0045 | D84: 46225 | E84: Account Manager | F84: Commercial Amendment | G84: 46317 | H84: 46287 | I84: 0 | K84: -30 | L84: Pending Review | M84: SP004 | N84: Commercial negotiation
A85: AUD00084 | B85: CTR-0046-01 | C85: CUST0046 | D85: 46378 | E85: Commercial Director | F85: Rollback | G85: 46512 | H85: 46512 | I85: 1 | J85: Rollback to previous agreed end date | K85: 0 | L85: Approved | M85: SP003 | N85: Commercial negotiation
A86: AUD00085 | B86: CTR-0046-01 | C86: CUST0046 | D86: 46286 | E86: Account Manager | F86: Commercial Amendment | G86: 46512 | H86: 46572 | I86: 0 | K86: 60 | L86: Approved | M86: SP003 | N86: Customer request
A87: AUD00086 | B87: CTR-0047-01 | C87: CUST0047 | D87: 45575 | E87: Sales Ops | F87: Rollback | G87: 46355 | H87: 46355 | I87: 1 | J87: Rollback to previous agreed end date | K87: 0 | L87: Pending Review | M87: SP010 | N87: Renewal alignment
A88: AUD00087 | B88: CTR-0048-02 | C88: CUST0048 | D88: 46303 | E88: Commercial Director | F88: Extension | G88: 46366 | H88: 46456 | I88: 0 | K88: 90 | L88: Approved | M88: SP004 | N88: Commercial negotiation
A89: AUD00088 | B89: CTR-0048-02 | C89: CUST0048 | D89: 46107 | E89: Account Manager | F89: Shortening | G89: 46456 | H89: 46426 | I89: 0 | K89: -30 | L89: Approved | M89: SP004 | N89: Commercial negotiation
A90: AUD00089 | B90: CTR-0048-03 | C90: CUST0048 | D90: 45370 | E90: Finance | F90: Renewal Pushback | G90: 45452 | H90: 45482 | I90: 0 | K90: 30 | L90: Approved | M90: SP004 | N90: Renewal alignment
A91: AUD00090 | B91: CTR-0049-01 | C91: CUST0049 | D91: 45519 | E91: Sales Ops | F91: Rollback | G91: 45683 | H91: 45683 | I91: 1 | J91: Rollback to previous agreed end date | K91: 0 | L91: Approved | M91: SP001 | N91: Internal correction
A92: AUD00091 | B92: CTR-0049-01 | C92: CUST0049 | D92: 45460 | E92: Account Manager | F92: Commercial Amendment | G92: 45683 | H92: 45743 | I92: 0 | K92: 60 | L92: Approved | M92: SP001 | N92: Commercial negotiation
A93: AUD00092 | B93: CTR-0049-02 | C93: CUST0049 | D93: 46054 | E93: Sales Ops | F93: Commercial Amendment | G93: 46244 | H93: 46274 | I93: 0 | K93: 30 | L93: Approved | M93: SP001 | N93: Customer request
A94: AUD00093 | B94: CTR-0049-02 | C94: CUST0049 | D94: 45976 | E94: Account Manager | F94: Extension | G94: 46274 | H94: 46304 | I94: 0 | K94: 30 | L94: Approved | M94: SP001 | N94: Internal correction
A95: AUD00094 | B95: CTR-0050-01 | C95: CUST0050 | D95: 45940 | E95: Sales Ops | F95: Rollback | G95: 46230 | H95: 46230 | I95: 1 | J95: Rollback to previous agreed end date | K95: 0 | L95: Approved | M95: SP002 | N95: Commercial negotiation
A96: AUD00095 | B96: CTR-0050-01 | C96: CUST0050 | D96: 46103 | E96: Commercial Director | F96: Rollback | G96: 46230 | H96: 46230 | I96: 1 | J96: Rollback to previous agreed end date | K96: 0 | L96: Pending Review | M96: SP002 | N96: Billing correction
A97: AUD00096 | B97: CTR-0050-02 | C97: CUST0050 | D97: 45713 | E97: Commercial Director | F97: Shortening | G97: 46194 | H97: 46104 | I97: 0 | K97: -90 | L97: Approved | M97: SP002 | N97: Commercial negotiation
A98: AUD00097 | B98: CTR-0050-02 | C98: CUST0050 | D98: 45522 | E98: Account Manager | F98: Commercial Amendment | G98: 46104 | H98: 46164 | I98: 0 | K98: 60 | L98: Pending Review | M98: SP002 | N98: Internal correction
A99: AUD00098 | B99: CTR-0052-01 | C99: CUST0052 | D99: 45535 | E99: Commercial Director | F99: Extension | G99: 45834 | H99: 45924 | I99: 0 | K99: 90 | L99: Approved | M99: SP002 | N99: Billing correction
A100: AUD00099 | B100: CTR-0053-01 | C100: CUST0053 | D100: 46423 | E100: Commercial Director | F100: Extension | G100: 46543 | H100: 46573 | I100: 0 | K100: 30 | L100: Pending Review | M100: SP008 | N100: Customer request
...

Sheet UpcomingRenewals
A1: Priority | B1: ContractID | C1: CustomerID | D1: AccountOwnerID | E1: ContractName | F1: ContractStatus | G1: CurrentEndDate | H1: DaysToRenewal | I1: ContractMRR | J1: ContractARR | K1: EndDateChangeCount | L1: RollbackCount | M1: RenewalRisk | N1: HealthCheckReason | O1: SuggestedAction
A2: Critical | B2: CTR-0062-01 | C2: CUST0062 | D2: SP003 | E2: CUST0062 Multi-Service Agreement 1 | F2: Expired - Rolling | G2: 46069 | H2: -180 | I2: 3789.15 | J2: 45469.8 | K2: 1 | L2: 1 | M2: Medium | N2: Contract has passed end date and appears to be rolling or needs review | O2: Immediate contract health check and renewal confirmation
A3: Critical | B3: CTR-0093-01 | C3: CUST0093 | D3: SP003 | E3: CUST0093 Managed Service Agreement 1 | F3: Expired - Needs Review | G3: 46069 | H3: -180 | I3: 5529 | J3: 66348 | K3: 1 | L3: 0 | M3: Medium | N3: Contract has passed end date and appears to be rolling or needs review | O3: Immediate contract health check and renewal confirmation
A4: Critical | B4: CTR-0025-01 | C4: CUST0025 | D4: SP006 | E4: CUST0025 Multi-Service Agreement 1 | F4: Expired - Needs Review | G4: 46076 | H4: -173 | I4: 3788 | J4: 45456 | K4: 3 | L4: 0 | M4: Medium | N4: Contract has passed end date and appears to be rolling or needs review | O4: Immediate contract health check and renewal confirmation
A5: Critical | B5: CTR-0078-01 | C5: CUST0078 | D5: SP008 | E5: CUST0078 Support Agreement 1 | F5: Expired - Needs Review | G5: 46080 | H5: -169 | I5: 1020 | J5: 12240 | K5: 0 | L5: 0 | M5: Low | N5: Contract has passed end date and appears to be rolling or needs review | O5: Immediate contract health check and renewal confirmation
A6: Critical | B6: CTR-0036-02 | C6: CUST0036 | D6: SP004 | E6: CUST0036 Managed Service Agreement 2 | F6: Expired - Needs Review | G6: 46093 | H6: -156 | I6: 3148.62 | J6: 37783.44 | K6: 0 | L6: 0 | M6: High | N6: Contract has passed end date and appears to be rolling or needs review | O6: Immediate contract health check and renewal confirmation
A7: Critical | B7: CTR-0049-02 | C7: CUST0049 | D7: SP001 | E7: CUST0049 Managed Service Agreement 2 | F7: Expired - Rolling | G7: 46105 | H7: -144 | I7: 1471 | J7: 17652 | K7: 2 | L7: 0 | M7: Low | N7: Contract has passed end date and appears to be rolling or needs review | O7: Immediate contract health check and renewal confirmation
A8: Critical | B8: CTR-0020-02 | C8: CUST0020 | D8: SP006 | E8: CUST0020 Support Agreement 2 | F8: Expired - Rolling | G8: 46107 | H8: -142 | I8: 3604 | J8: 43248 | K8: 0 | L8: 0 | M8: Medium | N8: Contract has passed end date and appears to be rolling or needs review | O8: Immediate contract health check and renewal confirmation
A9: Critical | B9: CTR-0084-01 | C9: CUST0084 | D9: SP001 | E9: CUST0084 Multi-Service Agreement 1 | F9: Expired - Rolling | G9: 46110 | H9: -139 | I9: 4908 | J9: 58896 | K9: 1 | L9: 0 | M9: High | N9: Contract has passed end date and appears to be rolling or needs review | O9: Immediate contract health check and renewal confirmation
A10: Critical | B10: CTR-0001-01 | C10: CUST0001 | D10: SP001 | E10: CUST0001 Support Agreement 1 | F10: Expired - Rolling | G10: 46112 | H10: -137 | I10: 374.77 | J10: 4497.24 | K10: 0 | L10: 0 | M10: Medium | N10: Contract has passed end date and appears to be rolling or needs review | O10: Immediate contract health check and renewal confirmation
A11: Critical | B11: CTR-0085-01 | C11: CUST0085 | D11: SP001 | E11: CUST0085 Multi-Service Agreement 1 | F11: Expired - Needs Review | G11: 46112 | H11: -137 | I11: 9328 | J11: 111936 | K11: 1 | L11: 0 | M11: Medium | N11: Contract has passed end date and appears to be rolling or needs review | O11: Immediate contract health check and renewal confirmation
A12: Critical | B12: CTR-0038-02 | C12: CUST0038 | D12: SP009 | E12: CUST0038 Multi-Service Agreement 2 | F12: Expired - Rolling | G12: 46114 | H12: -135 | I12: 3900 | J12: 46800 | K12: 0 | L12: 0 | M12: High | N12: Contract has passed end date and appears to be rolling or needs review | O12: Immediate contract health check and renewal confirmation
A13: Critical | B13: CTR-0082-01 | C13: CUST0082 | D13: SP006 | E13: CUST0082 Support Agreement 1 | F13: Expired - Needs Review | G13: 46121 | H13: -128 | I13: 2676 | J13: 32112 | K13: 0 | L13: 0 | M13: Medium | N13: Contract has passed end date and appears to be rolling or needs review | O13: Immediate contract health check and renewal confirmation
... A102: Planned | B102: CTR-0095-01 | C102: CUST0095 | D102: SP002 | E102: CUST0095 Support Agreement 1 | F102: Upcoming Renewal | G102: 46367 | H102: 118 | I102: 1446 | J102: 17352 | K102: 3 | L102: 0 | M102: Medium | N102: Renewal due within 120 days | O102: Plan proactive health check and whitespace review

Sheet CustomerContractSummary
A1: CustomerID | B1: AccountOwnerID | C1: ContractCount | D1: ActiveContractCount | E1: UpcomingRenewalCount | F1: RollingExpiredCount | G1: ServiceCount | H1: ServicesCurrentlyBilled | I1: TotalMRR | J1: TotalARR | K1: EstimatedAnnualGrossProfit | L1: EndDateChangeCount | M1: RollbackCount | N1: NearestContractEndDate | O1: DaysToNearestRenewal | P1: HealthCheckRequired | Q1: SuggestedManagerAction
A2: CUST0001 | B2: SP001 | C2: 1 | D2: 0 | E2: 1 | F2: 1 | G2: 1 | H2: Telco Support | I2: 374.77 | J2: 4497.24 | K2: 1394.16 | L2: 0 | M2: 0 | N2: 46112 | O2: -137 | P2: 1 | Q2: Immediate health check: contract appears expired/rolling
A3: CUST0002 | B3: SP004 | C3: 1 | D3: 1 | E3: 1 | F3: 0 | G3: 2 | H3: Modern Workplace, Telco Support | I3: 7001 | J3: 84012 | K3: 29133.12 | L3: 1 | M3: 1 | N3: 46282 | O3: 33 | P3: 1 | Q3: Schedule health check and renewal/whitespace review
A4: CUST0003 | B4: SP006 | C4: 1 | D4: 1 | E4: 1 | F4: 0 | G4: 1 | H4: Connectivity | I4: 2790 | J4: 33480 | K4: 10044 | L4: 0 | M4: 0 | N4: 46331 | O4: 82 | P4: 1 | Q4: Schedule health check and renewal/whitespace review
A5: CUST0004 | B5: SP007 | C5: 3 | D5: 3 | E5: 1 | F5: 0 | G5: 5 | H5: Cloud IT, Connectivity, Cyber Security, IT Support, Telco Support | I5: 18321 | J5: 219852 | K5: 96970.8 | L5: 5 | M5: 1 | N5: 46259 | O5: 10 | P5: 1 | Q5: Schedule health check and renewal/whitespace review
A6: CUST0005 | B6: SP008 | C6: 3 | D6: 3 | E6: 3 | F6: 0 | G6: 5 | H6: Connectivity, Hosted Telephony, IT Support, Modern Workplace, Telco Support | I6: 9063 | J6: 108756 | K6: 39332.4 | L6: 5 | M6: 0 | N6: 46259 | O6: 10 | P6: 1 | Q6: Schedule health check and renewal/whitespace review
A7: CUST0006 | B7: SP006 | C7: 1 | D7: 0 | E7: 1 | F7: 1 | G7: 2 | H7: Connectivity, Telco Support | I7: 3213 | J7: 38556 | K7: 11525.4 | L7: 3 | M7: 0 | N7: 46222 | O7: -27 | P7: 1 | Q7: Immediate health check: contract appears expired/rolling
A8: CUST0007 | B8: SP006 | C8: 1 | D8: 0 | E8: 1 | F8: 1 | G8: 3 | H8: Connectivity, Hosted Telephony, IT Support | I8: 1830.46 | J8: 21965.52 | K8: 8868.48 | L8: 1 | M8: 1 | N8: 46160 | O8: -89 | P8: 1 | Q8: Immediate health check: contract appears expired/rolling
A9: CUST0008 | B9: SP003 | C9: 3 | D9: 3 | E9: 0 | F9: 0 | G9: 4 | H9: Cyber Security, Hosted Telephony, IT Support, Telco Support | I9: 7438 | J9: 89256 | K9: 31633.32 | L9: 2 | M9: 1 | N9: 46449 | O9: 200 | P9: 0 | Q9: Review contract audit history before next renewal
A10: CUST0009 | B10: SP009 | C10: 1 | D10: 1 | E10: 1 | F10: 0 | G10: 1 | H10: IT Support | I10: 4829.54 | J10: 57954.48 | K10: 25500 | L10: 0 | M10: 0 | N10: 46315 | O10: 66 | P10: 1 | Q10: Schedule health check and renewal/whitespace review
A11: CUST0010 | B11: SP008 | C11: 3 | D11: 3 | E11: 1 | F11: 0 | G11: 5 | H11: Cloud IT, Connectivity, Cyber Security, IT Support, Telco Support | I11: 7046 | J11: 84552 | K11: 35518.08 | L11: 0 | M11: 0 | N11: 46317 | O11: 68 | P11: 1 | Q11: Schedule health check and renewal/whitespace review
A12: CUST0011 | B12: SP005 | C12: 1 | D12: 1 | E12: 0 | F12: 0 | G12: 1 | H12: Telco Support | I12: 449 | J12: 5388 | K12: 1616.4 | L12: 3 | M12: 2 | N12: 46828 | O12: 579 | P12: 0 | Q12: Review contract audit history before next renewal
A13: CUST0012 | B13: SP010 | C13: 1 | D13: 1 | E13: 1 | F13: 0 | G13: 1 | H13: Modern Workplace | I13: 1291.71 | J13: 15500.52 | K13: 5890.2 | L13: 0 | M13: 0 | N13: 46353 | O13: 104 | P13: 1 | Q13: Schedule health check and renewal/whitespace review
... A101: CUST0100 | B101: SP006 | C101: 1 | D101: 0 | E101: 1 | F101: 1 | G101: 2 | H101: Cloud IT, Telco Support | I101: 11743 | J101: 140916 | K101: 59913.72 | L101: 0 | M101: 0 | N101: 46206 | O101: -43 | P101: 1 | Q101: Immediate health check: contract appears expired/rolling

Sheet ContractFeatureNotes
A1: Section | B1: Detail
A2: Purpose | B2: Adds a formal customer-contract layer so customers currently billing can be linked to one or many contracts, and each contract can be linked to one or many services.
A3: Contracts | B3: One row per commercial contract. Includes customer, account owner/salesperson, original/current end date, change counts, rollback counts, renewal risk and health-check action.
A4: ContractServices | B4: Links services to each contract. Supports multiple services under one contract and multiple contracts per customer.
A5: ContractAuditLog | B5: Tracks every contract end-date change, previous end date, new end date, days changed, rollback flag, approval status and linked salesperson.
A6: UpcomingRenewals | B6: Prioritised list of contracts/customers that need renewal health checks. Includes account owner, current end date, days to renewal, ARR, changes and rollback count.
A7: CustomerContractSummary | B7: Customer-level view of contracts, services currently billed, total MRR/ARR, nearest renewal, rollback/change counts and suggested manager action.
A8: Sales manager value | B8: Sales managers can see which customers need health checks, who owns the account, what services are tied to the contract and whether the contract was repeatedly extended or rolled back.
A9: Data scientist value | B9: Contract features can be tested as predictors: days to renewal, change frequency, rollback count, rolling-contract status, service mix, ARR/MRR and renewal risk.
A10: Important caveat | B10: All contract and billing data in this workbook is simulated for demo purposes.

Sheet DataRelationships
A1: Entity | B1: Primary Key | C1: Foreign Key / Link | D1: Relationship
A2: Customers | B2: CustomerID | C2: Contracts.CustomerID | D2: One customer can have many contracts
A3: ContractServices | B3: CustomerID + Service | C3: ExistingCustomerBilling.CustomerID + Service | D3: Billing rows are linked to the matching customer/service contract
A4: Salespeople | B4: SalespersonID | C4: Contracts.AccountOwnerID / ExistingCustomerBilling.AccountOwnerID | D4: Each contract and billing stream links to a salesperson/account owner
A5: Contracts | B5: CurrentEndDate | C5: UpcomingRenewals | D5: Contracts due within the renewal window are surfaced for health checks
A6: Meetings | B6: MeetingID | C6: SalespersonID, CustomerID, OpportunityID | D6: Meeting belongs to a salesperson and customer and may support an opportunity
A7: OpportunityNotes | B7: NoteID | C7: OpportunityID, CustomerID, SalespersonID | D7: Customer or internal note requiring an opportunity response
A8: Projects | B8: ProjectID | C8: OpportunityID | D8: Delivery project created from an opportunity
A9: OpportunityTickets | B9: TicketID | C9: ProjectID, OpportunityID | D9: Operational ticket linked to project and opportunity
A10: TicketTasks | B10: TaskID | C10: TicketID, ProjectID, OpportunityID | D10: Task status contributing to ticket and project progress

Sheet MetricDefinitions
A1: MetricName | B1: Category | C1: Definition | D1: FormulaOrLogic | E1: PrimarySource | F1: Direction | G1: Availability | H1: ModelUse | I1: LeakageRisk
A2: CustomerReachouts | B2: Activity | C2: Count of outbound customer/prospect reach-outs in period | D2: COUNT(activity where type/channel is reach-out) | E2: Activities / MonthlyPerformance | F2: Higher with quality | G2: Available | H2: Feature | I2: Low
A3: UniqueCustomersContacted | B3: Activity | C3: Distinct customers contacted in period | D3: COUNT DISTINCT CustomerID on eligible activities | E3: Activities | F3: Higher with relevance | G3: Requires CustomerID on Activities | H3: Feature | I3: Low
A4: MeetingsBooked | B4: Activity | C4: Meetings scheduled in period | D4: COUNT meeting bookings | E4: Activities / CRM meetings | F4: Higher with quality | G4: Future field | H4: Feature | I4: Low
A5: Meetings | B5: Activity | C5: Customer/prospect meetings held in period | D5: COUNT completed/held meetings | E5: MonthlyPerformance | F5: Higher with quality | G5: Available | H5: Feature | I5: Low
A6: MeetingShowRate | B6: Activity | C6: Share of booked meetings that were held | D6: MeetingsHeld / MeetingsBooked | E6: Meeting data | F6: Higher | G6: Future field | H6: Feature | I6: Low
A7: OpportunitiesCreated | B7: Pipeline | C7: New opportunities created in period | D7: COUNT OpportunityID by CreatedDate | E7: Opportunities / MonthlyPerformance | F7: Higher with quality | G7: Available | H7: Feature | I7: Low
A8: PipelineValue | B8: Pipeline | C8: Value of open opportunities | D8: SUM PipelineValue where Stage=Open | E8: Opportunities | F8: Higher with quality | G8: Available | H8: Feature | I8: Low
A9: QualifiedOpportunities | B9: Pipeline | C9: Opportunities meeting qualification criteria | D9: COUNT qualified opportunities | E9: Opportunities | F9: Higher | G9: Requires qualification field/stage rules | H9: Feature | I9: Low
A10: AverageDealSize | B10: Pipeline | C10: Average opportunity value | D10: AVG PipelineValue | E10: Opportunities | F10: Contextual | G10: Available | H10: Feature | I10: Low
A11: PipelineCoverage | B11: Pipeline | C11: Open pipeline relative to target | D11: OpenPipelineValue / PeriodTarget | E11: Opportunities + Targets | F11: Higher to healthy range | G11: Available-derived | H11: Feature/KPI | I11: Low
A12: ReachoutToMeetingRate | B12: Conversion | C12: Share of reach-outs resulting in a meeting | D12: Meetings / CustomerReachouts | E12: MonthlyPerformance | F12: Higher | G12: Available-derived | H12: Feature | I12: Low
... A49: SynergyReferralConversionRate | B49: Synergy | C49: Share of received referrals converted | D49: Converted referrals / received referrals | E49: SynergyReferrals | F49: Higher | G49: Available-derived | H49: Feature/KPI | I49: Medium

Sheet Meetings
A1: MeetingID | B1: MeetingDate | C1: SalespersonID | D1: CustomerID | E1: OpportunityID | F1: CustomerRelationship | G1: MeetingType | H1: Subject | I1: DurationMinutes | J1: Attendees | K1: MeetingStatus | L1: MeetingSummary | M1: SalespersonNotes | N1: CriticalFindingFlag | O1: CriticalSeverity | P1: CriticalFinding | Q1: NextAction | R1: ActionOwner | S1: ActionDueDate | T1: FollowUpStatus | U1: LastUpdatedDate
A2: MTG00001 | B2: 45658 | C2: SP003 | D2: CUST0120 | E2: OPP0453 | F2: Existing Customer | G2: Opportunity Review | H2: Customer 0120 - Opportunity Review | I2: 45 | J2: Customer lead and salesperson | K2: Held | L2: The opportunity remains active with scope, stakeholders, and next commercial step confirmed. | M2: Met with Customer 0120 regarding opportunity review. The opportunity remains active with scope, stakeholders, and next commercial step confirmed. Customer context: existing managed-service account. Critical finding: None identified. Next step is owned by SP003. | N2: FALSE | O2: None | P2: None identified | Q2: Update account action plan | R2: SP003 | S2: 45660 | T2: In Progress | U2: 45660
A3: MTG00002 | B3: 45659 | C3: SP003 | D3: CUST0044 | F3: Existing Customer | G3: Support Escalation | H3: Customer 0044 - Support Escalation | I3: 30 | J3: Customer sponsor and salesperson | K3: Held | L3: The escalation was reviewed with clear technical ownership and a customer update cadence. | M3: Met with Customer 0044 regarding support escalation. The escalation was reviewed with clear technical ownership and a customer update cadence. Customer context: existing managed-service account. Critical finding: Critical incident remains open and is affecting operations. Next step is owned by SP003. | N3: TRUE | O3: Medium | P3: Critical incident remains open and is affecting operations | Q3: Escalate to service leadership | R3: SP003 | S3: 45674 | T3: In Progress | U3: 45674
A4: MTG00003 | B4: 45659 | C4: SP005 | D4: CUST0018 | E4: OPP0067 | F4: Existing Customer | G4: Support Escalation | H4: Customer 0018 - Support Escalation | I4: 45 | J4: Customer lead, technical specialist, and salesperson | K4: Held | L4: The escalation was reviewed with clear technical ownership and a customer update cadence. | M4: Met with Customer 0018 regarding support escalation. The escalation was reviewed with clear technical ownership and a customer update cadence. Customer context: existing managed-service account. Critical finding: Customer requested senior ownership of the escalation. Next step is owned by SP005. | N4: TRUE | O4: Critical | P4: Customer requested senior ownership of the escalation | Q4: Update account action plan | R4: SP005 | S4: 45679 | T4: In Progress | U4: 45679
A5: MTG00004 | B5: 45659 | C5: SP002 | D5: CUST0090 | E5: OPP0270 | F5: Existing Customer | G5: Opportunity Review | H5: Customer 0090 - Opportunity Review | I5: 30 | J5: Customer lead and salesperson | K5: Held | L5: The opportunity remains active with scope, stakeholders, and next commercial step confirmed. | M5: Met with Customer 0090 regarding opportunity review. The opportunity remains active with scope, stakeholders, and next commercial step confirmed. Customer context: existing managed-service account. Critical finding: None identified. Next step is owned by SP002. | N5: FALSE | O5: None | P5: None identified | Q5: Send written follow-up | R5: SP002 | S5: 45668 | T5: Complete | U5: 45668
A6: MTG00005 | B6: 45659 | C6: SP001 | D6: CUST0064 | F6: Existing Customer | G6: Regular Account Review | H6: Customer 0064 - Regular Account Review | I6: 60 | J6: Customer sponsor and salesperson | K6: Held | L6: Service performance and planned business changes were reviewed with the customer. | M6: Met with Customer 0064 regarding regular account review. Service performance and planned business changes were reviewed with the customer. Customer context: existing managed-service account. Critical finding: None identified. Next step is owned by SP001. | N6: FALSE | O6: None | P6: None identified | Q6: Escalate to service leadership | R6: SP001 | S6: 45672 | T6: Complete | U6: 45672
A7: MTG00006 | B7: 45660 | C7: SP002 | D7: CUST0068 | E7: OPP0154 | F7: Existing Customer | G7: Opportunity Review | H7: Customer 0068 - Opportunity Review | I7: 60 | J7: Customer sponsor and salesperson | K7: Held | L7: The opportunity remains active with scope, stakeholders, and next commercial step confirmed. | M7: Met with Customer 0068 regarding opportunity review. The opportunity remains active with scope, stakeholders, and next commercial step confirmed. Customer context: existing managed-service account. Critical finding: None identified. Next step is owned by SP002. | N7: FALSE | O7: None | P7: None identified | Q7: Schedule technical workshop | R7: SP002 | S7: 45670 | T7: Open | U7: 45670
A8: MTG00007 | B8: 45660 | C8: SP008 | D8: CUST0079 | E8: OPP0438 | F8: Existing Customer | G8: Opportunity Review | H8: Customer 0079 - Opportunity Review | I8: 60 | J8: Customer lead and salesperson | K8: Held | L8: The opportunity remains active with scope, stakeholders, and next commercial step confirmed. | M8: Met with Customer 0079 regarding opportunity review. The opportunity remains active with scope, stakeholders, and next commercial step confirmed. Customer context: existing managed-service account. Critical finding: Competitor is active in the final evaluation. Next step is owned by SP008. | N8: TRUE | O8: High | P8: Competitor is active in the final evaluation | Q8: Update account action plan | R8: SP008 | S8: 45664 | T8: Complete | U8: 45664
A9: MTG00008 | B9: 45660 | C9: SP009 | D9: CUST0071 | E9: OPP0201 | F9: Existing Customer | G9: Opportunity Review | H9: Customer 0071 - Opportunity Review | I9: 30 | J9: Customer sponsor and salesperson | K9: Held | L9: The opportunity remains active with scope, stakeholders, and next commercial step confirmed. | M9: Met with Customer 0071 regarding opportunity review. The opportunity remains active with scope, stakeholders, and next commercial step confirmed. Customer context: existing managed-service account. Critical finding: None identified. Next step is owned by SP009. | N9: FALSE | O9: None | P9: None identified | Q9: Send written follow-up | R9: SP009 | S9: 45679 | T9: Open | U9: 45679
A10: MTG00009 | B10: 45663 | C10: SP002 | D10: CUST0103 | F10: Existing Customer | G10: Regular Account Review | H10: Customer 0103 - Regular Account Review | I10: 60 | J10: Customer lead, technical specialist, and salesperson | K10: Held | L10: Service performance and planned business changes were reviewed with the customer. | M10: Met with Customer 0103 regarding regular account review. Service performance and planned business changes were reviewed with the customer. Customer context: existing managed-service account. Critical finding: None identified. Next step is owned by SP002. | N10: FALSE | O10: None | P10: None identified | Q10: Confirm commercial response | R10: SP002 | S10: 45684 | T10: In Progress | U10: 45684
A11: MTG00010 | B11: 45663 | C11: SP006 | D11: CUST0003 | F11: Existing Customer | G11: Support Escalation | H11: Customer 0003 - Support Escalation | I11: 45 | J11: Customer lead and salesperson | K11: Held | L11: The escalation was reviewed with clear technical ownership and a customer update cadence. | M11: Met with Customer 0003 regarding support escalation. The escalation was reviewed with clear technical ownership and a customer update cadence. Customer context: existing managed-service account. Critical finding: Critical incident remains open and is affecting operations. Next step is owned by SP006. | N11: TRUE | O11: Critical | P11: Critical incident remains open and is affecting operations | Q11: Update account action plan | R11: SP006 | S11: 45677 | T11: Complete | U11: 45677
A12: MTG00011 | B12: 45664 | C12: SP006 | D12: CUST0103 | F12: Existing Customer | G12: Renewal Planning | H12: Customer 0103 - Renewal Planning | I12: 30 | J12: Customer lead, technical specialist, and salesperson | K12: Held | L12: Renewal scope, decision process, and value evidence were reviewed with the customer. | M12: Met with Customer 0103 regarding renewal planning. Renewal scope, decision process, and value evidence were reviewed with the customer. Customer context: existing managed-service account. Critical finding: None identified. Next step is owned by SP006. | N12: FALSE | O12: None | P12: None identified | Q12: Update account action plan | R12: SP006 | S12: 45683 | T12: Open | U12: 45683
A13: MTG00012 | B13: 45665 | C13: SP006 | D13: CUST0007 | F13: Existing Customer | G13: Regular Account Review | H13: Customer 0007 - Regular Account Review | I13: 30 | J13: Customer sponsor and salesperson | K13: Held | L13: Service performance and planned business changes were reviewed with the customer. | M13: Met with Customer 0007 regarding regular account review. Service performance and planned business changes were reviewed with the customer. Customer context: existing managed-service account. Critical finding: A new cyber requirement is not covered by the current service. Next step is owned by SP006. | N13: TRUE | O13: Medium | P13: A new cyber requirement is not covered by the current service | Q13: Update account action plan | R13: SP006 | S13: 45686 | T13: Complete | U13: 45686
A14: MTG00013 | B14: 45665 | C14: SP010 | D14: CUST0108 | E14: OPP0490 | F14: New Customer | G14: New Business Discovery | H14: Customer 0108 - New Business Discovery | I14: 60 | J14: Customer lead, technical specialist, and salesperson | K14: Held | L14: Customer confirmed the initial business outcomes and agreed to a qualification workshop. | M14: Met with Customer 0108 regarding new business discovery. Customer confirmed the initial business outcomes and agreed to a qualification workshop. Customer context: new customer prospect. Critical finding: None identified. Next step is owned by SP010. | N14: FALSE | O14: None | P14: None identified | Q14: Escalate to service leadership | R14: SP010 | S14: 45685 | T14: Open | U14: 45685
A15: MTG00014 | B15: 45665 | C15: SP009 | D15: CUST0031 | E15: OPP0419 | F15: Existing Customer | G15: Support Escalation | H15: Customer 0031 - Support Escalation | I15: 45 | J15: Customer sponsor and salesperson | K15: Held | L15: The escalation was reviewed with clear technical ownership and a customer update cadence. | M15: Met with Customer 0031 regarding support escalation. The escalation was reviewed with clear technical ownership and a customer update cadence. Customer context: existing managed-service account. Critical finding: None identified. Next step is owned by SP009. | N15: FALSE | O15: None | P15: None identified | Q15: Schedule technical workshop | R15: SP009 | S15: 45685 | T15: Complete | U15: 45685
A16: MTG00015 | B16: 45666 | C16: SP001 | D16: CUST0112 | F16: Existing Customer | G16: Regular Account Review | H16: Customer 0112 - Regular Account Review | I16: 45 | J16: Customer lead, technical specialist, and salesperson | K16: Held | L16: Service performance and planned business changes were reviewed with the customer. | M16: Met with Customer 0112 regarding regular account review. Service performance and planned business changes were reviewed with the customer. Customer context: existing managed-service account. Critical finding: None identified. Next step is owned by SP001. | N16: FALSE | O16: None | P16: None identified | Q16: Send written follow-up | R16: SP001 | S16: 45686 | T16: In Progress | U16: 45686
A17: MTG00016 | B17: 45666 | C17: SP004 | D17: CUST0029 | E17: OPP0216 | F17: New Customer | G17: Opportunity Review | H17: Customer 0029 - Opportunity Review | I17: 45 | J17: Customer sponsor and salesperson | K17: Held | L17: The opportunity remains active with scope, stakeholders, and next commercial step confirmed. | M17: Met with Customer 0029 regarding opportunity review. The opportunity remains active with scope, stakeholders, and next commercial step confirmed. Customer context: new customer prospect. Critical finding: None identified. Next step is owned by SP004. | N17: FALSE | O17: None | P17: None identified | Q17: Confirm commercial response | R17: SP004 | S17: 45671 | T17: Open | U17: 45671
A18: MTG00017 | B18: 45667 | C18: SP009 | D18: CUST0096 | E18: OPP0359 | F18: New Customer | G18: Opportunity Review | H18: Customer 0096 - Opportunity Review | I18: 60 | J18: Customer lead and salesperson | K18: Held | L18: The opportunity remains active with scope, stakeholders, and next commercial step confirmed. | M18: Met with Customer 0096 regarding opportunity review. The opportunity remains active with scope, stakeholders, and next commercial step confirmed. Customer context: new customer prospect. Critical finding: None identified. Next step is owned by SP009. | N18: FALSE | O18: None | P18: None identified | Q18: Confirm commercial response | R18: SP009 | S18: 45670 | T18: Open | U18: 45670
A19: MTG00018 | B19: 45670 | C19: SP007 | D19: CUST0063 | E19: OPP0307 | F19: New Customer | G19: Opportunity Review | H19: Customer 0063 - Opportunity Review | I19: 90 | J19: Customer lead, technical specialist, and salesperson | K19: Held | L19: The opportunity remains active with scope, stakeholders, and next commercial step confirmed. | M19: Met with Customer 0063 regarding opportunity review. The opportunity remains active with scope, stakeholders, and next commercial step confirmed. Customer context: new customer prospect. Critical finding: Procurement requested revised commercial terms. Next step is owned by SP007. | N19: TRUE | O19: High | P19: Procurement requested revised commercial terms | Q19: Confirm commercial response | R19: SP007 | S19: 45690 | T19: In Progress | U19: 45690
A20: MTG00019 | B20: 45672 | C20: SP006 | D20: CUST0053 | E20: OPP0020 | F20: New Customer | G20: New Business Discovery | H20: Customer 0053 - New Business Discovery | I20: 30 | J20: Customer lead and salesperson | K20: Held | L20: Customer confirmed the initial business outcomes and agreed to a qualification workshop. | M20: Met with Customer 0053 regarding new business discovery. Customer confirmed the initial business outcomes and agreed to a qualification workshop. Customer context: new customer prospect. Critical finding: None identified. Next step is owned by SP006. | N20: FALSE | O20: None | P20: None identified | Q20: Escalate to service leadership | R20: SP006 | S20: 45683 | T20: In Progress | U20: 45683
A21: MTG00020 | B21: 45673 | C21: SP001 | D21: CUST0066 | F21: Existing Customer | G21: Renewal Planning | H21: Customer 0066 - Renewal Planning | I21: 30 | J21: Customer lead, technical specialist, and salesperson | K21: Held | L21: Renewal scope, decision process, and value evidence were reviewed with the customer. | M21: Met with Customer 0066 regarding renewal planning. Renewal scope, decision process, and value evidence were reviewed with the customer. Customer context: existing managed-service account. Critical finding: None identified. Next step is owned by SP001. | N21: FALSE | O21: None | P21: None identified | Q21: Send written follow-up | R21: SP001 | S21: 45689 | T21: Open | U21: 45689
A22: MTG00021 | B22: 45673 | C22: SP002 | D22: CUST0107 | E22: OPP0198 | F22: Existing Customer | G22: Account Health Check | H22: Customer 0107 - Account Health Check | I22: 30 | J22: Customer lead, technical specialist, and salesperson | K22: Held | L22: Account health was reviewed across adoption, value, support, and renewal readiness. | M22: Met with Customer 0107 regarding account health check. Account health was reviewed across adoption, value, support, and renewal readiness. Customer context: existing managed-service account. Critical finding: None identified. Next step is owned by SP002. | N22: FALSE | O22: None | P22: None identified | Q22: Schedule technical workshop | R22: SP002 | S22: 45691 | T22: Open | U22: 45691
A23: MTG00022 | B23: 45673 | C23: SP005 | D23: CUST0096 | E23: OPP0189 | F23: New Customer | G23: New Business Discovery | H23: Customer 0096 - New Business Discovery | I23: 60 | J23: Customer lead, technical specialist, and salesperson | K23: Held | L23: Customer confirmed the initial business outcomes and agreed to a qualification workshop. | M23: Met with Customer 0096 regarding new business discovery. Customer confirmed the initial business outcomes and agreed to a qualification workshop. Customer context: new customer prospect. Critical finding: Budget approval depends on a board review. Next step is owned by SP005. | N23: TRUE | O23: High | P23: Budget approval depends on a board review | Q23: Confirm commercial response | R23: SP005 | S23: 45692 | T23: Open | U23: 45692
A24: MTG00023 | B24: 45674 | C24: SP005 | D24: CUST0053 | F24: New Customer | G24: Renewal Planning | H24: Customer 0053 - Renewal Planning | I24: 45 | J24: Customer sponsor and salesperson | K24: Held | L24: Renewal scope, decision process, and value evidence were reviewed with the customer. | M24: Met with Customer 0053 regarding renewal planning. Renewal scope, decision process, and value evidence were reviewed with the customer. Customer context: new customer prospect. Critical finding: None identified. Next step is owned by SP005. | N24: FALSE | O24: None | P24: None identified | Q24: Update account action plan | R24: SP005 | S24: 45682 | T24: In Progress | U24: 45682
A25: MTG00024 | B25: 45674 | C25: SP003 | D25: CUST0033 | F25: Existing Customer | G25: Account Health Check | H25: Customer 0033 - Account Health Check | I25: 45 | J25: Customer lead, technical specialist, and salesperson | K25: Held | L25: Account health was reviewed across adoption, value, support, and renewal readiness. | M25: Met with Customer 0033 regarding account health check. Account health was reviewed across adoption, value, support, and renewal readiness. Customer context: existing managed-service account. Critical finding: None identified. Next step is owned by SP003. | N25: FALSE | O25: None | P25: None identified | Q25: Send written follow-up | R25: SP003 | S25: 45684 | T25: Open | U25: 45684
A26: MTG00025 | B26: 45674 | C26: SP002 | D26: CUST0088 | E26: OPP0043 | F26: Existing Customer | G26: Opportunity Review | H26: Customer 0088 - Opportunity Review | I26: 60 | J26: Customer sponsor and salesperson | K26: Held | L26: The opportunity remains active with scope, stakeholders, and next commercial step confirmed. | M26: Met with Customer 0088 regarding opportunity review. The opportunity remains active with scope, stakeholders, and next commercial step confirmed. Customer context: existing managed-service account. Critical finding: Competitor is active in the final evaluation. Next step is owned by SP002. | N26: TRUE | O26: High | P26: Competitor is active in the final evaluation | Q26: Schedule technical workshop | R26: SP002 | S26: 45684 | T26: Complete | U26: 45684
A27: MTG00026 | B27: 45680 | C27: SP003 | D27: CUST0008 | E27: OPP0383 | F27: Existing Customer | G27: Opportunity Review | H27: Customer 0008 - Opportunity Review | I27: 30 | J27: Customer sponsor and salesperson | K27: Held | L27: The opportunity remains active with scope, stakeholders, and next commercial step confirmed. | M27: Met with Customer 0008 regarding opportunity review. The opportunity remains active with scope, stakeholders, and next commercial step confirmed. Customer context: existing managed-service account. Critical finding: None identified. Next step is owned by SP003. | N27: FALSE | O27: None | P27: None identified | Q27: Update account action plan | R27: SP003 | S27: 45692 | T27: In Progress | U27: 45692
A28: MTG00027 | B28: 45681 | C28: SP010 | D28: CUST0066 | E28: OPP0175 | F28: Existing Customer | G28: Opportunity Review | H28: Customer 0066 - Opportunity Review | I28: 30 | J28: Customer lead, technical specialist, and salesperson | K28: Held | L28: The opportunity remains active with scope, stakeholders, and next commercial step confirmed. | M28: Met with Customer 0066 regarding opportunity review. The opportunity remains active with scope, stakeholders, and next commercial step confirmed. Customer context: existing managed-service account. Critical finding: None identified. Next step is owned by SP010. | N28: FALSE | O28: None | P28: None identified | Q28: Update account action plan | R28: SP010 | S28: 45687 | T28: Complete | U28: 45687
A29: MTG00028 | B29: 45684 | C29: SP010 | D29: CUST0085 | E29: OPP0121 | F29: Existing Customer | G29: Support Escalation | H29: Customer 0085 - Support Escalation | I29: 45 | J29: Customer lead and salesperson | K29: Held | L29: The escalation was reviewed with clear technical ownership and a customer update cadence. | M29: Met with Customer 0085 regarding support escalation. The escalation was reviewed with clear technical ownership and a customer update cadence. Customer context: existing managed-service account. Critical finding: None identified. Next step is owned by SP010. | N29: FALSE | O29: None | P29: None identified | Q29: Schedule technical workshop | R29: SP010 | S29: 45700 | T29: Open | U29: 45700
A30: MTG00029 | B30: 45685 | C30: SP002 | D30: CUST0077 | E30: OPP0111 | F30: Existing Customer | G30: Opportunity Review | H30: Customer 0077 - Opportunity Review | I30: 45 | J30: Customer lead and salesperson | K30: Held | L30: The opportunity remains active with scope, stakeholders, and next commercial step confirmed. | M30: Met with Customer 0077 regarding opportunity review. The opportunity remains active with scope, stakeholders, and next commercial step confirmed. Customer context: existing managed-service account. Critical finding: None identified. Next step is owned by SP002. | N30: FALSE | O30: None | P30: None identified | Q30: Update account action plan | R30: SP002 | S30: 45687 | T30: In Progress | U30: 45687
A31: MTG00030 | B31: 45687 | C31: SP007 | D31: CUST0027 | E31: OPP0096 | F31: Existing Customer | G31: Opportunity Review | H31: Customer 0027 - Opportunity Review | I31: 45 | J31: Customer lead, technical specialist, and salesperson | K31: Held | L31: The opportunity remains active with scope, stakeholders, and next commercial step confirmed. | M31: Met with Customer 0027 regarding opportunity review. The opportunity remains active with scope, stakeholders, and next commercial step confirmed. Customer context: existing managed-service account. Critical finding: None identified. Next step is owned by SP007. | N31: FALSE | O31: None | P31: None identified | Q31: Schedule technical workshop | R31: SP007 | S31: 45690 | T31: Open | U31: 45690
A32: MTG00031 | B32: 45692 | C32: SP001 | D32: CUST0084 | E32: OPP0090 | F32: Existing Customer | G32: Opportunity Review | H32: Customer 0084 - Opportunity Review | I32: 45 | J32: Customer sponsor and salesperson | K32: Held | L32: The opportunity remains active with scope, stakeholders, and next commercial step confirmed. | M32: Met with Customer 0084 regarding opportunity review. The opportunity remains active with scope, stakeholders, and next commercial step confirmed. Customer context: existing managed-service account. Critical finding: None identified. Next step is owned by SP001. | N32: FALSE | O32: None | P32: None identified | Q32: Confirm commercial response | R32: SP001 | S32: 45702 | T32: Complete | U32: 45702
A33: MTG00032 | B33: 45694 | C33: SP008 | D33: CUST0075 | E33: OPP0317 | F33: Existing Customer | G33: Opportunity Review | H33: Customer 0075 - Opportunity Review | I33: 45 | J33: Customer sponsor and salesperson | K33: Held | L33: The opportunity remains active with scope, stakeholders, and next commercial step confirmed. | M33: Met with Customer 0075 regarding opportunity review. The opportunity remains active with scope, stakeholders, and next commercial step confirmed. Customer context: existing managed-service account. Critical finding: Procurement requested revised commercial terms. Next step is owned by SP008. | N33: TRUE | O33: High | P33: Procurement requested revised commercial terms | Q33: Confirm commercial response | R33: SP008 | S33: 45712 | T33: In Progress | U33: 45712
A34: MTG00033 | B34: 45694 | C34: SP004 | D34: CUST0018 | E34: OPP0137 | F34: Existing Customer | G34: Regular Account Review | H34: Customer 0018 - Regular Account Review | I34: 45 | J34: Customer lead and salesperson | K34: Held | L34: Service performance and planned business changes were reviewed with the customer. | M34: Met with Customer 0018 regarding regular account review. Service performance and planned business changes were reviewed with the customer. Customer context: existing managed-service account. Critical finding: A new cyber requirement is not covered by the current service. Next step is owned by SP004. | N34: TRUE | O34: Medium | P34: A new cyber requirement is not covered by the current service | Q34: Send written follow-up | R34: SP004 | S34: 45706 | T34: In Progress | U34: 45706
A35: MTG00034 | B35: 45695 | C35: SP005 | D35: CUST0067 | E35: OPP0253 | F35: Existing Customer | G35: Regular Account Review | H35: Customer 0067 - Regular Account Review | I35: 60 | J35: Customer lead and salesperson | K35: Held | L35: Service performance and planned business changes were reviewed with the customer. | M35: Met with Customer 0067 regarding regular account review. Service performance and planned business changes were reviewed with the customer. Customer context: existing managed-service account. Critical finding: None identified. Next step is owned by SP005. | N35: FALSE | O35: None | P35: None identified | Q35: Update account action plan | R35: SP005 | S35: 45715 | T35: In Progress | U35: 45715
A36: MTG00035 | B36: 45698 | C36: SP002 | D36: CUST0112 | E36: OPP0472 | F36: Existing Customer | G36: Opportunity Review | H36: Customer 0112 - Opportunity Review | I36: 60 | J36: Customer lead, technical specialist, and salesperson | K36: Held | L36: The opportunity remains active with scope, stakeholders, and next commercial step confirmed. | M36: Met with Customer 0112 regarding opportunity review. The opportunity remains active with scope, stakeholders, and next commercial step confirmed. Customer context: existing managed-service account. Critical finding: None identified. Next step is owned by SP002. | N36: FALSE | O36: None | P36: None identified | Q36: Confirm commercial response | R36: SP002 | S36: 45719 | T36: Complete | U36: 45719
A37: MTG00036 | B37: 45699 | C37: SP006 | D37: CUST0115 | E37: OPP0366 | F37: Existing Customer | G37: Support Escalation | H37: Customer 0115 - Support Escalation | I37: 30 | J37: Customer sponsor and salesperson | K37: Held | L37: The escalation was reviewed with clear technical ownership and a customer update cadence. | M37: Met with Customer 0115 regarding support escalation. The escalation was reviewed with clear technical ownership and a customer update cadence. Customer context: existing managed-service account. Critical finding: None identified. Next step is owned by SP006. | N37: FALSE | O37: None | P37: None identified | Q37: Send written follow-up | R37: SP006 | S37: 45704 | T37: Complete | U37: 45704
... A39: MTG00038 | B39: 45699 | C39: SP009 | D39: CUST0007 | E39: OPP0489 | F39: Existing Customer | G39: Opportunity Review | H39: Customer 0007 - Opportunity Review | I39: 30 | J39: Customer lead, technical specialist, and salesperson | K39: Held | L39: The opportunity remains active with scope, stakeholders, and next commercial step confirmed. | M39: Met with Customer 0007 regarding opportunity review. The opportunity remains active with scope, stakeholders, and next commercial step confirmed. Customer context: existing managed-service account. Critical finding: None identified. Next step is owned by SP009. | N39: FALSE | O39: None | P39: None identified | Q39: Schedule technical workshop | R39: SP009 | S39: 45703 | T39: Complete | U39: 45703
A40: MTG00039 | B40: 45700 | C40: SP007 | D40: CUST0063 | F40: New Customer | G40: Account Health Check | H40: Customer 0063 - Account Health Check | I40: 45 | J40: Customer sponsor and salesperson | K40: Held | L40: Account health was reviewed across adoption, value, support, and renewal readiness. | M40: Met with Customer 0063 regarding account health check. Account health was reviewed across adoption, value, support, and renewal readiness. Customer context: new customer prospect. Critical finding: None identified. Next step is owned by SP007. | N40: FALSE | O40: None | P40: None identified | Q40: Escalate to service leadership | R40: SP007 | S40: 45719 | T40: In Progress | U40: 45719
A41: MTG00040 | B41: 45700 | C41: SP009 | D41: CUST0074 | E41: OPP0243 | F41: Existing Customer | G41: Opportunity Review | H41: Customer 0074 - Opportunity Review | I41: 60 | J41: Customer lead, technical specialist, and salesperson | K41: Held | L41: The opportunity remains active with scope, stakeholders, and next commercial step confirmed. | M41: Met with Customer 0074 regarding opportunity review. The opportunity remains active with scope, stakeholders, and next commercial step confirmed. Customer context: existing managed-service account. Critical finding: None identified. Next step is owned by SP009. | N41: FALSE | O41: None | P41: None identified | Q41: Schedule technical workshop | R41: SP009 | S41: 45715 | T41: Complete | U41: 45715
A42: MTG00041 | B42: 45701 | C42: SP003 | D42: CUST0062 | F42: New Customer | G42: Account Health Check | H42: Customer 0062 - Account Health Check | I42: 45 | J42: Customer lead, technical specialist, and salesperson | K42: Held | L42: Account health was reviewed across adoption, value, support, and renewal readiness. | M42: Met with Customer 0062 regarding account health check. Account health was reviewed across adoption, value, support, and renewal readiness. Customer context: new customer prospect. Critical finding: None identified. Next step is owned by SP003. | N42: FALSE | O42: None | P42: None identified | Q42: Update account action plan | R42: SP003 | S42: 45707 | T42: Complete | U42: 45707
A43: MTG00042 | B43: 45701 | C43: SP005 | D43: CUST0106 | E43: OPP0125 | F43: Existing Customer | G43: Opportunity Review | H43: Customer 0106 - Opportunity Review | I43: 30 | J43: Customer lead, technical specialist, and salesperson | K43: Held | L43: The opportunity remains active with scope, stakeholders, and next commercial step confirmed. | M43: Met with Customer 0106 regarding opportunity review. The opportunity remains active with scope, stakeholders, and next commercial step confirmed. Customer context: existing managed-service account. Critical finding: Procurement requested revised commercial terms. Next step is owned by SP005. | N43: TRUE | O43: Medium | P43: Procurement requested revised commercial terms | Q43: Confirm commercial response | R43: SP005 | S43: 45718 | T43: Complete | U43: 45718
A44: MTG00043 | B44: 45702 | C44: SP002 | D44: CUST0092 | F44: Existing Customer | G44: Renewal Planning | H44: Customer 0092 - Renewal Planning | I44: 45 | J44: Customer lead, technical specialist, and salesperson | K44: Held | L44: Renewal scope, decision process, and value evidence were reviewed with the customer. | M44: Met with Customer 0092 regarding renewal planning. Renewal scope, decision process, and value evidence were reviewed with the customer. Customer context: existing managed-service account. Critical finding: None identified. Next step is owned by SP002. | N44: FALSE | O44: None | P44: None identified | Q44: Send written follow-up | R44: SP002 | S44: 45718 | T44: Complete | U44: 45718
A45: MTG00044 | B45: 45705 | C45: SP010 | D45: CUST0025 | E45: OPP0146 | F45: New Customer | G45: Account Health Check | H45: Customer 0025 - Account Health Check | I45: 60 | J45: Customer lead and salesperson | K45: Held | L45: Account health was reviewed across adoption, value, support, and renewal readiness. | M45: Met with Customer 0025 regarding account health check. Account health was reviewed across adoption, value, support, and renewal readiness. Customer context: new customer prospect. Critical finding: None identified. Next step is owned by SP010. | N45: FALSE | O45: None | P45: None identified | Q45: Send written follow-up | R45: SP010 | S45: 45713 | T45: In Progress | U45: 45713
A46: MTG00045 | B46: 45705 | C46: SP008 | D46: CUST0035 | F46: Existing Customer | G46: Regular Account Review | H46: Customer 0035 - Regular Account Review | I46: 45 | J46: Customer lead and salesperson | K46: Held | L46: Service performance and planned business changes were reviewed with the customer. | M46: Met with Customer 0035 regarding regular account review. Service performance and planned business changes were reviewed with the customer. Customer context: existing managed-service account. Critical finding: None identified. Next step is owned by SP008. | N46: FALSE | O46: None | P46: None identified | Q46: Send written follow-up | R46: SP008 | S46: 45707 | T46: In Progress | U46: 45707
A47: MTG00046 | B47: 45706 | C47: SP002 | D47: CUST0050 | F47: Existing Customer | G47: Support Escalation | H47: Customer 0050 - Support Escalation | I47: 45 | J47: Customer sponsor and salesperson | K47: Held | L47: The escalation was reviewed with clear technical ownership and a customer update cadence. | M47: Met with Customer 0050 regarding support escalation. The escalation was reviewed with clear technical ownership and a customer update cadence. Customer context: existing managed-service account. Critical finding: None identified. Next step is owned by SP002. | N47: FALSE | O47: None | P47: None identified | Q47: Schedule technical workshop | R47: SP002 | S47: 45708 | T47: Complete | U47: 45708
A48: MTG00047 | B48: 45706 | C48: SP006 | D48: CUST0025 | F48: New Customer | G48: Account Health Check | H48: Customer 0025 - Account Health Check | I48: 60 | J48: Customer lead, technical specialist, and salesperson | K48: Held | L48: Account health was reviewed across adoption, value, support, and renewal readiness. | M48: Met with Customer 0025 regarding account health check. Account health was reviewed across adoption, value, support, and renewal readiness. Customer context: new customer prospect. Critical finding: None identified. Next step is owned by SP006. | N48: FALSE | O48: None | P48: None identified | Q48: Schedule technical workshop | R48: SP006 | S48: 45710 | T48: Complete | U48: 45710
A49: MTG00048 | B49: 45707 | C49: SP001 | D49: CUST0069 | F49: New Customer | G49: Account Health Check | H49: Customer 0069 - Account Health Check | I49: 60 | J49: Customer lead and salesperson | K49: Held | L49: Account health was reviewed across adoption, value, support, and renewal readiness. | M49: Met with Customer 0069 regarding account health check. Account health was reviewed across adoption, value, support, and renewal readiness. Customer context: new customer prospect. Critical finding: None identified. Next step is owned by SP001. | N49: FALSE | O49: None | P49: None identified | Q49: Confirm commercial response | R49: SP001 | S49: 45720 | T49: Complete | U49: 45720
A50: MTG00049 | B50: 45707 | C50: SP006 | D50: CUST0115 | E50: OPP0366 | F50: Existing Customer | G50: Opportunity Review | H50: Customer 0115 - Opportunity Review | I50: 30 | J50: Customer lead, technical specialist, and salesperson | K50: Held | L50: The opportunity remains active with scope, stakeholders, and next commercial step confirmed. | M50: Met with Customer 0115 regarding opportunity review. The opportunity remains active with scope, stakeholders, and next commercial step confirmed. Customer context: existing managed-service account. Critical finding: None identified. Next step is owned by SP006. | N50: FALSE | O50: None | P50: None identified | Q50: Update account action plan | R50: SP006 | S50: 45713 | T50: Complete | U50: 45713
A51: MTG00050 | B51: 45708 | C51: SP001 | D51: CUST0095 | F51: Existing Customer | G51: Account Health Check | H51: Customer 0095 - Account Health Check | I51: 45 | J51: Customer sponsor and salesperson | K51: Held | L51: Account health was reviewed across adoption, value, support, and renewal readiness. | M51: Met with Customer 0095 regarding account health check. Account health was reviewed across adoption, value, support, and renewal readiness. Customer context: existing managed-service account. Critical finding: None identified. Next step is owned by SP001. | N51: FALSE | O51: None | P51: None identified | Q51: Confirm commercial response | R51: SP001 | S51: 45713 | T51: Complete | U51: 45713
A52: MTG00051 | B52: 45708 | C52: SP002 | D52: CUST0008 | F52: Existing Customer | G52: Account Health Check | H52: Customer 0008 - Account Health Check | I52: 45 | J52: Customer lead, technical specialist, and salesperson | K52: Held | L52: Account health was reviewed across adoption, value, support, and renewal readiness. | M52: Met with Customer 0008 regarding account health check. Account health was reviewed across adoption, value, support, and renewal readiness. Customer context: existing managed-service account. Critical finding: None identified. Next step is owned by SP002. | N52: FALSE | O52: None | P52: None identified | Q52: Update account action plan | R52: SP002 | S52: 45719 | T52: Open | U52: 45719
A53: MTG00052 | B53: 45709 | C53: SP002 | D53: CUST0040 | E53: OPP0039 | F53: Existing Customer | G53: Opportunity Review | H53: Customer 0040 - Opportunity Review | I53: 60 | J53: Customer sponsor and salesperson | K53: Held | L53: The opportunity remains active with scope, stakeholders, and next commercial step confirmed. | M53: Met with Customer 0040 regarding opportunity review. The opportunity remains active with scope, stakeholders, and next commercial step confirmed. Customer context: existing managed-service account. Critical finding: None identified. Next step is owned by SP002. | N53: FALSE | O53: None | P53: None identified | Q53: Confirm commercial response | R53: SP002 | S53: 45723 | T53: Open | U53: 45723
A54: MTG00053 | B54: 45712 | C54: SP009 | D54: CUST0083 | E54: OPP0202 | F54: Existing Customer | G54: Opportunity Review | H54: Customer 0083 - Opportunity Review | I54: 90 | J54: Customer lead, technical specialist, and salesperson | K54: Held | L54: The opportunity remains active with scope, stakeholders, and next commercial step confirmed. | M54: Met with Customer 0083 regarding opportunity review. The opportunity remains active with scope, stakeholders, and next commercial step confirmed. Customer context: existing managed-service account. Critical finding: None identified. Next step is owned by SP009. | N54: FALSE | O54: None | P54: None identified | Q54: Send written follow-up | R54: SP009 | S54: 45729 | T54: Complete | U54: 45729
A55: MTG00054 | B55: 45713 | C55: SP003 | D55: CUST0062 | F55: New Customer | G55: Support Escalation | H55: Customer 0062 - Support Escalation | I55: 60 | J55: Customer sponsor and salesperson | K55: Held | L55: The escalation was reviewed with clear technical ownership and a customer update cadence. | M55: Met with Customer 0062 regarding support escalation. The escalation was reviewed with clear technical ownership and a customer update cadence. Customer context: new customer prospect. Critical finding: Customer requested senior ownership of the escalation. Next step is owned by SP003. | N55: TRUE | O55: Medium | P55: Customer requested senior ownership of the escalation | Q55: Schedule technical workshop | R55: SP003 | S55: 45732 | T55: Open | U55: 45732
A56: MTG00055 | B56: 45714 | C56: SP009 | D56: CUST0072 | F56: Existing Customer | G56: Account Health Check | H56: Customer 0072 - Account Health Check | I56: 45 | J56: Customer lead, technical specialist, and salesperson | K56: Held | L56: Account health was reviewed across adoption, value, support, and renewal readiness. | M56: Met with Customer 0072 regarding account health check. Account health was reviewed across adoption, value, support, and renewal readiness. Customer context: existing managed-service account. Critical finding: None identified. Next step is owned by SP009. | N56: FALSE | O56: None | P56: None identified | Q56: Update account action plan | R56: SP009 | S56: 45716 | T56: Complete | U56: 45716
A57: MTG00056 | B57: 45714 | C57: SP010 | D57: CUST0049 | F57: Existing Customer | G57: Support Escalation | H57: Customer 0049 - Support Escalation | I57: 60 | J57: Customer sponsor and salesperson | K57: Held | L57: The escalation was reviewed with clear technical ownership and a customer update cadence. | M57: Met with Customer 0049 regarding support escalation. The escalation was reviewed with clear technical ownership and a customer update cadence. Customer context: existing managed-service account. Critical finding: None identified. Next step is owned by SP010. | N57: FALSE | O57: None | P57: None identified | Q57: Send written follow-up | R57: SP010 | S57: 45730 | T57: Complete | U57: 45730
A58: MTG00057 | B58: 45715 | C58: SP007 | D58: CUST0072 | F58: Existing Customer | G58: Regular Account Review | H58: Customer 0072 - Regular Account Review | I58: 45 | J58: Customer sponsor and salesperson | K58: Held | L58: Service performance and planned business changes were reviewed with the customer. | M58: Met with Customer 0072 regarding regular account review. Service performance and planned business changes were reviewed with the customer. Customer context: existing managed-service account. Critical finding: None identified. Next step is owned by SP007. | N58: FALSE | O58: None | P58: None identified | Q58: Send written follow-up | R58: SP007 | S58: 45719 | T58: In Progress | U58: 45719
A59: MTG00058 | B59: 45715 | C59: SP002 | D59: CUST0034 | F59: Existing Customer | G59: Account Health Check | H59: Customer 0034 - Account Health Check | I59: 45 | J59: Customer lead, technical specialist, and salesperson | K59: Held | L59: Account health was reviewed across adoption, value, support, and renewal readiness. | M59: Met with Customer 0034 regarding account health check. Account health was reviewed across adoption, value, support, and renewal readiness. Customer context: existing managed-service account. Critical finding: None identified. Next step is owned by SP002. | N59: FALSE | O59: None | P59: None identified | Q59: Schedule technical workshop | R59: SP002 | S59: 45732 | T59: Complete | U59: 45732
A60: MTG00059 | B60: 45716 | C60: SP010 | D60: CUST0047 | E60: OPP0450 | F60: Existing Customer | G60: Opportunity Review | H60: Customer 0047 - Opportunity Review | I60: 45 | J60: Customer sponsor and salesperson | K60: Held | L60: The opportunity remains active with scope, stakeholders, and next commercial step confirmed. | M60: Met with Customer 0047 regarding opportunity review. The opportunity remains active with scope, stakeholders, and next commercial step confirmed. Customer context: existing managed-service account. Critical finding: None identified. Next step is owned by SP010. | N60: FALSE | O60: None | P60: None identified | Q60: Escalate to service leadership | R60: SP010 | S60: 45730 | T60: In Progress | U60: 45730
A61: MTG00060 | B61: 45716 | C61: SP007 | D61: CUST0001 | E61: OPP0081 | F61: New Customer | G61: New Business Discovery | H61: Customer 0001 - New Business Discovery | I61: 60 | J61: Customer sponsor and salesperson | K61: Held | L61: Customer confirmed the initial business outcomes and agreed to a qualification workshop. | M61: Met with Customer 0001 regarding new business discovery. Customer confirmed the initial business outcomes and agreed to a qualification workshop. Customer context: new customer prospect. Critical finding: None identified. Next step is owned by SP007. | N61: FALSE | O61: None | P61: None identified | Q61: Schedule technical workshop | R61: SP007 | S61: 45726 | T61: Open | U61: 45726
A62: MTG00061 | B62: 45719 | C62: SP008 | D62: CUST0071 | E62: OPP0378 | F62: Existing Customer | G62: Opportunity Review | H62: Customer 0071 - Opportunity Review | I62: 60 | J62: Customer sponsor and salesperson | K62: Held | L62: The opportunity remains active with scope, stakeholders, and next commercial step confirmed. | M62: Met with Customer 0071 regarding opportunity review. The opportunity remains active with scope, stakeholders, and next commercial step confirmed. Customer context: existing managed-service account. Critical finding: None identified. Next step is owned by SP008. | N62: FALSE | O62: None | P62: None identified | Q62: Send written follow-up | R62: SP008 | S62: 45740 | T62: Complete | U62: 45740
A63: MTG00062 | B63: 45719 | C63: SP006 | D63: CUST0117 | E63: OPP0044 | F63: Existing Customer | G63: Opportunity Review | H63: Customer 0117 - Opportunity Review | I63: 90 | J63: Customer sponsor and salesperson | K63: Held | L63: The opportunity remains active with scope, stakeholders, and next commercial step confirmed. | M63: Met with Customer 0117 regarding opportunity review. The opportunity remains active with scope, stakeholders, and next commercial step confirmed. Customer context: existing managed-service account. Critical finding: None identified. Next step is owned by SP006. | N63: FALSE | O63: None | P63: None identified | Q63: Update account action plan | R63: SP006 | S63: 45732 | T63: Complete | U63: 45732
A64: MTG00063 | B64: 45720 | C64: SP010 | D64: CUST0077 | F64: Existing Customer | G64: Renewal Planning | H64: Customer 0077 - Renewal Planning | I64: 45 | J64: Customer lead, technical specialist, and salesperson | K64: Held | L64: Renewal scope, decision process, and value evidence were reviewed with the customer. | M64: Met with Customer 0077 regarding renewal planning. Renewal scope, decision process, and value evidence were reviewed with the customer. Customer context: existing managed-service account. Critical finding: None identified. Next step is owned by SP010. | N64: FALSE | O64: None | P64: None identified | Q64: Confirm commercial response | R64: SP010 | S64: 45734 | T64: Open | U64: 45734
A65: MTG00064 | B65: 45720 | C65: SP007 | D65: CUST0112 | F65: Existing Customer | G65: Support Escalation | H65: Customer 0112 - Support Escalation | I65: 30 | J65: Customer lead, technical specialist, and salesperson | K65: Held | L65: The escalation was reviewed with clear technical ownership and a customer update cadence. | M65: Met with Customer 0112 regarding support escalation. The escalation was reviewed with clear technical ownership and a customer update cadence. Customer context: existing managed-service account. Critical finding: Customer requested senior ownership of the escalation. Next step is owned by SP007. | N65: TRUE | O65: High | P65: Customer requested senior ownership of the escalation | Q65: Escalate to service leadership | R65: SP007 | S65: 45738 | T65: Complete | U65: 45738
A66: MTG00065 | B66: 45720 | C66: SP001 | D66: CUST0047 | F66: Existing Customer | G66: Regular Account Review | H66: Customer 0047 - Regular Account Review | I66: 30 | J66: Customer sponsor and salesperson | K66: Held | L66: Service performance and planned business changes were reviewed with the customer. | M66: Met with Customer 0047 regarding regular account review. Service performance and planned business changes were reviewed with the customer. Customer context: existing managed-service account. Critical finding: None identified. Next step is owned by SP001. | N66: FALSE | O66: None | P66: None identified | Q66: Send written follow-up | R66: SP001 | S66: 45727 | T66: Complete | U66: 45727
A67: MTG00066 | B67: 45720 | C67: SP009 | D67: CUST0112 | F67: Existing Customer | G67: Renewal Planning | H67: Customer 0112 - Renewal Planning | I67: 60 | J67: Customer lead, technical specialist, and salesperson | K67: Held | L67: Renewal scope, decision process, and value evidence were reviewed with the customer. | M67: Met with Customer 0112 regarding renewal planning. Renewal scope, decision process, and value evidence were reviewed with the customer. Customer context: existing managed-service account. Critical finding: Renewal decision is blocked by unresolved service concerns. Next step is owned by SP009. | N67: TRUE | O67: High | P67: Renewal decision is blocked by unresolved service concerns | Q67: Escalate to service leadership | R67: SP009 | S67: 45727 | T67: In Progress | U67: 45727
A68: MTG00067 | B68: 45721 | C68: SP002 | D68: CUST0099 | E68: OPP0114 | F68: Existing Customer | G68: Support Escalation | H68: Customer 0099 - Support Escalation | I68: 45 | J68: Customer lead, technical specialist, and salesperson | K68: Held | L68: The escalation was reviewed with clear technical ownership and a customer update cadence. | M68: Met with Customer 0099 regarding support escalation. The escalation was reviewed with clear technical ownership and a customer update cadence. Customer context: existing managed-service account. Critical finding: None identified. Next step is owned by SP002. | N68: FALSE | O68: None | P68: None identified | Q68: Send written follow-up | R68: SP002 | S68: 45731 | T68: Complete | U68: 45731
A69: MTG00068 | B69: 45721 | C69: SP010 | D69: CUST0087 | E69: OPP0340 | F69: Existing Customer | G69: Opportunity Review | H69: Customer 0087 - Opportunity Review | I69: 45 | J69: Customer lead, technical specialist, and salesperson | K69: Held | L69: The opportunity remains active with scope, stakeholders, and next commercial step confirmed. | M69: Met with Customer 0087 regarding opportunity review. The opportunity remains active with scope, stakeholders, and next commercial step confirmed. Customer context: existing managed-service account. Critical finding: Competitor is active in the final evaluation. Next step is owned by SP010. | N69: TRUE | O69: High | P69: Competitor is active in the final evaluation | Q69: Update account action plan | R69: SP010 | S69: 45723 | T69: Open | U69: 45723
A70: MTG00069 | B70: 45721 | C70: SP005 | D70: CUST0116 | F70: New Customer | G70: Account Health Check | H70: Customer 0116 - Account Health Check | I70: 60 | J70: Customer lead, technical specialist, and salesperson | K70: Held | L70: Account health was reviewed across adoption, value, support, and renewal readiness. | M70: Met with Customer 0116 regarding account health check. Account health was reviewed across adoption, value, support, and renewal readiness. Customer context: new customer prospect. Critical finding: None identified. Next step is owned by SP005. | N70: FALSE | O70: None | P70: None identified | Q70: Send written follow-up | R70: SP005 | S70: 45736 | T70: Complete | U70: 45736
A71: MTG00070 | B71: 45723 | C71: SP004 | D71: CUST0073 | E71: OPP0364 | F71: New Customer | G71: New Business Discovery | H71: Customer 0073 - New Business Discovery | I71: 60 | J71: Customer lead and salesperson | K71: Held | L71: Customer confirmed the initial business outcomes and agreed to a qualification workshop. | M71: Met with Customer 0073 regarding new business discovery. Customer confirmed the initial business outcomes and agreed to a qualification workshop. Customer context: new customer prospect. Critical finding: None identified. Next step is owned by SP004. | N71: FALSE | O71: None | P71: None identified | Q71: Confirm commercial response | R71: SP004 | S71: 45725 | T71: In Progress | U71: 45725
A72: MTG00071 | B72: 45723 | C72: SP006 | D72: CUST0082 | F72: Existing Customer | G72: Regular Account Review | H72: Customer 0082 - Regular Account Review | I72: 90 | J72: Customer lead and salesperson | K72: Held | L72: Service performance and planned business changes were reviewed with the customer. | M72: Met with Customer 0082 regarding regular account review. Service performance and planned business changes were reviewed with the customer. Customer context: existing managed-service account. Critical finding: None identified. Next step is owned by SP006. | N72: FALSE | O72: None | P72: None identified | Q72: Escalate to service leadership | R72: SP006 | S72: 45728 | T72: Complete | U72: 45728
A73: MTG00072 | B73: 45727 | C73: SP002 | D73: CUST0021 | F73: Existing Customer | G73: Support Escalation | H73: Customer 0021 - Support Escalation | I73: 30 | J73: Customer lead and salesperson | K73: Held | L73: The escalation was reviewed with clear technical ownership and a customer update cadence. | M73: Met with Customer 0021 regarding support escalation. The escalation was reviewed with clear technical ownership and a customer update cadence. Customer context: existing managed-service account. Critical finding: None identified. Next step is owned by SP002. | N73: FALSE | O73: None | P73: None identified | Q73: Confirm commercial response | R73: SP002 | S73: 45733 | T73: Complete | U73: 45733
A74: MTG00073 | B74: 45728 | C74: SP005 | D74: CUST0044 | F74: Existing Customer | G74: Renewal Planning | H74: Customer 0044 - Renewal Planning | I74: 45 | J74: Customer sponsor and salesperson | K74: Held | L74: Renewal scope, decision process, and value evidence were reviewed with the customer. | M74: Met with Customer 0044 regarding renewal planning. Renewal scope, decision process, and value evidence were reviewed with the customer. Customer context: existing managed-service account. Critical finding: Customer requested a price and value review before renewal. Next step is owned by SP005. | N74: TRUE | O74: Medium | P74: Customer requested a price and value review before renewal | Q74: Send written follow-up | R74: SP005 | S74: 45746 | T74: Open | U74: 45746
A75: MTG00074 | B75: 45728 | C75: SP004 | D75: CUST0120 | E75: OPP0304 | F75: Existing Customer | G75: Opportunity Review | H75: Customer 0120 - Opportunity Review | I75: 45 | J75: Customer lead, technical specialist, and salesperson | K75: Held | L75: The opportunity remains active with scope, stakeholders, and next commercial step confirmed. | M75: Met with Customer 0120 regarding opportunity review. The opportunity remains active with scope, stakeholders, and next commercial step confirmed. Customer context: existing managed-service account. Critical finding: None identified. Next step is owned by SP004. | N75: FALSE | O75: None | P75: None identified | Q75: Update account action plan | R75: SP004 | S75: 45740 | T75: In Progress | U75: 45740
A76: MTG00075 | B76: 45729 | C76: SP008 | D76: CUST0052 | F76: Existing Customer | G76: Support Escalation | H76: Customer 0052 - Support Escalation | I76: 45 | J76: Customer lead, technical specialist, and salesperson | K76: Held | L76: The escalation was reviewed with clear technical ownership and a customer update cadence. | M76: Met with Customer 0052 regarding support escalation. The escalation was reviewed with clear technical ownership and a customer update cadence. Customer context: existing managed-service account. Critical finding: Customer requested senior ownership of the escalation. Next step is owned by SP008. | N76: TRUE | O76: High | P76: Customer requested senior ownership of the escalation | Q76: Confirm commercial response | R76: SP008 | S76: 45734 | T76: Complete | U76: 45734
